<?xml version="1.0" encoding="UTF-8"?>
<rdf:RDF xmlns:rdf="http://www.w3.org/1999/02/22-rdf-syntax-ns#" xmlns:lla="http://data.llgc.org.uk/lla/def#" xmlns:rdfs="http://www.w3.org/2000/01/rdf-schema#" xmlns:dcterms="http://purl.org/dc/terms/" xmlns:archiveshub="http://data.archiveshub.ac.uk/def" xmlns:foaf="http://xmlns.com/foaf/0.1/" xmlns:bio="http://purl.org/vocab/bio/0.1/" xmlns:dc="http://purl.org/dc/elements/1.1/" xmlns:void="http://rdfs.org/ns/void#" xmlns:owl="http://www.w3.org/2002/07/owl#">
  <rdf:Description rdf:about="http://data.llgc.org.uk/lla/id/ship/15772">
    <rdf:type rdf:resource="http://data.llgc.org.uk/lla/def#LogbookShip"/>
    <lla:hasHomePort xml:lang="en">Aberystwyth</lla:hasHomePort>
    <lla:officialnumber rdf:datatype="http://www.w3.org/2001/XMLSchema#string">15772</lla:officialnumber>
    <lla:mentionedIn rdf:resource="http://data.llgc.org.uk/lla/id/archivefile/477-33_vtls004957170"/>
    <rdfs:label xml:lang="en">Ruby</rdfs:label>
    <owl:sameAs rdf:resource="http://www.wikidata.org/entity/Q24027055"/>
    <lla:mentionedIn rdf:resource="http://data.llgc.org.uk/lla/id/logbook/15772-477331"/>
    <lla:mentionedIn rdf:resource="http://data.llgc.org.uk/lla/id/logbookentry/15772-477331-1"/>
    <lla:mentionedIn rdf:resource="http://data.llgc.org.uk/lla/id/logbookentry/15772-477331-2"/>
    <lla:mentionedIn rdf:resource="http://data.llgc.org.uk/lla/id/logbookentry/15772-477331-3"/>
    <lla:mentionedIn rdf:resource="http://data.llgc.org.uk/lla/id/logbookentry/15772-477331-4"/>
    <lla:mentionedIn rdf:resource="http://data.llgc.org.uk/lla/id/logbookentry/15772-477331-5"/>
    <lla:mentionedIn rdf:resource="http://data.llgc.org.uk/lla/id/logbookentry/15772-477331-6"/>
    <lla:mentionedIn rdf:resource="http://data.llgc.org.uk/lla/id/logbookentry/15772-477331-7"/>
    <lla:mentionedIn rdf:resource="http://data.llgc.org.uk/lla/id/logbookentry/15772-477331-8"/>
    <lla:mentionedIn rdf:resource="http://data.llgc.org.uk/lla/id/logbookentry/15772-477331-9"/>
    <lla:mentionedIn rdf:resource="http://data.llgc.org.uk/lla/id/logbookentry/15772-477331-10"/>
    <lla:mentionedIn rdf:resource="http://data.llgc.org.uk/lla/id/logbookentry/15772-477331-11"/>
    <lla:mentionedIn rdf:resource="http://data.llgc.org.uk/lla/id/logbookentry/15772-477331-12"/>
    <lla:mentionedIn rdf:resource="http://data.llgc.org.uk/lla/id/logbookentry/15772-477331-13"/>
    <lla:mentionedIn rdf:resource="http://data.llgc.org.uk/lla/id/logbook/15772-477332"/>
    <lla:mentionedIn rdf:resource="http://data.llgc.org.uk/lla/id/logbookentry/15772-477332-1"/>
    <lla:mentionedIn rdf:resource="http://data.llgc.org.uk/lla/id/logbookentry/15772-477332-2"/>
    <lla:mentionedIn rdf:resource="http://data.llgc.org.uk/lla/id/logbookentry/15772-477332-3"/>
    <lla:mentionedIn rdf:resource="http://data.llgc.org.uk/lla/id/logbookentry/15772-477332-4"/>
    <lla:mentionedIn rdf:resource="http://data.llgc.org.uk/lla/id/logbookentry/15772-477332-5"/>
    <lla:mentionedIn rdf:resource="http://data.llgc.org.uk/lla/id/logbookentry/15772-477332-6"/>
    <lla:mentionedIn rdf:resource="http://data.llgc.org.uk/lla/id/logbookentry/15772-477332-7"/>
    <lla:mentionedIn rdf:resource="http://data.llgc.org.uk/lla/id/logbookentry/15772-477332-8"/>
    <lla:mentionedIn rdf:resource="http://data.llgc.org.uk/lla/id/logbookentry/15772-477332-9"/>
    <lla:mentionedIn rdf:resource="http://data.llgc.org.uk/lla/id/logbookentry/15772-477332-10"/>
    <lla:mentionedIn rdf:resource="http://data.llgc.org.uk/lla/id/logbookentry/15772-477332-11"/>
    <lla:mentionedIn rdf:resource="http://data.llgc.org.uk/lla/id/logbookentry/15772-477332-12"/>
  </rdf:Description>
  <rdf:Description rdf:about="http://data.llgc.org.uk/lla/id/archivefile/477-33_vtls004957170">
    <rdf:type rdf:resource="http://data.llgc.org.uk/lla/def#File"/>
    <lla:vtlsNum rdf:datatype="http://www.w3.org/2001/XMLSchema#string">004957170</lla:vtlsNum>
    <dcterms:identifier rdf:datatype="http://www.w3.org/2001/XMLSchema#string">477-33</dcterms:identifier>
    <lla:sourceFile rdf:datatype="http://www.w3.org/2001/XMLSchema#string">File_477-33_vtls004957170.xls</lla:sourceFile>
    <lla:mentions rdf:resource="http://data.llgc.org.uk/lla/id/ship/15772"/>
    <dcterms:hasPart rdf:resource="http://data.llgc.org.uk/lla/id/logbook/15772-477331"/>
    <dcterms:hasPart rdf:resource="http://data.llgc.org.uk/lla/id/logbook/15772-477332"/>
  </rdf:Description>
  <rdf:Description rdf:about="http://data.llgc.org.uk/lla/id/logbook/15772-477331">
    <rdf:type rdf:resource="http://data.llgc.org.uk/lla/def#Logbook"/>
    <dcterms:identifier rdf:datatype="http://www.w3.org/2001/XMLSchema#string">477-33-1</dcterms:identifier>
    <dcterms:isPartOf rdf:resource="http://data.llgc.org.uk/lla/id/archivefile/477-33_vtls004957170"/>
    <dcterms:hasPart rdf:resource="http://data.llgc.org.uk/lla/id/logbookentry/15772-477331-1"/>
    <dcterms:hasPart rdf:resource="http://data.llgc.org.uk/lla/id/logbookentry/15772-477331-2"/>
    <dcterms:hasPart rdf:resource="http://data.llgc.org.uk/lla/id/logbookentry/15772-477331-3"/>
    <dcterms:hasPart rdf:resource="http://data.llgc.org.uk/lla/id/logbookentry/15772-477331-4"/>
    <dcterms:hasPart rdf:resource="http://data.llgc.org.uk/lla/id/logbookentry/15772-477331-5"/>
    <dcterms:hasPart rdf:resource="http://data.llgc.org.uk/lla/id/logbookentry/15772-477331-6"/>
    <dcterms:hasPart rdf:resource="http://data.llgc.org.uk/lla/id/logbookentry/15772-477331-7"/>
    <dcterms:hasPart rdf:resource="http://data.llgc.org.uk/lla/id/logbookentry/15772-477331-8"/>
    <dcterms:hasPart rdf:resource="http://data.llgc.org.uk/lla/id/logbookentry/15772-477331-9"/>
    <dcterms:hasPart rdf:resource="http://data.llgc.org.uk/lla/id/logbookentry/15772-477331-10"/>
    <dcterms:hasPart rdf:resource="http://data.llgc.org.uk/lla/id/logbookentry/15772-477331-11"/>
    <dcterms:hasPart rdf:resource="http://data.llgc.org.uk/lla/id/logbookentry/15772-477331-12"/>
    <dcterms:hasPart rdf:resource="http://data.llgc.org.uk/lla/id/logbookentry/15772-477331-13"/>
  </rdf:Description>
  <rdf:Description rdf:about="http://data.llgc.org.uk/lla/id/logbookentry/15772-477331-1">
    <rdf:type rdf:resource="http://data.llgc.org.uk/lla/def#LogbookEntry"/>
    <dcterms:isPartOf rdf:resource="http://data.llgc.org.uk/lla/id/logbook/15772-477331"/>
    <lla:calculatedAge rdf:datatype="http://www.w3.org/2001/XMLSchema#int">20</lla:calculatedAge>
    <lla:describesEvent rdf:resource="http://data.llgc.org.uk/lla/id/event/joining/15772-477331-1"/>
    <lla:reason xml:lang="en">Remains</lla:reason>
    <lla:mark rdf:datatype="http://www.w3.org/2001/XMLSchema#boolean">false</lla:mark>
  </rdf:Description>
  <rdf:Description rdf:about="http://data.llgc.org.uk/lla/id/mariner/15772-477331-1">
    <rdf:type rdf:resource="http://data.llgc.org.uk/lla/def#Mariner"/>
    <foaf:name>William Howard</foaf:name>
    <bio:Birth rdf:resource="http://data.llgc.org.uk/lla/id/event/birth/15772-477331-1"/>
  </rdf:Description>
  <rdf:Description rdf:about="http://data.llgc.org.uk/lla/id/event/birth/15772-477331-1">
    <rdf:type rdf:resource="http://purl.org/vocab/bio/0.1/Birth"/>
    <dc:date rdf:datatype="http://www.w3.org/2001/XMLSchema#dateTime">1881-01-01</dc:date>
    <bio:place xml:lang="en">Pal</bio:place>
    <bio:agent rdf:resource="http://data.llgc.org.uk/lla/id/mariner/15772-477331-1"/>
  </rdf:Description>
  <rdf:Description rdf:about="http://data.llgc.org.uk/lla/id/event/joining/15772-477331-1">
    <rdf:type rdf:resource="http://data.llgc.org.uk/lla/def#ShipJoiningEvent"/>
    <dc:date rdf:datatype="http://www.w3.org/2001/XMLSchema#dateTime">732</dc:date>
    <bio:place xml:lang="en">Dublin</bio:place>
    <lla:hasCapacity xml:lang="en">Master</lla:hasCapacity>
    <lla:involvesMariner rdf:resource="http://data.llgc.org.uk/lla/id/mariner/15772-477331-1"/>
    <lla:recordedIn rdf:resource="http://data.llgc.org.uk/lla/id/logbookentry/15772-477331-1"/>
    <lla:involvesShip rdf:resource="http://data.llgc.org.uk/lla/id/ship/15772"/>
  </rdf:Description>
  <rdf:Description rdf:about="http://data.llgc.org.uk/lla/id/logbookentry/15772-477331-2">
    <rdf:type rdf:resource="http://data.llgc.org.uk/lla/def#LogbookEntry"/>
    <dcterms:isPartOf rdf:resource="http://data.llgc.org.uk/lla/id/logbook/15772-477331"/>
    <lla:calculatedAge rdf:datatype="http://www.w3.org/2001/XMLSchema#int">63</lla:calculatedAge>
    <lla:describesEvent rdf:resource="http://data.llgc.org.uk/lla/id/event/joining/15772-477331-2"/>
    <lla:describesEvent rdf:resource="http://data.llgc.org.uk/lla/id/event/leaving/15772-477331-2"/>
    <lla:reason xml:lang="en">Left</lla:reason>
    <lla:mark rdf:datatype="http://www.w3.org/2001/XMLSchema#boolean">false</lla:mark>
  </rdf:Description>
  <rdf:Description rdf:about="http://data.llgc.org.uk/lla/id/mariner/15772-477331-2">
    <rdf:type rdf:resource="http://data.llgc.org.uk/lla/def#Mariner"/>
    <foaf:name>John Matthews</foaf:name>
    <bio:Birth rdf:resource="http://data.llgc.org.uk/lla/id/event/birth/15772-477331-2"/>
  </rdf:Description>
  <rdf:Description rdf:about="http://data.llgc.org.uk/lla/id/event/birth/15772-477331-2">
    <rdf:type rdf:resource="http://purl.org/vocab/bio/0.1/Birth"/>
    <dc:date rdf:datatype="http://www.w3.org/2001/XMLSchema#dateTime">1838-01-01</dc:date>
    <bio:place xml:lang="en">Oreston</bio:place>
    <bio:agent rdf:resource="http://data.llgc.org.uk/lla/id/mariner/15772-477331-2"/>
  </rdf:Description>
  <rdf:Description rdf:about="http://data.llgc.org.uk/lla/id/event/joining/15772-477331-2">
    <rdf:type rdf:resource="http://data.llgc.org.uk/lla/def#ShipJoiningEvent"/>
    <dc:date rdf:datatype="http://www.w3.org/2001/XMLSchema#dateTime">732</dc:date>
    <bio:place xml:lang="en">Dublin</bio:place>
    <lla:hasCapacity xml:lang="en">Mate</lla:hasCapacity>
    <lla:involvesMariner rdf:resource="http://data.llgc.org.uk/lla/id/mariner/15772-477331-2"/>
    <lla:recordedIn rdf:resource="http://data.llgc.org.uk/lla/id/logbookentry/15772-477331-2"/>
    <lla:involvesShip rdf:resource="http://data.llgc.org.uk/lla/id/ship/15772"/>
  </rdf:Description>
  <rdf:Description rdf:about="http://data.llgc.org.uk/lla/id/event/leaving/15772-477331-2">
    <rdf:type rdf:resource="http://data.llgc.org.uk/lla/def#ShipLeavingEvent"/>
    <dc:date rdf:datatype="http://www.w3.org/2001/XMLSchema#dateTime">791</dc:date>
    <bio:place xml:lang="en">Looe</bio:place>
    <lla:involvesMariner rdf:resource="http://data.llgc.org.uk/lla/id/mariner/15772-477331-2"/>
    <lla:recordedIn rdf:resource="http://data.llgc.org.uk/lla/id/logbookentry/15772-477331-2"/>
    <lla:involvesShip rdf:resource="http://data.llgc.org.uk/lla/id/ship/15772"/>
  </rdf:Description>
  <rdf:Description rdf:about="http://data.llgc.org.uk/lla/id/logbookentry/15772-477331-3">
    <rdf:type rdf:resource="http://data.llgc.org.uk/lla/def#LogbookEntry"/>
    <dcterms:isPartOf rdf:resource="http://data.llgc.org.uk/lla/id/logbook/15772-477331"/>
    <lla:calculatedAge rdf:datatype="http://www.w3.org/2001/XMLSchema#int">21</lla:calculatedAge>
    <lla:describesEvent rdf:resource="http://data.llgc.org.uk/lla/id/event/joining/15772-477331-3"/>
    <lla:describesEvent rdf:resource="http://data.llgc.org.uk/lla/id/event/leaving/15772-477331-3"/>
    <lla:reason xml:lang="en">Left</lla:reason>
    <lla:mark rdf:datatype="http://www.w3.org/2001/XMLSchema#boolean">false</lla:mark>
  </rdf:Description>
  <rdf:Description rdf:about="http://data.llgc.org.uk/lla/id/mariner/15772-477331-3">
    <rdf:type rdf:resource="http://data.llgc.org.uk/lla/def#Mariner"/>
    <foaf:name>Arthur Barlow</foaf:name>
    <bio:Birth rdf:resource="http://data.llgc.org.uk/lla/id/event/birth/15772-477331-3"/>
  </rdf:Description>
  <rdf:Description rdf:about="http://data.llgc.org.uk/lla/id/event/birth/15772-477331-3">
    <rdf:type rdf:resource="http://purl.org/vocab/bio/0.1/Birth"/>
    <dc:date rdf:datatype="http://www.w3.org/2001/XMLSchema#dateTime">1880-01-01</dc:date>
    <bio:place xml:lang="en">Wicklow</bio:place>
    <bio:agent rdf:resource="http://data.llgc.org.uk/lla/id/mariner/15772-477331-3"/>
  </rdf:Description>
  <rdf:Description rdf:about="http://data.llgc.org.uk/lla/id/event/joining/15772-477331-3">
    <rdf:type rdf:resource="http://data.llgc.org.uk/lla/def#ShipJoiningEvent"/>
    <dc:date rdf:datatype="http://www.w3.org/2001/XMLSchema#dateTime">732</dc:date>
    <bio:place xml:lang="en">Dublin</bio:place>
    <lla:hasCapacity xml:lang="en">Able Seaman</lla:hasCapacity>
    <lla:involvesMariner rdf:resource="http://data.llgc.org.uk/lla/id/mariner/15772-477331-3"/>
    <lla:recordedIn rdf:resource="http://data.llgc.org.uk/lla/id/logbookentry/15772-477331-3"/>
    <lla:involvesShip rdf:resource="http://data.llgc.org.uk/lla/id/ship/15772"/>
  </rdf:Description>
  <rdf:Description rdf:about="http://data.llgc.org.uk/lla/id/event/leaving/15772-477331-3">
    <rdf:type rdf:resource="http://data.llgc.org.uk/lla/def#ShipLeavingEvent"/>
    <dc:date rdf:datatype="http://www.w3.org/2001/XMLSchema#dateTime">804</dc:date>
    <bio:place xml:lang="en">London</bio:place>
    <lla:involvesMariner rdf:resource="http://data.llgc.org.uk/lla/id/mariner/15772-477331-3"/>
    <lla:recordedIn rdf:resource="http://data.llgc.org.uk/lla/id/logbookentry/15772-477331-3"/>
    <lla:involvesShip rdf:resource="http://data.llgc.org.uk/lla/id/ship/15772"/>
  </rdf:Description>
  <rdf:Description rdf:about="http://data.llgc.org.uk/lla/id/logbookentry/15772-477331-4">
    <rdf:type rdf:resource="http://data.llgc.org.uk/lla/def#LogbookEntry"/>
    <dcterms:isPartOf rdf:resource="http://data.llgc.org.uk/lla/id/logbook/15772-477331"/>
    <lla:calculatedAge rdf:datatype="http://www.w3.org/2001/XMLSchema#int">23</lla:calculatedAge>
    <lla:describesEvent rdf:resource="http://data.llgc.org.uk/lla/id/event/joining/15772-477331-4"/>
    <lla:describesEvent rdf:resource="http://data.llgc.org.uk/lla/id/event/leaving/15772-477331-4"/>
    <lla:reason xml:lang="en">Left</lla:reason>
    <lla:mark rdf:datatype="http://www.w3.org/2001/XMLSchema#boolean">false</lla:mark>
  </rdf:Description>
  <rdf:Description rdf:about="http://data.llgc.org.uk/lla/id/mariner/15772-477331-4">
    <rdf:type rdf:resource="http://data.llgc.org.uk/lla/def#Mariner"/>
    <foaf:name>Benjamin Marsh</foaf:name>
    <bio:Birth rdf:resource="http://data.llgc.org.uk/lla/id/event/birth/15772-477331-4"/>
  </rdf:Description>
  <rdf:Description rdf:about="http://data.llgc.org.uk/lla/id/event/birth/15772-477331-4">
    <rdf:type rdf:resource="http://purl.org/vocab/bio/0.1/Birth"/>
    <dc:date rdf:datatype="http://www.w3.org/2001/XMLSchema#dateTime">1878-01-01</dc:date>
    <bio:place xml:lang="en">London</bio:place>
    <bio:agent rdf:resource="http://data.llgc.org.uk/lla/id/mariner/15772-477331-4"/>
  </rdf:Description>
  <rdf:Description rdf:about="http://data.llgc.org.uk/lla/id/event/joining/15772-477331-4">
    <rdf:type rdf:resource="http://data.llgc.org.uk/lla/def#ShipJoiningEvent"/>
    <dc:date rdf:datatype="http://www.w3.org/2001/XMLSchema#dateTime">732</dc:date>
    <bio:place xml:lang="en">Dublin</bio:place>
    <lla:hasCapacity xml:lang="en">Able Seaman</lla:hasCapacity>
    <lla:involvesMariner rdf:resource="http://data.llgc.org.uk/lla/id/mariner/15772-477331-4"/>
    <lla:recordedIn rdf:resource="http://data.llgc.org.uk/lla/id/logbookentry/15772-477331-4"/>
    <lla:involvesShip rdf:resource="http://data.llgc.org.uk/lla/id/ship/15772"/>
  </rdf:Description>
  <rdf:Description rdf:about="http://data.llgc.org.uk/lla/id/event/leaving/15772-477331-4">
    <rdf:type rdf:resource="http://data.llgc.org.uk/lla/def#ShipLeavingEvent"/>
    <dc:date rdf:datatype="http://www.w3.org/2001/XMLSchema#dateTime">804</dc:date>
    <bio:place xml:lang="en">London</bio:place>
    <lla:involvesMariner rdf:resource="http://data.llgc.org.uk/lla/id/mariner/15772-477331-4"/>
    <lla:recordedIn rdf:resource="http://data.llgc.org.uk/lla/id/logbookentry/15772-477331-4"/>
    <lla:involvesShip rdf:resource="http://data.llgc.org.uk/lla/id/ship/15772"/>
  </rdf:Description>
  <rdf:Description rdf:about="http://data.llgc.org.uk/lla/id/logbookentry/15772-477331-5">
    <rdf:type rdf:resource="http://data.llgc.org.uk/lla/def#LogbookEntry"/>
    <dcterms:isPartOf rdf:resource="http://data.llgc.org.uk/lla/id/logbook/15772-477331"/>
    <lla:calculatedAge rdf:datatype="http://www.w3.org/2001/XMLSchema#int">18</lla:calculatedAge>
    <lla:describesEvent rdf:resource="http://data.llgc.org.uk/lla/id/event/leaving/15772-477331-5-2"/>
    <lla:describesEvent rdf:resource="http://data.llgc.org.uk/lla/id/event/joining/15772-477331-5"/>
    <lla:describesEvent rdf:resource="http://data.llgc.org.uk/lla/id/event/leaving/15772-477331-5"/>
    <lla:reason xml:lang="en">Left</lla:reason>
    <lla:mark rdf:datatype="http://www.w3.org/2001/XMLSchema#boolean">false</lla:mark>
  </rdf:Description>
  <rdf:Description rdf:about="http://data.llgc.org.uk/lla/id/mariner/15772-477331-5">
    <rdf:type rdf:resource="http://data.llgc.org.uk/lla/def#Mariner"/>
    <foaf:name>John H Russell</foaf:name>
    <bio:Birth rdf:resource="http://data.llgc.org.uk/lla/id/event/birth/15772-477331-5"/>
  </rdf:Description>
  <rdf:Description rdf:about="http://data.llgc.org.uk/lla/id/event/birth/15772-477331-5">
    <rdf:type rdf:resource="http://purl.org/vocab/bio/0.1/Birth"/>
    <dc:date rdf:datatype="http://www.w3.org/2001/XMLSchema#dateTime">1884-01-01</dc:date>
    <bio:place xml:lang="en">Victoria (British Columbia)</bio:place>
    <bio:agent rdf:resource="http://data.llgc.org.uk/lla/id/mariner/15772-477331-5"/>
  </rdf:Description>
  <rdf:Description rdf:about="http://data.llgc.org.uk/lla/id/event/leaving/15772-477331-5-2">
    <rdf:type rdf:resource="http://data.llgc.org.uk/lla/def#ShipLeavingEvent"/>
    <dc:date rdf:datatype="http://www.w3.org/2001/XMLSchema#dateTime">1902</dc:date>
    <lla:involvesMariner rdf:resource="http://data.llgc.org.uk/lla/id/mariner/15772-477331-5"/>
    <lla:recordedIn rdf:resource="http://data.llgc.org.uk/lla/id/logbookentry/15772-477331-5"/>
    <lla:involvesShip rdf:resource="http://data.llgc.org.uk/lla/id/ship/15772-477331-5"/>
  </rdf:Description>
  <rdf:Description rdf:about="http://data.llgc.org.uk/lla/id/ship/15772-477331-5">
    <rdf:type rdf:resource="http://data.llgc.org.uk/lla/def#Ship"/>
    <lla:mentionedIn rdf:resource="http://data.llgc.org.uk/lla/id/archivefile/477-33_vtls004957170"/>
    <lla:mentionedIn rdf:resource="http://data.llgc.org.uk/lla/id/logbook/15772-477331"/>
    <lla:mentionedIn rdf:resource="http://data.llgc.org.uk/lla/id/logbookentry/15772-477331-5"/>
    <rdfs:label xml:lang="en">Juy P</rdfs:label>
  </rdf:Description>
  <rdf:Description rdf:about="http://data.llgc.org.uk/lla/id/event/joining/15772-477331-5">
    <rdf:type rdf:resource="http://data.llgc.org.uk/lla/def#ShipJoiningEvent"/>
    <dc:date rdf:datatype="http://www.w3.org/2001/XMLSchema#dateTime">805</dc:date>
    <bio:place xml:lang="en">London</bio:place>
    <lla:hasCapacity xml:lang="en">Able Seaman</lla:hasCapacity>
    <lla:involvesMariner rdf:resource="http://data.llgc.org.uk/lla/id/mariner/15772-477331-5"/>
    <lla:recordedIn rdf:resource="http://data.llgc.org.uk/lla/id/logbookentry/15772-477331-5"/>
    <lla:involvesShip rdf:resource="http://data.llgc.org.uk/lla/id/ship/15772"/>
    <lla:hasPreviousIndividualEvent rdf:resource="http://data.llgc.org.uk/lla/id/event/leaving/15772-477331-5-2"/>
  </rdf:Description>
  <rdf:Description rdf:about="http://data.llgc.org.uk/lla/id/event/leaving/15772-477331-5">
    <rdf:type rdf:resource="http://data.llgc.org.uk/lla/def#ShipLeavingEvent"/>
    <dc:date rdf:datatype="http://www.w3.org/2001/XMLSchema#dateTime">791</dc:date>
    <bio:place xml:lang="en">Looe</bio:place>
    <lla:involvesMariner rdf:resource="http://data.llgc.org.uk/lla/id/mariner/15772-477331-5"/>
    <lla:recordedIn rdf:resource="http://data.llgc.org.uk/lla/id/logbookentry/15772-477331-5"/>
    <lla:involvesShip rdf:resource="http://data.llgc.org.uk/lla/id/ship/15772"/>
  </rdf:Description>
  <rdf:Description rdf:about="http://data.llgc.org.uk/lla/id/logbookentry/15772-477331-6">
    <rdf:type rdf:resource="http://data.llgc.org.uk/lla/def#LogbookEntry"/>
    <dcterms:isPartOf rdf:resource="http://data.llgc.org.uk/lla/id/logbook/15772-477331"/>
    <lla:calculatedAge rdf:datatype="http://www.w3.org/2001/XMLSchema#int">22</lla:calculatedAge>
    <lla:describesEvent rdf:resource="http://data.llgc.org.uk/lla/id/event/leaving/15772-477331-6-2"/>
    <lla:describesEvent rdf:resource="http://data.llgc.org.uk/lla/id/event/joining/15772-477331-6"/>
    <lla:describesEvent rdf:resource="http://data.llgc.org.uk/lla/id/event/leaving/15772-477331-6"/>
    <lla:reason xml:lang="en">Left</lla:reason>
    <lla:mark rdf:datatype="http://www.w3.org/2001/XMLSchema#boolean">false</lla:mark>
  </rdf:Description>
  <rdf:Description rdf:about="http://data.llgc.org.uk/lla/id/mariner/15772-477331-6">
    <rdf:type rdf:resource="http://data.llgc.org.uk/lla/def#Mariner"/>
    <foaf:name>Frederick James Slanmar</foaf:name>
    <bio:Birth rdf:resource="http://data.llgc.org.uk/lla/id/event/birth/15772-477331-6"/>
  </rdf:Description>
  <rdf:Description rdf:about="http://data.llgc.org.uk/lla/id/event/birth/15772-477331-6">
    <rdf:type rdf:resource="http://purl.org/vocab/bio/0.1/Birth"/>
    <dc:date rdf:datatype="http://www.w3.org/2001/XMLSchema#dateTime">1880-01-01</dc:date>
    <bio:place xml:lang="en">London</bio:place>
    <bio:agent rdf:resource="http://data.llgc.org.uk/lla/id/mariner/15772-477331-6"/>
  </rdf:Description>
  <rdf:Description rdf:about="http://data.llgc.org.uk/lla/id/event/leaving/15772-477331-6-2">
    <rdf:type rdf:resource="http://data.llgc.org.uk/lla/def#ShipLeavingEvent"/>
    <dc:date rdf:datatype="http://www.w3.org/2001/XMLSchema#dateTime">1902</dc:date>
    <lla:involvesMariner rdf:resource="http://data.llgc.org.uk/lla/id/mariner/15772-477331-6"/>
    <lla:recordedIn rdf:resource="http://data.llgc.org.uk/lla/id/logbookentry/15772-477331-6"/>
    <lla:involvesShip rdf:resource="http://data.llgc.org.uk/lla/id/ship/15772-477331-6"/>
  </rdf:Description>
  <rdf:Description rdf:about="http://data.llgc.org.uk/lla/id/ship/15772-477331-6">
    <rdf:type rdf:resource="http://data.llgc.org.uk/lla/def#Ship"/>
    <lla:mentionedIn rdf:resource="http://data.llgc.org.uk/lla/id/archivefile/477-33_vtls004957170"/>
    <lla:mentionedIn rdf:resource="http://data.llgc.org.uk/lla/id/logbook/15772-477331"/>
    <lla:mentionedIn rdf:resource="http://data.llgc.org.uk/lla/id/logbookentry/15772-477331-6"/>
    <rdfs:label xml:lang="en">Bing Lo</rdfs:label>
  </rdf:Description>
  <rdf:Description rdf:about="http://data.llgc.org.uk/lla/id/event/joining/15772-477331-6">
    <rdf:type rdf:resource="http://data.llgc.org.uk/lla/def#ShipJoiningEvent"/>
    <dc:date rdf:datatype="http://www.w3.org/2001/XMLSchema#dateTime">809</dc:date>
    <bio:place xml:lang="en">London</bio:place>
    <lla:hasCapacity xml:lang="en">Able Seaman</lla:hasCapacity>
    <lla:involvesMariner rdf:resource="http://data.llgc.org.uk/lla/id/mariner/15772-477331-6"/>
    <lla:recordedIn rdf:resource="http://data.llgc.org.uk/lla/id/logbookentry/15772-477331-6"/>
    <lla:involvesShip rdf:resource="http://data.llgc.org.uk/lla/id/ship/15772"/>
    <lla:hasPreviousIndividualEvent rdf:resource="http://data.llgc.org.uk/lla/id/event/leaving/15772-477331-6-2"/>
  </rdf:Description>
  <rdf:Description rdf:about="http://data.llgc.org.uk/lla/id/event/leaving/15772-477331-6">
    <rdf:type rdf:resource="http://data.llgc.org.uk/lla/def#ShipLeavingEvent"/>
    <dc:date rdf:datatype="http://www.w3.org/2001/XMLSchema#dateTime">791</dc:date>
    <bio:place xml:lang="en">Looe</bio:place>
    <lla:involvesMariner rdf:resource="http://data.llgc.org.uk/lla/id/mariner/15772-477331-6"/>
    <lla:recordedIn rdf:resource="http://data.llgc.org.uk/lla/id/logbookentry/15772-477331-6"/>
    <lla:involvesShip rdf:resource="http://data.llgc.org.uk/lla/id/ship/15772"/>
  </rdf:Description>
  <rdf:Description rdf:about="http://data.llgc.org.uk/lla/id/logbookentry/15772-477331-7">
    <rdf:type rdf:resource="http://data.llgc.org.uk/lla/def#LogbookEntry"/>
    <dcterms:isPartOf rdf:resource="http://data.llgc.org.uk/lla/id/logbook/15772-477331"/>
    <lla:calculatedAge rdf:datatype="http://www.w3.org/2001/XMLSchema#int">27</lla:calculatedAge>
    <lla:describesEvent rdf:resource="http://data.llgc.org.uk/lla/id/event/leaving/15772-477331-7-2"/>
    <lla:describesEvent rdf:resource="http://data.llgc.org.uk/lla/id/event/joining/15772-477331-7"/>
    <lla:describesEvent rdf:resource="http://data.llgc.org.uk/lla/id/event/leaving/15772-477331-7"/>
    <lla:reason xml:lang="en">Left</lla:reason>
    <lla:mark rdf:datatype="http://www.w3.org/2001/XMLSchema#boolean">false</lla:mark>
  </rdf:Description>
  <rdf:Description rdf:about="http://data.llgc.org.uk/lla/id/mariner/15772-477331-7">
    <rdf:type rdf:resource="http://data.llgc.org.uk/lla/def#Mariner"/>
    <foaf:name>[R$$l Warks]</foaf:name>
    <bio:Birth rdf:resource="http://data.llgc.org.uk/lla/id/event/birth/15772-477331-7"/>
  </rdf:Description>
  <rdf:Description rdf:about="http://data.llgc.org.uk/lla/id/event/birth/15772-477331-7">
    <rdf:type rdf:resource="http://purl.org/vocab/bio/0.1/Birth"/>
    <dc:date rdf:datatype="http://www.w3.org/2001/XMLSchema#dateTime">1875-01-01</dc:date>
    <bio:place xml:lang="en">London</bio:place>
    <bio:agent rdf:resource="http://data.llgc.org.uk/lla/id/mariner/15772-477331-7"/>
  </rdf:Description>
  <rdf:Description rdf:about="http://data.llgc.org.uk/lla/id/event/leaving/15772-477331-7-2">
    <rdf:type rdf:resource="http://data.llgc.org.uk/lla/def#ShipLeavingEvent"/>
    <dc:date rdf:datatype="http://www.w3.org/2001/XMLSchema#dateTime">1902</dc:date>
    <lla:involvesMariner rdf:resource="http://data.llgc.org.uk/lla/id/mariner/15772-477331-7"/>
    <lla:recordedIn rdf:resource="http://data.llgc.org.uk/lla/id/logbookentry/15772-477331-7"/>
    <lla:involvesShip rdf:resource="http://data.llgc.org.uk/lla/id/ship/15772-477331-7"/>
  </rdf:Description>
  <rdf:Description rdf:about="http://data.llgc.org.uk/lla/id/ship/15772-477331-7">
    <rdf:type rdf:resource="http://data.llgc.org.uk/lla/def#Ship"/>
    <lla:mentionedIn rdf:resource="http://data.llgc.org.uk/lla/id/archivefile/477-33_vtls004957170"/>
    <lla:mentionedIn rdf:resource="http://data.llgc.org.uk/lla/id/logbook/15772-477331"/>
    <lla:mentionedIn rdf:resource="http://data.llgc.org.uk/lla/id/logbookentry/15772-477331-7"/>
    <rdfs:label xml:lang="en">Amy</rdfs:label>
  </rdf:Description>
  <rdf:Description rdf:about="http://data.llgc.org.uk/lla/id/event/joining/15772-477331-7">
    <rdf:type rdf:resource="http://data.llgc.org.uk/lla/def#ShipJoiningEvent"/>
    <dc:date rdf:datatype="http://www.w3.org/2001/XMLSchema#dateTime">837</dc:date>
    <bio:place xml:lang="en">Pal</bio:place>
    <lla:hasCapacity xml:lang="en">Able Seaman</lla:hasCapacity>
    <lla:involvesMariner rdf:resource="http://data.llgc.org.uk/lla/id/mariner/15772-477331-7"/>
    <lla:recordedIn rdf:resource="http://data.llgc.org.uk/lla/id/logbookentry/15772-477331-7"/>
    <lla:involvesShip rdf:resource="http://data.llgc.org.uk/lla/id/ship/15772"/>
    <lla:hasPreviousIndividualEvent rdf:resource="http://data.llgc.org.uk/lla/id/event/leaving/15772-477331-7-2"/>
  </rdf:Description>
  <rdf:Description rdf:about="http://data.llgc.org.uk/lla/id/event/leaving/15772-477331-7">
    <rdf:type rdf:resource="http://data.llgc.org.uk/lla/def#ShipLeavingEvent"/>
    <dc:date rdf:datatype="http://www.w3.org/2001/XMLSchema#dateTime">879</dc:date>
    <bio:place xml:lang="en">London</bio:place>
    <lla:involvesMariner rdf:resource="http://data.llgc.org.uk/lla/id/mariner/15772-477331-7"/>
    <lla:recordedIn rdf:resource="http://data.llgc.org.uk/lla/id/logbookentry/15772-477331-7"/>
    <lla:involvesShip rdf:resource="http://data.llgc.org.uk/lla/id/ship/15772"/>
  </rdf:Description>
  <rdf:Description rdf:about="http://data.llgc.org.uk/lla/id/logbookentry/15772-477331-8">
    <rdf:type rdf:resource="http://data.llgc.org.uk/lla/def#LogbookEntry"/>
    <dcterms:isPartOf rdf:resource="http://data.llgc.org.uk/lla/id/logbook/15772-477331"/>
    <lla:calculatedAge rdf:datatype="http://www.w3.org/2001/XMLSchema#int">27</lla:calculatedAge>
    <lla:describesEvent rdf:resource="http://data.llgc.org.uk/lla/id/event/leaving/15772-477331-8-2"/>
    <lla:describesEvent rdf:resource="http://data.llgc.org.uk/lla/id/event/joining/15772-477331-8"/>
    <lla:describesEvent rdf:resource="http://data.llgc.org.uk/lla/id/event/leaving/15772-477331-8"/>
    <lla:reason xml:lang="en">Left</lla:reason>
    <lla:mark rdf:datatype="http://www.w3.org/2001/XMLSchema#boolean">false</lla:mark>
  </rdf:Description>
  <rdf:Description rdf:about="http://data.llgc.org.uk/lla/id/mariner/15772-477331-8">
    <rdf:type rdf:resource="http://data.llgc.org.uk/lla/def#Mariner"/>
    <foaf:name>James Smith</foaf:name>
    <bio:Birth rdf:resource="http://data.llgc.org.uk/lla/id/event/birth/15772-477331-8"/>
  </rdf:Description>
  <rdf:Description rdf:about="http://data.llgc.org.uk/lla/id/event/birth/15772-477331-8">
    <rdf:type rdf:resource="http://purl.org/vocab/bio/0.1/Birth"/>
    <dc:date rdf:datatype="http://www.w3.org/2001/XMLSchema#dateTime">1875-01-01</dc:date>
    <bio:place xml:lang="en">Preston</bio:place>
    <bio:agent rdf:resource="http://data.llgc.org.uk/lla/id/mariner/15772-477331-8"/>
  </rdf:Description>
  <rdf:Description rdf:about="http://data.llgc.org.uk/lla/id/event/leaving/15772-477331-8-2">
    <rdf:type rdf:resource="http://data.llgc.org.uk/lla/def#ShipLeavingEvent"/>
    <dc:date rdf:datatype="http://www.w3.org/2001/XMLSchema#dateTime">1902</dc:date>
    <lla:involvesMariner rdf:resource="http://data.llgc.org.uk/lla/id/mariner/15772-477331-8"/>
    <lla:recordedIn rdf:resource="http://data.llgc.org.uk/lla/id/logbookentry/15772-477331-8"/>
    <lla:involvesShip rdf:resource="http://data.llgc.org.uk/lla/id/ship/15772-477331-8"/>
  </rdf:Description>
  <rdf:Description rdf:about="http://data.llgc.org.uk/lla/id/ship/15772-477331-8">
    <rdf:type rdf:resource="http://data.llgc.org.uk/lla/def#Ship"/>
    <lla:mentionedIn rdf:resource="http://data.llgc.org.uk/lla/id/archivefile/477-33_vtls004957170"/>
    <lla:mentionedIn rdf:resource="http://data.llgc.org.uk/lla/id/logbook/15772-477331"/>
    <lla:mentionedIn rdf:resource="http://data.llgc.org.uk/lla/id/logbookentry/15772-477331-8"/>
    <rdfs:label xml:lang="en">William Gilmore</rdfs:label>
  </rdf:Description>
  <rdf:Description rdf:about="http://data.llgc.org.uk/lla/id/event/joining/15772-477331-8">
    <rdf:type rdf:resource="http://data.llgc.org.uk/lla/def#ShipJoiningEvent"/>
    <dc:date rdf:datatype="http://www.w3.org/2001/XMLSchema#dateTime">836</dc:date>
    <bio:place xml:lang="en">Pal</bio:place>
    <lla:hasCapacity xml:lang="en">Able Seaman</lla:hasCapacity>
    <lla:involvesMariner rdf:resource="http://data.llgc.org.uk/lla/id/mariner/15772-477331-8"/>
    <lla:recordedIn rdf:resource="http://data.llgc.org.uk/lla/id/logbookentry/15772-477331-8"/>
    <lla:involvesShip rdf:resource="http://data.llgc.org.uk/lla/id/ship/15772"/>
    <lla:hasPreviousIndividualEvent rdf:resource="http://data.llgc.org.uk/lla/id/event/leaving/15772-477331-8-2"/>
  </rdf:Description>
  <rdf:Description rdf:about="http://data.llgc.org.uk/lla/id/event/leaving/15772-477331-8">
    <rdf:type rdf:resource="http://data.llgc.org.uk/lla/def#ShipLeavingEvent"/>
    <dc:date rdf:datatype="http://www.w3.org/2001/XMLSchema#dateTime">899</dc:date>
    <bio:place xml:lang="en">London</bio:place>
    <lla:involvesMariner rdf:resource="http://data.llgc.org.uk/lla/id/mariner/15772-477331-8"/>
    <lla:recordedIn rdf:resource="http://data.llgc.org.uk/lla/id/logbookentry/15772-477331-8"/>
    <lla:involvesShip rdf:resource="http://data.llgc.org.uk/lla/id/ship/15772"/>
  </rdf:Description>
  <rdf:Description rdf:about="http://data.llgc.org.uk/lla/id/logbookentry/15772-477331-9">
    <rdf:type rdf:resource="http://data.llgc.org.uk/lla/def#LogbookEntry"/>
    <dcterms:isPartOf rdf:resource="http://data.llgc.org.uk/lla/id/logbook/15772-477331"/>
    <lla:calculatedAge rdf:datatype="http://www.w3.org/2001/XMLSchema#int">18</lla:calculatedAge>
    <lla:describesEvent rdf:resource="http://data.llgc.org.uk/lla/id/event/leaving/15772-477331-9-2"/>
    <lla:describesEvent rdf:resource="http://data.llgc.org.uk/lla/id/event/joining/15772-477331-9"/>
    <lla:describesEvent rdf:resource="http://data.llgc.org.uk/lla/id/event/leaving/15772-477331-9"/>
    <lla:reason xml:lang="en">Left</lla:reason>
    <lla:mark rdf:datatype="http://www.w3.org/2001/XMLSchema#boolean">false</lla:mark>
  </rdf:Description>
  <rdf:Description rdf:about="http://data.llgc.org.uk/lla/id/mariner/15772-477331-9">
    <rdf:type rdf:resource="http://data.llgc.org.uk/lla/def#Mariner"/>
    <foaf:name>J Gifford</foaf:name>
    <bio:Birth rdf:resource="http://data.llgc.org.uk/lla/id/event/birth/15772-477331-9"/>
  </rdf:Description>
  <rdf:Description rdf:about="http://data.llgc.org.uk/lla/id/event/birth/15772-477331-9">
    <rdf:type rdf:resource="http://purl.org/vocab/bio/0.1/Birth"/>
    <dc:date rdf:datatype="http://www.w3.org/2001/XMLSchema#dateTime">1884-01-01</dc:date>
    <bio:place xml:lang="en">Glasgow</bio:place>
    <bio:agent rdf:resource="http://data.llgc.org.uk/lla/id/mariner/15772-477331-9"/>
  </rdf:Description>
  <rdf:Description rdf:about="http://data.llgc.org.uk/lla/id/event/leaving/15772-477331-9-2">
    <rdf:type rdf:resource="http://data.llgc.org.uk/lla/def#ShipLeavingEvent"/>
    <dc:date rdf:datatype="http://www.w3.org/2001/XMLSchema#dateTime">1902</dc:date>
    <lla:involvesMariner rdf:resource="http://data.llgc.org.uk/lla/id/mariner/15772-477331-9"/>
    <lla:recordedIn rdf:resource="http://data.llgc.org.uk/lla/id/logbookentry/15772-477331-9"/>
    <lla:involvesShip rdf:resource="http://data.llgc.org.uk/lla/id/ship/15772-477331-9"/>
  </rdf:Description>
  <rdf:Description rdf:about="http://data.llgc.org.uk/lla/id/ship/15772-477331-9">
    <rdf:type rdf:resource="http://data.llgc.org.uk/lla/def#Ship"/>
    <lla:mentionedIn rdf:resource="http://data.llgc.org.uk/lla/id/archivefile/477-33_vtls004957170"/>
    <lla:mentionedIn rdf:resource="http://data.llgc.org.uk/lla/id/logbook/15772-477331"/>
    <lla:mentionedIn rdf:resource="http://data.llgc.org.uk/lla/id/logbookentry/15772-477331-9"/>
    <rdfs:label xml:lang="en">Uganda</rdfs:label>
  </rdf:Description>
  <rdf:Description rdf:about="http://data.llgc.org.uk/lla/id/event/joining/15772-477331-9">
    <rdf:type rdf:resource="http://data.llgc.org.uk/lla/def#ShipJoiningEvent"/>
    <dc:date rdf:datatype="http://www.w3.org/2001/XMLSchema#dateTime">840</dc:date>
    <bio:place xml:lang="en">Pal</bio:place>
    <lla:hasCapacity xml:lang="en">Able Seaman</lla:hasCapacity>
    <lla:involvesMariner rdf:resource="http://data.llgc.org.uk/lla/id/mariner/15772-477331-9"/>
    <lla:recordedIn rdf:resource="http://data.llgc.org.uk/lla/id/logbookentry/15772-477331-9"/>
    <lla:involvesShip rdf:resource="http://data.llgc.org.uk/lla/id/ship/15772"/>
    <lla:hasPreviousIndividualEvent rdf:resource="http://data.llgc.org.uk/lla/id/event/leaving/15772-477331-9-2"/>
  </rdf:Description>
  <rdf:Description rdf:about="http://data.llgc.org.uk/lla/id/event/leaving/15772-477331-9">
    <rdf:type rdf:resource="http://data.llgc.org.uk/lla/def#ShipLeavingEvent"/>
    <dc:date rdf:datatype="http://www.w3.org/2001/XMLSchema#dateTime">899</dc:date>
    <bio:place xml:lang="en">London</bio:place>
    <lla:involvesMariner rdf:resource="http://data.llgc.org.uk/lla/id/mariner/15772-477331-9"/>
    <lla:recordedIn rdf:resource="http://data.llgc.org.uk/lla/id/logbookentry/15772-477331-9"/>
    <lla:involvesShip rdf:resource="http://data.llgc.org.uk/lla/id/ship/15772"/>
  </rdf:Description>
  <rdf:Description rdf:about="http://data.llgc.org.uk/lla/id/logbookentry/15772-477331-10">
    <rdf:type rdf:resource="http://data.llgc.org.uk/lla/def#LogbookEntry"/>
    <dcterms:isPartOf rdf:resource="http://data.llgc.org.uk/lla/id/logbook/15772-477331"/>
    <lla:calculatedAge rdf:datatype="http://www.w3.org/2001/XMLSchema#int">44</lla:calculatedAge>
    <lla:describesEvent rdf:resource="http://data.llgc.org.uk/lla/id/event/leaving/15772-477331-10-2"/>
    <lla:describesEvent rdf:resource="http://data.llgc.org.uk/lla/id/event/joining/15772-477331-10"/>
    <lla:reason xml:lang="en">Remains</lla:reason>
    <lla:mark rdf:datatype="http://www.w3.org/2001/XMLSchema#boolean">false</lla:mark>
  </rdf:Description>
  <rdf:Description rdf:about="http://data.llgc.org.uk/lla/id/mariner/15772-477331-10">
    <rdf:type rdf:resource="http://data.llgc.org.uk/lla/def#Mariner"/>
    <foaf:name>William Roberts</foaf:name>
    <bio:Birth rdf:resource="http://data.llgc.org.uk/lla/id/event/birth/15772-477331-10"/>
  </rdf:Description>
  <rdf:Description rdf:about="http://data.llgc.org.uk/lla/id/event/birth/15772-477331-10">
    <rdf:type rdf:resource="http://purl.org/vocab/bio/0.1/Birth"/>
    <dc:date rdf:datatype="http://www.w3.org/2001/XMLSchema#dateTime">1858-01-01</dc:date>
    <bio:place xml:lang="en">Newquay</bio:place>
    <bio:agent rdf:resource="http://data.llgc.org.uk/lla/id/mariner/15772-477331-10"/>
  </rdf:Description>
  <rdf:Description rdf:about="http://data.llgc.org.uk/lla/id/event/leaving/15772-477331-10-2">
    <rdf:type rdf:resource="http://data.llgc.org.uk/lla/def#ShipLeavingEvent"/>
    <dc:date rdf:datatype="http://www.w3.org/2001/XMLSchema#dateTime">1902</dc:date>
    <lla:involvesMariner rdf:resource="http://data.llgc.org.uk/lla/id/mariner/15772-477331-10"/>
    <lla:recordedIn rdf:resource="http://data.llgc.org.uk/lla/id/logbookentry/15772-477331-10"/>
    <lla:involvesShip rdf:resource="http://data.llgc.org.uk/lla/id/ship/15772-477331-10"/>
  </rdf:Description>
  <rdf:Description rdf:about="http://data.llgc.org.uk/lla/id/ship/15772-477331-10">
    <rdf:type rdf:resource="http://data.llgc.org.uk/lla/def#Ship"/>
    <lla:mentionedIn rdf:resource="http://data.llgc.org.uk/lla/id/archivefile/477-33_vtls004957170"/>
    <lla:mentionedIn rdf:resource="http://data.llgc.org.uk/lla/id/logbook/15772-477331"/>
    <lla:mentionedIn rdf:resource="http://data.llgc.org.uk/lla/id/logbookentry/15772-477331-10"/>
    <rdfs:label xml:lang="en">Lothian</rdfs:label>
  </rdf:Description>
  <rdf:Description rdf:about="http://data.llgc.org.uk/lla/id/event/joining/15772-477331-10">
    <rdf:type rdf:resource="http://data.llgc.org.uk/lla/def#ShipJoiningEvent"/>
    <dc:date rdf:datatype="http://www.w3.org/2001/XMLSchema#dateTime">862</dc:date>
    <bio:place xml:lang="en">London</bio:place>
    <lla:hasCapacity xml:lang="en">Able Seaman</lla:hasCapacity>
    <lla:involvesMariner rdf:resource="http://data.llgc.org.uk/lla/id/mariner/15772-477331-10"/>
    <lla:recordedIn rdf:resource="http://data.llgc.org.uk/lla/id/logbookentry/15772-477331-10"/>
    <lla:involvesShip rdf:resource="http://data.llgc.org.uk/lla/id/ship/15772"/>
    <lla:hasPreviousIndividualEvent rdf:resource="http://data.llgc.org.uk/lla/id/event/leaving/15772-477331-10-2"/>
  </rdf:Description>
  <rdf:Description rdf:about="http://data.llgc.org.uk/lla/id/logbookentry/15772-477331-11">
    <rdf:type rdf:resource="http://data.llgc.org.uk/lla/def#LogbookEntry"/>
    <dcterms:isPartOf rdf:resource="http://data.llgc.org.uk/lla/id/logbook/15772-477331"/>
    <lla:calculatedAge rdf:datatype="http://www.w3.org/2001/XMLSchema#int">20</lla:calculatedAge>
    <lla:describesEvent rdf:resource="http://data.llgc.org.uk/lla/id/event/leaving/15772-477331-11-2"/>
    <lla:describesEvent rdf:resource="http://data.llgc.org.uk/lla/id/event/joining/15772-477331-11"/>
    <lla:reason xml:lang="en">Remains</lla:reason>
    <lla:mark rdf:datatype="http://www.w3.org/2001/XMLSchema#boolean">false</lla:mark>
  </rdf:Description>
  <rdf:Description rdf:about="http://data.llgc.org.uk/lla/id/mariner/15772-477331-11">
    <rdf:type rdf:resource="http://data.llgc.org.uk/lla/def#Mariner"/>
    <foaf:name>William Collins</foaf:name>
    <bio:Birth rdf:resource="http://data.llgc.org.uk/lla/id/event/birth/15772-477331-11"/>
  </rdf:Description>
  <rdf:Description rdf:about="http://data.llgc.org.uk/lla/id/event/birth/15772-477331-11">
    <rdf:type rdf:resource="http://purl.org/vocab/bio/0.1/Birth"/>
    <dc:date rdf:datatype="http://www.w3.org/2001/XMLSchema#dateTime">1881-01-01</dc:date>
    <bio:place xml:lang="en">Ipswich</bio:place>
    <bio:agent rdf:resource="http://data.llgc.org.uk/lla/id/mariner/15772-477331-11"/>
  </rdf:Description>
  <rdf:Description rdf:about="http://data.llgc.org.uk/lla/id/event/leaving/15772-477331-11-2">
    <rdf:type rdf:resource="http://data.llgc.org.uk/lla/def#ShipLeavingEvent"/>
    <dc:date rdf:datatype="http://www.w3.org/2001/XMLSchema#dateTime">1901</dc:date>
    <lla:involvesMariner rdf:resource="http://data.llgc.org.uk/lla/id/mariner/15772-477331-11"/>
    <lla:recordedIn rdf:resource="http://data.llgc.org.uk/lla/id/logbookentry/15772-477331-11"/>
    <lla:involvesShip rdf:resource="http://data.llgc.org.uk/lla/id/ship/15772-477331-11"/>
  </rdf:Description>
  <rdf:Description rdf:about="http://data.llgc.org.uk/lla/id/ship/15772-477331-11">
    <rdf:type rdf:resource="http://data.llgc.org.uk/lla/def#Ship"/>
    <lla:mentionedIn rdf:resource="http://data.llgc.org.uk/lla/id/archivefile/477-33_vtls004957170"/>
    <lla:mentionedIn rdf:resource="http://data.llgc.org.uk/lla/id/logbook/15772-477331"/>
    <lla:mentionedIn rdf:resource="http://data.llgc.org.uk/lla/id/logbookentry/15772-477331-11"/>
    <rdfs:label xml:lang="en">Thistle</rdfs:label>
  </rdf:Description>
  <rdf:Description rdf:about="http://data.llgc.org.uk/lla/id/event/joining/15772-477331-11">
    <rdf:type rdf:resource="http://data.llgc.org.uk/lla/def#ShipJoiningEvent"/>
    <dc:date rdf:datatype="http://www.w3.org/2001/XMLSchema#dateTime">914</dc:date>
    <bio:place xml:lang="en">London</bio:place>
    <lla:hasCapacity xml:lang="en">Able Seaman</lla:hasCapacity>
    <lla:involvesMariner rdf:resource="http://data.llgc.org.uk/lla/id/mariner/15772-477331-11"/>
    <lla:recordedIn rdf:resource="http://data.llgc.org.uk/lla/id/logbookentry/15772-477331-11"/>
    <lla:involvesShip rdf:resource="http://data.llgc.org.uk/lla/id/ship/15772"/>
    <lla:hasPreviousIndividualEvent rdf:resource="http://data.llgc.org.uk/lla/id/event/leaving/15772-477331-11-2"/>
  </rdf:Description>
  <rdf:Description rdf:about="http://data.llgc.org.uk/lla/id/logbookentry/15772-477331-12">
    <rdf:type rdf:resource="http://data.llgc.org.uk/lla/def#LogbookEntry"/>
    <dcterms:isPartOf rdf:resource="http://data.llgc.org.uk/lla/id/logbook/15772-477331"/>
    <lla:calculatedAge rdf:datatype="http://www.w3.org/2001/XMLSchema#int">15</lla:calculatedAge>
    <lla:describesEvent rdf:resource="http://data.llgc.org.uk/lla/id/event/leaving/15772-477331-12-2"/>
    <lla:describesEvent rdf:resource="http://data.llgc.org.uk/lla/id/event/joining/15772-477331-12"/>
    <lla:reason xml:lang="en">Remains</lla:reason>
    <lla:mark rdf:datatype="http://www.w3.org/2001/XMLSchema#boolean">false</lla:mark>
  </rdf:Description>
  <rdf:Description rdf:about="http://data.llgc.org.uk/lla/id/mariner/15772-477331-12">
    <rdf:type rdf:resource="http://data.llgc.org.uk/lla/def#Mariner"/>
    <foaf:name>E Japper</foaf:name>
    <bio:Birth rdf:resource="http://data.llgc.org.uk/lla/id/event/birth/15772-477331-12"/>
  </rdf:Description>
  <rdf:Description rdf:about="http://data.llgc.org.uk/lla/id/event/birth/15772-477331-12">
    <rdf:type rdf:resource="http://purl.org/vocab/bio/0.1/Birth"/>
    <dc:date rdf:datatype="http://www.w3.org/2001/XMLSchema#dateTime">1887-01-01</dc:date>
    <bio:place xml:lang="en">Walsall</bio:place>
    <bio:agent rdf:resource="http://data.llgc.org.uk/lla/id/mariner/15772-477331-12"/>
  </rdf:Description>
  <rdf:Description rdf:about="http://data.llgc.org.uk/lla/id/event/leaving/15772-477331-12-2">
    <rdf:type rdf:resource="http://data.llgc.org.uk/lla/def#ShipLeavingEvent"/>
    <dc:date rdf:datatype="http://www.w3.org/2001/XMLSchema#dateTime">1902</dc:date>
    <lla:involvesMariner rdf:resource="http://data.llgc.org.uk/lla/id/mariner/15772-477331-12"/>
    <lla:recordedIn rdf:resource="http://data.llgc.org.uk/lla/id/logbookentry/15772-477331-12"/>
    <lla:involvesShip rdf:resource="http://data.llgc.org.uk/lla/id/ship/15772-477331-12"/>
  </rdf:Description>
  <rdf:Description rdf:about="http://data.llgc.org.uk/lla/id/ship/15772-477331-12">
    <rdf:type rdf:resource="http://data.llgc.org.uk/lla/def#Ship"/>
    <lla:mentionedIn rdf:resource="http://data.llgc.org.uk/lla/id/archivefile/477-33_vtls004957170"/>
    <lla:mentionedIn rdf:resource="http://data.llgc.org.uk/lla/id/logbook/15772-477331"/>
    <lla:mentionedIn rdf:resource="http://data.llgc.org.uk/lla/id/logbookentry/15772-477331-12"/>
    <rdfs:label xml:lang="en">Arethusa</rdfs:label>
  </rdf:Description>
  <rdf:Description rdf:about="http://data.llgc.org.uk/lla/id/event/joining/15772-477331-12">
    <rdf:type rdf:resource="http://data.llgc.org.uk/lla/def#ShipJoiningEvent"/>
    <dc:date rdf:datatype="http://www.w3.org/2001/XMLSchema#dateTime">914</dc:date>
    <bio:place xml:lang="en">London</bio:place>
    <lla:hasCapacity xml:lang="en">Boy</lla:hasCapacity>
    <lla:involvesMariner rdf:resource="http://data.llgc.org.uk/lla/id/mariner/15772-477331-12"/>
    <lla:recordedIn rdf:resource="http://data.llgc.org.uk/lla/id/logbookentry/15772-477331-12"/>
    <lla:involvesShip rdf:resource="http://data.llgc.org.uk/lla/id/ship/15772"/>
    <lla:hasPreviousIndividualEvent rdf:resource="http://data.llgc.org.uk/lla/id/event/leaving/15772-477331-12-2"/>
  </rdf:Description>
  <rdf:Description rdf:about="http://data.llgc.org.uk/lla/id/logbookentry/15772-477331-13">
    <rdf:type rdf:resource="http://data.llgc.org.uk/lla/def#LogbookEntry"/>
    <dcterms:isPartOf rdf:resource="http://data.llgc.org.uk/lla/id/logbook/15772-477331"/>
    <lla:calculatedAge rdf:datatype="http://www.w3.org/2001/XMLSchema#int">16</lla:calculatedAge>
    <lla:describesEvent rdf:resource="http://data.llgc.org.uk/lla/id/event/leaving/15772-477331-13-2"/>
    <lla:describesEvent rdf:resource="http://data.llgc.org.uk/lla/id/event/joining/15772-477331-13"/>
    <lla:reason xml:lang="en">Remains</lla:reason>
    <lla:mark rdf:datatype="http://www.w3.org/2001/XMLSchema#boolean">false</lla:mark>
  </rdf:Description>
  <rdf:Description rdf:about="http://data.llgc.org.uk/lla/id/mariner/15772-477331-13">
    <rdf:type rdf:resource="http://data.llgc.org.uk/lla/def#Mariner"/>
    <foaf:name>C Timmins</foaf:name>
    <bio:Birth rdf:resource="http://data.llgc.org.uk/lla/id/event/birth/15772-477331-13"/>
  </rdf:Description>
  <rdf:Description rdf:about="http://data.llgc.org.uk/lla/id/event/birth/15772-477331-13">
    <rdf:type rdf:resource="http://purl.org/vocab/bio/0.1/Birth"/>
    <dc:date rdf:datatype="http://www.w3.org/2001/XMLSchema#dateTime">1886-01-01</dc:date>
    <bio:place xml:lang="en">Ashford</bio:place>
    <bio:agent rdf:resource="http://data.llgc.org.uk/lla/id/mariner/15772-477331-13"/>
  </rdf:Description>
  <rdf:Description rdf:about="http://data.llgc.org.uk/lla/id/event/leaving/15772-477331-13-2">
    <rdf:type rdf:resource="http://data.llgc.org.uk/lla/def#ShipLeavingEvent"/>
    <dc:date rdf:datatype="http://www.w3.org/2001/XMLSchema#dateTime">1902</dc:date>
    <lla:involvesMariner rdf:resource="http://data.llgc.org.uk/lla/id/mariner/15772-477331-13"/>
    <lla:recordedIn rdf:resource="http://data.llgc.org.uk/lla/id/logbookentry/15772-477331-13"/>
    <lla:involvesShip rdf:resource="http://data.llgc.org.uk/lla/id/ship/15772-477331-13"/>
  </rdf:Description>
  <rdf:Description rdf:about="http://data.llgc.org.uk/lla/id/ship/15772-477331-13">
    <rdf:type rdf:resource="http://data.llgc.org.uk/lla/def#Ship"/>
    <lla:mentionedIn rdf:resource="http://data.llgc.org.uk/lla/id/archivefile/477-33_vtls004957170"/>
    <lla:mentionedIn rdf:resource="http://data.llgc.org.uk/lla/id/logbook/15772-477331"/>
    <lla:mentionedIn rdf:resource="http://data.llgc.org.uk/lla/id/logbookentry/15772-477331-13"/>
    <rdfs:label xml:lang="en">Arethusa</rdfs:label>
  </rdf:Description>
  <rdf:Description rdf:about="http://data.llgc.org.uk/lla/id/event/joining/15772-477331-13">
    <rdf:type rdf:resource="http://data.llgc.org.uk/lla/def#ShipJoiningEvent"/>
    <dc:date rdf:datatype="http://www.w3.org/2001/XMLSchema#dateTime">914</dc:date>
    <bio:place xml:lang="en">London</bio:place>
    <lla:hasCapacity xml:lang="en">Boy</lla:hasCapacity>
    <lla:involvesMariner rdf:resource="http://data.llgc.org.uk/lla/id/mariner/15772-477331-13"/>
    <lla:recordedIn rdf:resource="http://data.llgc.org.uk/lla/id/logbookentry/15772-477331-13"/>
    <lla:involvesShip rdf:resource="http://data.llgc.org.uk/lla/id/ship/15772"/>
    <lla:hasPreviousIndividualEvent rdf:resource="http://data.llgc.org.uk/lla/id/event/leaving/15772-477331-13-2"/>
  </rdf:Description>
  <rdf:Description rdf:about="http://data.llgc.org.uk/lla/id/logbook/15772-477332">
    <rdf:type rdf:resource="http://data.llgc.org.uk/lla/def#Logbook"/>
    <dcterms:identifier rdf:datatype="http://www.w3.org/2001/XMLSchema#string">477-33-2</dcterms:identifier>
    <dcterms:isPartOf rdf:resource="http://data.llgc.org.uk/lla/id/archivefile/477-33_vtls004957170"/>
    <dcterms:hasPart rdf:resource="http://data.llgc.org.uk/lla/id/logbookentry/15772-477332-1"/>
    <dcterms:hasPart rdf:resource="http://data.llgc.org.uk/lla/id/logbookentry/15772-477332-2"/>
    <dcterms:hasPart rdf:resource="http://data.llgc.org.uk/lla/id/logbookentry/15772-477332-3"/>
    <dcterms:hasPart rdf:resource="http://data.llgc.org.uk/lla/id/logbookentry/15772-477332-4"/>
    <dcterms:hasPart rdf:resource="http://data.llgc.org.uk/lla/id/logbookentry/15772-477332-5"/>
    <dcterms:hasPart rdf:resource="http://data.llgc.org.uk/lla/id/logbookentry/15772-477332-6"/>
    <dcterms:hasPart rdf:resource="http://data.llgc.org.uk/lla/id/logbookentry/15772-477332-7"/>
    <dcterms:hasPart rdf:resource="http://data.llgc.org.uk/lla/id/logbookentry/15772-477332-8"/>
    <dcterms:hasPart rdf:resource="http://data.llgc.org.uk/lla/id/logbookentry/15772-477332-9"/>
    <dcterms:hasPart rdf:resource="http://data.llgc.org.uk/lla/id/logbookentry/15772-477332-10"/>
    <dcterms:hasPart rdf:resource="http://data.llgc.org.uk/lla/id/logbookentry/15772-477332-11"/>
    <dcterms:hasPart rdf:resource="http://data.llgc.org.uk/lla/id/logbookentry/15772-477332-12"/>
  </rdf:Description>
  <rdf:Description rdf:about="http://data.llgc.org.uk/lla/id/logbookentry/15772-477332-1">
    <rdf:type rdf:resource="http://data.llgc.org.uk/lla/def#LogbookEntry"/>
    <dcterms:isPartOf rdf:resource="http://data.llgc.org.uk/lla/id/logbook/15772-477332"/>
    <lla:describesEvent rdf:resource="http://data.llgc.org.uk/lla/id/event/joining/15772-477332-1"/>
    <lla:describesEvent rdf:resource="http://data.llgc.org.uk/lla/id/event/leaving/15772-477332-1"/>
    <lla:reason xml:lang="en">Left</lla:reason>
    <lla:mark rdf:datatype="http://www.w3.org/2001/XMLSchema#boolean">false</lla:mark>
  </rdf:Description>
  <rdf:Description rdf:about="http://data.llgc.org.uk/lla/id/mariner/15772-477332-1">
    <rdf:type rdf:resource="http://data.llgc.org.uk/lla/def#Mariner"/>
    <foaf:name>William Howard</foaf:name>
    <bio:Birth rdf:resource="http://data.llgc.org.uk/lla/id/event/birth/15772-477332-1"/>
  </rdf:Description>
  <rdf:Description rdf:about="http://data.llgc.org.uk/lla/id/event/birth/15772-477332-1">
    <rdf:type rdf:resource="http://purl.org/vocab/bio/0.1/Birth"/>
    <bio:place xml:lang="en">Pal</bio:place>
    <bio:agent rdf:resource="http://data.llgc.org.uk/lla/id/mariner/15772-477332-1"/>
  </rdf:Description>
  <rdf:Description rdf:about="http://data.llgc.org.uk/lla/id/event/joining/15772-477332-1">
    <rdf:type rdf:resource="http://data.llgc.org.uk/lla/def#ShipJoiningEvent"/>
    <dc:date rdf:datatype="http://www.w3.org/2001/XMLSchema#dateTime">933</dc:date>
    <bio:place xml:lang="en">Lancaster</bio:place>
    <lla:hasCapacity xml:lang="en">Master</lla:hasCapacity>
    <lla:involvesMariner rdf:resource="http://data.llgc.org.uk/lla/id/mariner/15772-477332-1"/>
    <lla:recordedIn rdf:resource="http://data.llgc.org.uk/lla/id/logbookentry/15772-477332-1"/>
    <lla:involvesShip rdf:resource="http://data.llgc.org.uk/lla/id/ship/15772"/>
  </rdf:Description>
  <rdf:Description rdf:about="http://data.llgc.org.uk/lla/id/event/leaving/15772-477332-1">
    <rdf:type rdf:resource="http://data.llgc.org.uk/lla/def#ShipLeavingEvent"/>
    <dc:date rdf:datatype="http://www.w3.org/2001/XMLSchema#dateTime">1075</dc:date>
    <bio:place xml:lang="en">Folkestone</bio:place>
    <lla:involvesMariner rdf:resource="http://data.llgc.org.uk/lla/id/mariner/15772-477332-1"/>
    <lla:recordedIn rdf:resource="http://data.llgc.org.uk/lla/id/logbookentry/15772-477332-1"/>
    <lla:involvesShip rdf:resource="http://data.llgc.org.uk/lla/id/ship/15772"/>
  </rdf:Description>
  <rdf:Description rdf:about="http://data.llgc.org.uk/lla/id/logbookentry/15772-477332-2">
    <rdf:type rdf:resource="http://data.llgc.org.uk/lla/def#LogbookEntry"/>
    <dcterms:isPartOf rdf:resource="http://data.llgc.org.uk/lla/id/logbook/15772-477332"/>
    <lla:calculatedAge rdf:datatype="http://www.w3.org/2001/XMLSchema#int">22</lla:calculatedAge>
    <lla:describesEvent rdf:resource="http://data.llgc.org.uk/lla/id/event/leaving/15772-477332-2-2"/>
    <lla:describesEvent rdf:resource="http://data.llgc.org.uk/lla/id/event/joining/15772-477332-2"/>
    <lla:describesEvent rdf:resource="http://data.llgc.org.uk/lla/id/event/leaving/15772-477332-2"/>
    <lla:reason xml:lang="en">Discharged</lla:reason>
    <lla:mark rdf:datatype="http://www.w3.org/2001/XMLSchema#boolean">false</lla:mark>
  </rdf:Description>
  <rdf:Description rdf:about="http://data.llgc.org.uk/lla/id/mariner/15772-477332-2">
    <rdf:type rdf:resource="http://data.llgc.org.uk/lla/def#Mariner"/>
    <foaf:name>Robert Hogan</foaf:name>
    <bio:Birth rdf:resource="http://data.llgc.org.uk/lla/id/event/birth/15772-477332-2"/>
  </rdf:Description>
  <rdf:Description rdf:about="http://data.llgc.org.uk/lla/id/event/birth/15772-477332-2">
    <rdf:type rdf:resource="http://purl.org/vocab/bio/0.1/Birth"/>
    <dc:date rdf:datatype="http://www.w3.org/2001/XMLSchema#dateTime">1879-01-01</dc:date>
    <bio:place xml:lang="en">Wicklow</bio:place>
    <bio:agent rdf:resource="http://data.llgc.org.uk/lla/id/mariner/15772-477332-2"/>
  </rdf:Description>
  <rdf:Description rdf:about="http://data.llgc.org.uk/lla/id/event/leaving/15772-477332-2-2">
    <rdf:type rdf:resource="http://data.llgc.org.uk/lla/def#ShipLeavingEvent"/>
    <dc:date rdf:datatype="http://www.w3.org/2001/XMLSchema#dateTime">1901</dc:date>
    <lla:involvesMariner rdf:resource="http://data.llgc.org.uk/lla/id/mariner/15772-477332-2"/>
    <lla:recordedIn rdf:resource="http://data.llgc.org.uk/lla/id/logbookentry/15772-477332-2"/>
    <lla:involvesShip rdf:resource="http://data.llgc.org.uk/lla/id/ship/15772-477332-2"/>
  </rdf:Description>
  <rdf:Description rdf:about="http://data.llgc.org.uk/lla/id/ship/15772-477332-2">
    <rdf:type rdf:resource="http://data.llgc.org.uk/lla/def#Ship"/>
    <lla:mentionedIn rdf:resource="http://data.llgc.org.uk/lla/id/archivefile/477-33_vtls004957170"/>
    <lla:mentionedIn rdf:resource="http://data.llgc.org.uk/lla/id/logbook/15772-477332"/>
    <lla:mentionedIn rdf:resource="http://data.llgc.org.uk/lla/id/logbookentry/15772-477332-2"/>
    <rdfs:label xml:lang="en">William &amp; Henry</rdfs:label>
  </rdf:Description>
  <rdf:Description rdf:about="http://data.llgc.org.uk/lla/id/event/joining/15772-477332-2">
    <rdf:type rdf:resource="http://data.llgc.org.uk/lla/def#ShipJoiningEvent"/>
    <dc:date rdf:datatype="http://www.w3.org/2001/XMLSchema#dateTime">944</dc:date>
    <bio:place xml:lang="en">Lancaster</bio:place>
    <lla:hasCapacity xml:lang="en">Mate</lla:hasCapacity>
    <lla:involvesMariner rdf:resource="http://data.llgc.org.uk/lla/id/mariner/15772-477332-2"/>
    <lla:recordedIn rdf:resource="http://data.llgc.org.uk/lla/id/logbookentry/15772-477332-2"/>
    <lla:involvesShip rdf:resource="http://data.llgc.org.uk/lla/id/ship/15772"/>
    <lla:hasPreviousIndividualEvent rdf:resource="http://data.llgc.org.uk/lla/id/event/leaving/15772-477332-2-2"/>
  </rdf:Description>
  <rdf:Description rdf:about="http://data.llgc.org.uk/lla/id/event/leaving/15772-477332-2">
    <rdf:type rdf:resource="http://data.llgc.org.uk/lla/def#ShipLeavingEvent"/>
    <dc:date rdf:datatype="http://www.w3.org/2001/XMLSchema#dateTime">990</dc:date>
    <bio:place xml:lang="en">Plymouth</bio:place>
    <lla:involvesMariner rdf:resource="http://data.llgc.org.uk/lla/id/mariner/15772-477332-2"/>
    <lla:recordedIn rdf:resource="http://data.llgc.org.uk/lla/id/logbookentry/15772-477332-2"/>
    <lla:involvesShip rdf:resource="http://data.llgc.org.uk/lla/id/ship/15772"/>
  </rdf:Description>
  <rdf:Description rdf:about="http://data.llgc.org.uk/lla/id/logbookentry/15772-477332-3">
    <rdf:type rdf:resource="http://data.llgc.org.uk/lla/def#LogbookEntry"/>
    <dcterms:isPartOf rdf:resource="http://data.llgc.org.uk/lla/id/logbook/15772-477332"/>
    <lla:calculatedAge rdf:datatype="http://www.w3.org/2001/XMLSchema#int">20</lla:calculatedAge>
    <lla:describesEvent rdf:resource="http://data.llgc.org.uk/lla/id/event/joining/15772-477332-3"/>
    <lla:describesEvent rdf:resource="http://data.llgc.org.uk/lla/id/event/leaving/15772-477332-3"/>
    <lla:reason xml:lang="en">Discharged</lla:reason>
    <lla:mark rdf:datatype="http://www.w3.org/2001/XMLSchema#boolean">false</lla:mark>
  </rdf:Description>
  <rdf:Description rdf:about="http://data.llgc.org.uk/lla/id/mariner/15772-477332-3">
    <rdf:type rdf:resource="http://data.llgc.org.uk/lla/def#Mariner"/>
    <foaf:name>William Collins</foaf:name>
    <bio:Birth rdf:resource="http://data.llgc.org.uk/lla/id/event/birth/15772-477332-3"/>
  </rdf:Description>
  <rdf:Description rdf:about="http://data.llgc.org.uk/lla/id/event/birth/15772-477332-3">
    <rdf:type rdf:resource="http://purl.org/vocab/bio/0.1/Birth"/>
    <dc:date rdf:datatype="http://www.w3.org/2001/XMLSchema#dateTime">1881-01-01</dc:date>
    <bio:place xml:lang="en">Ipswich</bio:place>
    <bio:agent rdf:resource="http://data.llgc.org.uk/lla/id/mariner/15772-477332-3"/>
  </rdf:Description>
  <rdf:Description rdf:about="http://data.llgc.org.uk/lla/id/event/joining/15772-477332-3">
    <rdf:type rdf:resource="http://data.llgc.org.uk/lla/def#ShipJoiningEvent"/>
    <dc:date rdf:datatype="http://www.w3.org/2001/XMLSchema#dateTime">933</dc:date>
    <bio:place xml:lang="en">Lancaster</bio:place>
    <lla:hasCapacity xml:lang="en">Able Seaman</lla:hasCapacity>
    <lla:involvesMariner rdf:resource="http://data.llgc.org.uk/lla/id/mariner/15772-477332-3"/>
    <lla:recordedIn rdf:resource="http://data.llgc.org.uk/lla/id/logbookentry/15772-477332-3"/>
    <lla:involvesShip rdf:resource="http://data.llgc.org.uk/lla/id/ship/15772"/>
  </rdf:Description>
  <rdf:Description rdf:about="http://data.llgc.org.uk/lla/id/event/leaving/15772-477332-3">
    <rdf:type rdf:resource="http://data.llgc.org.uk/lla/def#ShipLeavingEvent"/>
    <dc:date rdf:datatype="http://www.w3.org/2001/XMLSchema#dateTime">943</dc:date>
    <bio:place xml:lang="en">Lancaster</bio:place>
    <lla:involvesMariner rdf:resource="http://data.llgc.org.uk/lla/id/mariner/15772-477332-3"/>
    <lla:recordedIn rdf:resource="http://data.llgc.org.uk/lla/id/logbookentry/15772-477332-3"/>
    <lla:involvesShip rdf:resource="http://data.llgc.org.uk/lla/id/ship/15772"/>
  </rdf:Description>
  <rdf:Description rdf:about="http://data.llgc.org.uk/lla/id/logbookentry/15772-477332-4">
    <rdf:type rdf:resource="http://data.llgc.org.uk/lla/def#LogbookEntry"/>
    <dcterms:isPartOf rdf:resource="http://data.llgc.org.uk/lla/id/logbook/15772-477332"/>
    <lla:calculatedAge rdf:datatype="http://www.w3.org/2001/XMLSchema#int">14</lla:calculatedAge>
    <lla:describesEvent rdf:resource="http://data.llgc.org.uk/lla/id/event/joining/15772-477332-4"/>
    <lla:describesEvent rdf:resource="http://data.llgc.org.uk/lla/id/event/leaving/15772-477332-4"/>
    <lla:reason xml:lang="en">Discharged</lla:reason>
    <lla:mark rdf:datatype="http://www.w3.org/2001/XMLSchema#boolean">false</lla:mark>
  </rdf:Description>
  <rdf:Description rdf:about="http://data.llgc.org.uk/lla/id/mariner/15772-477332-4">
    <rdf:type rdf:resource="http://data.llgc.org.uk/lla/def#Mariner"/>
    <foaf:name>Edward Tapper</foaf:name>
    <bio:Birth rdf:resource="http://data.llgc.org.uk/lla/id/event/birth/15772-477332-4"/>
  </rdf:Description>
  <rdf:Description rdf:about="http://data.llgc.org.uk/lla/id/event/birth/15772-477332-4">
    <rdf:type rdf:resource="http://purl.org/vocab/bio/0.1/Birth"/>
    <dc:date rdf:datatype="http://www.w3.org/2001/XMLSchema#dateTime">1887-01-01</dc:date>
    <bio:place xml:lang="en">Walsall</bio:place>
    <bio:agent rdf:resource="http://data.llgc.org.uk/lla/id/mariner/15772-477332-4"/>
  </rdf:Description>
  <rdf:Description rdf:about="http://data.llgc.org.uk/lla/id/event/joining/15772-477332-4">
    <rdf:type rdf:resource="http://data.llgc.org.uk/lla/def#ShipJoiningEvent"/>
    <dc:date rdf:datatype="http://www.w3.org/2001/XMLSchema#dateTime">933</dc:date>
    <bio:place xml:lang="en">Lancaster</bio:place>
    <lla:hasCapacity xml:lang="en">Able Seaman</lla:hasCapacity>
    <lla:involvesMariner rdf:resource="http://data.llgc.org.uk/lla/id/mariner/15772-477332-4"/>
    <lla:recordedIn rdf:resource="http://data.llgc.org.uk/lla/id/logbookentry/15772-477332-4"/>
    <lla:involvesShip rdf:resource="http://data.llgc.org.uk/lla/id/ship/15772"/>
  </rdf:Description>
  <rdf:Description rdf:about="http://data.llgc.org.uk/lla/id/event/leaving/15772-477332-4">
    <rdf:type rdf:resource="http://data.llgc.org.uk/lla/def#ShipLeavingEvent"/>
    <dc:date rdf:datatype="http://www.w3.org/2001/XMLSchema#dateTime">1040</dc:date>
    <bio:place xml:lang="en">Plymouth</bio:place>
    <lla:involvesMariner rdf:resource="http://data.llgc.org.uk/lla/id/mariner/15772-477332-4"/>
    <lla:recordedIn rdf:resource="http://data.llgc.org.uk/lla/id/logbookentry/15772-477332-4"/>
    <lla:involvesShip rdf:resource="http://data.llgc.org.uk/lla/id/ship/15772"/>
  </rdf:Description>
  <rdf:Description rdf:about="http://data.llgc.org.uk/lla/id/logbookentry/15772-477332-5">
    <rdf:type rdf:resource="http://data.llgc.org.uk/lla/def#LogbookEntry"/>
    <dcterms:isPartOf rdf:resource="http://data.llgc.org.uk/lla/id/logbook/15772-477332"/>
    <lla:calculatedAge rdf:datatype="http://www.w3.org/2001/XMLSchema#int">16</lla:calculatedAge>
    <lla:describesEvent rdf:resource="http://data.llgc.org.uk/lla/id/event/joining/15772-477332-5"/>
    <lla:describesEvent rdf:resource="http://data.llgc.org.uk/lla/id/event/leaving/15772-477332-5"/>
    <lla:reason xml:lang="en">Discharged</lla:reason>
    <lla:mark rdf:datatype="http://www.w3.org/2001/XMLSchema#boolean">false</lla:mark>
  </rdf:Description>
  <rdf:Description rdf:about="http://data.llgc.org.uk/lla/id/mariner/15772-477332-5">
    <rdf:type rdf:resource="http://data.llgc.org.uk/lla/def#Mariner"/>
    <foaf:name>Charles Timmins</foaf:name>
    <bio:Birth rdf:resource="http://data.llgc.org.uk/lla/id/event/birth/15772-477332-5"/>
  </rdf:Description>
  <rdf:Description rdf:about="http://data.llgc.org.uk/lla/id/event/birth/15772-477332-5">
    <rdf:type rdf:resource="http://purl.org/vocab/bio/0.1/Birth"/>
    <dc:date rdf:datatype="http://www.w3.org/2001/XMLSchema#dateTime">1886-01-01</dc:date>
    <bio:place xml:lang="en">Ashford</bio:place>
    <bio:agent rdf:resource="http://data.llgc.org.uk/lla/id/mariner/15772-477332-5"/>
  </rdf:Description>
  <rdf:Description rdf:about="http://data.llgc.org.uk/lla/id/event/joining/15772-477332-5">
    <rdf:type rdf:resource="http://data.llgc.org.uk/lla/def#ShipJoiningEvent"/>
    <dc:date rdf:datatype="http://www.w3.org/2001/XMLSchema#dateTime">933</dc:date>
    <bio:place xml:lang="en">Lancaster</bio:place>
    <lla:hasCapacity xml:lang="en">Boy</lla:hasCapacity>
    <lla:involvesMariner rdf:resource="http://data.llgc.org.uk/lla/id/mariner/15772-477332-5"/>
    <lla:recordedIn rdf:resource="http://data.llgc.org.uk/lla/id/logbookentry/15772-477332-5"/>
    <lla:involvesShip rdf:resource="http://data.llgc.org.uk/lla/id/ship/15772"/>
  </rdf:Description>
  <rdf:Description rdf:about="http://data.llgc.org.uk/lla/id/event/leaving/15772-477332-5">
    <rdf:type rdf:resource="http://data.llgc.org.uk/lla/def#ShipLeavingEvent"/>
    <dc:date rdf:datatype="http://www.w3.org/2001/XMLSchema#dateTime">1040</dc:date>
    <bio:place xml:lang="en">Plymouth</bio:place>
    <lla:involvesMariner rdf:resource="http://data.llgc.org.uk/lla/id/mariner/15772-477332-5"/>
    <lla:recordedIn rdf:resource="http://data.llgc.org.uk/lla/id/logbookentry/15772-477332-5"/>
    <lla:involvesShip rdf:resource="http://data.llgc.org.uk/lla/id/ship/15772"/>
  </rdf:Description>
  <rdf:Description rdf:about="http://data.llgc.org.uk/lla/id/logbookentry/15772-477332-6">
    <rdf:type rdf:resource="http://data.llgc.org.uk/lla/def#LogbookEntry"/>
    <dcterms:isPartOf rdf:resource="http://data.llgc.org.uk/lla/id/logbook/15772-477332"/>
    <lla:calculatedAge rdf:datatype="http://www.w3.org/2001/XMLSchema#int">25</lla:calculatedAge>
    <lla:describesEvent rdf:resource="http://data.llgc.org.uk/lla/id/event/leaving/15772-477332-6-2"/>
    <lla:describesEvent rdf:resource="http://data.llgc.org.uk/lla/id/event/joining/15772-477332-6"/>
    <lla:describesEvent rdf:resource="http://data.llgc.org.uk/lla/id/event/leaving/15772-477332-6"/>
    <lla:reason xml:lang="en">Discharged</lla:reason>
    <lla:mark rdf:datatype="http://www.w3.org/2001/XMLSchema#boolean">false</lla:mark>
  </rdf:Description>
  <rdf:Description rdf:about="http://data.llgc.org.uk/lla/id/mariner/15772-477332-6">
    <rdf:type rdf:resource="http://data.llgc.org.uk/lla/def#Mariner"/>
    <foaf:name>Michael Hogan</foaf:name>
    <bio:Birth rdf:resource="http://data.llgc.org.uk/lla/id/event/birth/15772-477332-6"/>
  </rdf:Description>
  <rdf:Description rdf:about="http://data.llgc.org.uk/lla/id/event/birth/15772-477332-6">
    <rdf:type rdf:resource="http://purl.org/vocab/bio/0.1/Birth"/>
    <dc:date rdf:datatype="http://www.w3.org/2001/XMLSchema#dateTime">1876-01-01</dc:date>
    <bio:place xml:lang="en">Wicklow</bio:place>
    <bio:agent rdf:resource="http://data.llgc.org.uk/lla/id/mariner/15772-477332-6"/>
  </rdf:Description>
  <rdf:Description rdf:about="http://data.llgc.org.uk/lla/id/event/leaving/15772-477332-6-2">
    <rdf:type rdf:resource="http://data.llgc.org.uk/lla/def#ShipLeavingEvent"/>
    <dc:date rdf:datatype="http://www.w3.org/2001/XMLSchema#dateTime">1901</dc:date>
    <lla:involvesMariner rdf:resource="http://data.llgc.org.uk/lla/id/mariner/15772-477332-6"/>
    <lla:recordedIn rdf:resource="http://data.llgc.org.uk/lla/id/logbookentry/15772-477332-6"/>
    <lla:involvesShip rdf:resource="http://data.llgc.org.uk/lla/id/ship/15772-477332-6"/>
  </rdf:Description>
  <rdf:Description rdf:about="http://data.llgc.org.uk/lla/id/ship/15772-477332-6">
    <rdf:type rdf:resource="http://data.llgc.org.uk/lla/def#Ship"/>
    <lla:mentionedIn rdf:resource="http://data.llgc.org.uk/lla/id/archivefile/477-33_vtls004957170"/>
    <lla:mentionedIn rdf:resource="http://data.llgc.org.uk/lla/id/logbook/15772-477332"/>
    <lla:mentionedIn rdf:resource="http://data.llgc.org.uk/lla/id/logbookentry/15772-477332-6"/>
    <rdfs:label xml:lang="en">Ocean Maid</rdfs:label>
  </rdf:Description>
  <rdf:Description rdf:about="http://data.llgc.org.uk/lla/id/event/joining/15772-477332-6">
    <rdf:type rdf:resource="http://data.llgc.org.uk/lla/def#ShipJoiningEvent"/>
    <dc:date rdf:datatype="http://www.w3.org/2001/XMLSchema#dateTime">944</dc:date>
    <bio:place xml:lang="en">Lancaster</bio:place>
    <lla:hasCapacity xml:lang="en">Able Seaman</lla:hasCapacity>
    <lla:involvesMariner rdf:resource="http://data.llgc.org.uk/lla/id/mariner/15772-477332-6"/>
    <lla:recordedIn rdf:resource="http://data.llgc.org.uk/lla/id/logbookentry/15772-477332-6"/>
    <lla:involvesShip rdf:resource="http://data.llgc.org.uk/lla/id/ship/15772"/>
    <lla:hasPreviousIndividualEvent rdf:resource="http://data.llgc.org.uk/lla/id/event/leaving/15772-477332-6-2"/>
  </rdf:Description>
  <rdf:Description rdf:about="http://data.llgc.org.uk/lla/id/event/leaving/15772-477332-6">
    <rdf:type rdf:resource="http://data.llgc.org.uk/lla/def#ShipLeavingEvent"/>
    <dc:date rdf:datatype="http://www.w3.org/2001/XMLSchema#dateTime">1025</dc:date>
    <bio:place xml:lang="en">Rochester</bio:place>
    <lla:involvesMariner rdf:resource="http://data.llgc.org.uk/lla/id/mariner/15772-477332-6"/>
    <lla:recordedIn rdf:resource="http://data.llgc.org.uk/lla/id/logbookentry/15772-477332-6"/>
    <lla:involvesShip rdf:resource="http://data.llgc.org.uk/lla/id/ship/15772"/>
  </rdf:Description>
  <rdf:Description rdf:about="http://data.llgc.org.uk/lla/id/logbookentry/15772-477332-7">
    <rdf:type rdf:resource="http://data.llgc.org.uk/lla/def#LogbookEntry"/>
    <dcterms:isPartOf rdf:resource="http://data.llgc.org.uk/lla/id/logbook/15772-477332"/>
    <lla:calculatedAge rdf:datatype="http://www.w3.org/2001/XMLSchema#int">56</lla:calculatedAge>
    <lla:describesEvent rdf:resource="http://data.llgc.org.uk/lla/id/event/leaving/15772-477332-7-2"/>
    <lla:describesEvent rdf:resource="http://data.llgc.org.uk/lla/id/event/joining/15772-477332-7"/>
    <lla:describesEvent rdf:resource="http://data.llgc.org.uk/lla/id/event/leaving/15772-477332-7"/>
    <lla:reason xml:lang="en">Discharged</lla:reason>
    <lla:mark rdf:datatype="http://www.w3.org/2001/XMLSchema#boolean">false</lla:mark>
  </rdf:Description>
  <rdf:Description rdf:about="http://data.llgc.org.uk/lla/id/mariner/15772-477332-7">
    <rdf:type rdf:resource="http://data.llgc.org.uk/lla/def#Mariner"/>
    <foaf:name>Peter John Masters</foaf:name>
    <bio:Birth rdf:resource="http://data.llgc.org.uk/lla/id/event/birth/15772-477332-7"/>
  </rdf:Description>
  <rdf:Description rdf:about="http://data.llgc.org.uk/lla/id/event/birth/15772-477332-7">
    <rdf:type rdf:resource="http://purl.org/vocab/bio/0.1/Birth"/>
    <dc:date rdf:datatype="http://www.w3.org/2001/XMLSchema#dateTime">1846-01-01</dc:date>
    <bio:place xml:lang="en">Oreston</bio:place>
    <bio:agent rdf:resource="http://data.llgc.org.uk/lla/id/mariner/15772-477332-7"/>
  </rdf:Description>
  <rdf:Description rdf:about="http://data.llgc.org.uk/lla/id/event/leaving/15772-477332-7-2">
    <rdf:type rdf:resource="http://data.llgc.org.uk/lla/def#ShipLeavingEvent"/>
    <dc:date rdf:datatype="http://www.w3.org/2001/XMLSchema#dateTime">1902</dc:date>
    <lla:involvesMariner rdf:resource="http://data.llgc.org.uk/lla/id/mariner/15772-477332-7"/>
    <lla:recordedIn rdf:resource="http://data.llgc.org.uk/lla/id/logbookentry/15772-477332-7"/>
    <lla:involvesShip rdf:resource="http://data.llgc.org.uk/lla/id/ship/15772-477332-7"/>
  </rdf:Description>
  <rdf:Description rdf:about="http://data.llgc.org.uk/lla/id/ship/15772-477332-7">
    <rdf:type rdf:resource="http://data.llgc.org.uk/lla/def#Ship"/>
    <lla:mentionedIn rdf:resource="http://data.llgc.org.uk/lla/id/archivefile/477-33_vtls004957170"/>
    <lla:mentionedIn rdf:resource="http://data.llgc.org.uk/lla/id/logbook/15772-477332"/>
    <lla:mentionedIn rdf:resource="http://data.llgc.org.uk/lla/id/logbookentry/15772-477332-7"/>
    <rdfs:label xml:lang="en">John W Pearn</rdfs:label>
  </rdf:Description>
  <rdf:Description rdf:about="http://data.llgc.org.uk/lla/id/event/joining/15772-477332-7">
    <rdf:type rdf:resource="http://data.llgc.org.uk/lla/def#ShipJoiningEvent"/>
    <dc:date rdf:datatype="http://www.w3.org/2001/XMLSchema#dateTime">991</dc:date>
    <bio:place xml:lang="en">Plymouth</bio:place>
    <lla:hasCapacity xml:lang="en">Mate</lla:hasCapacity>
    <lla:involvesMariner rdf:resource="http://data.llgc.org.uk/lla/id/mariner/15772-477332-7"/>
    <lla:recordedIn rdf:resource="http://data.llgc.org.uk/lla/id/logbookentry/15772-477332-7"/>
    <lla:involvesShip rdf:resource="http://data.llgc.org.uk/lla/id/ship/15772"/>
    <lla:hasPreviousIndividualEvent rdf:resource="http://data.llgc.org.uk/lla/id/event/leaving/15772-477332-7-2"/>
  </rdf:Description>
  <rdf:Description rdf:about="http://data.llgc.org.uk/lla/id/event/leaving/15772-477332-7">
    <rdf:type rdf:resource="http://data.llgc.org.uk/lla/def#ShipLeavingEvent"/>
    <dc:date rdf:datatype="http://www.w3.org/2001/XMLSchema#dateTime">1040</dc:date>
    <bio:place xml:lang="en">Plymouth</bio:place>
    <lla:involvesMariner rdf:resource="http://data.llgc.org.uk/lla/id/mariner/15772-477332-7"/>
    <lla:recordedIn rdf:resource="http://data.llgc.org.uk/lla/id/logbookentry/15772-477332-7"/>
    <lla:involvesShip rdf:resource="http://data.llgc.org.uk/lla/id/ship/15772"/>
  </rdf:Description>
  <rdf:Description rdf:about="http://data.llgc.org.uk/lla/id/logbookentry/15772-477332-8">
    <rdf:type rdf:resource="http://data.llgc.org.uk/lla/def#LogbookEntry"/>
    <dcterms:isPartOf rdf:resource="http://data.llgc.org.uk/lla/id/logbook/15772-477332"/>
    <lla:calculatedAge rdf:datatype="http://www.w3.org/2001/XMLSchema#int">24</lla:calculatedAge>
    <lla:describesEvent rdf:resource="http://data.llgc.org.uk/lla/id/event/leaving/15772-477332-8-2"/>
    <lla:describesEvent rdf:resource="http://data.llgc.org.uk/lla/id/event/joining/15772-477332-8"/>
    <lla:describesEvent rdf:resource="http://data.llgc.org.uk/lla/id/event/leaving/15772-477332-8"/>
    <lla:reason xml:lang="en">Remaining</lla:reason>
    <lla:mark rdf:datatype="http://www.w3.org/2001/XMLSchema#boolean">false</lla:mark>
  </rdf:Description>
  <rdf:Description rdf:about="http://data.llgc.org.uk/lla/id/mariner/15772-477332-8">
    <rdf:type rdf:resource="http://data.llgc.org.uk/lla/def#Mariner"/>
    <foaf:name>[Lahmuel] Parcy</foaf:name>
    <bio:Birth rdf:resource="http://data.llgc.org.uk/lla/id/event/birth/15772-477332-8"/>
  </rdf:Description>
  <rdf:Description rdf:about="http://data.llgc.org.uk/lla/id/event/birth/15772-477332-8">
    <rdf:type rdf:resource="http://purl.org/vocab/bio/0.1/Birth"/>
    <dc:date rdf:datatype="http://www.w3.org/2001/XMLSchema#dateTime">1878-01-01</dc:date>
    <bio:place xml:lang="en">Flint</bio:place>
    <bio:agent rdf:resource="http://data.llgc.org.uk/lla/id/mariner/15772-477332-8"/>
  </rdf:Description>
  <rdf:Description rdf:about="http://data.llgc.org.uk/lla/id/event/leaving/15772-477332-8-2">
    <rdf:type rdf:resource="http://data.llgc.org.uk/lla/def#ShipLeavingEvent"/>
    <dc:date rdf:datatype="http://www.w3.org/2001/XMLSchema#dateTime">1902</dc:date>
    <lla:involvesMariner rdf:resource="http://data.llgc.org.uk/lla/id/mariner/15772-477332-8"/>
    <lla:recordedIn rdf:resource="http://data.llgc.org.uk/lla/id/logbookentry/15772-477332-8"/>
    <lla:involvesShip rdf:resource="http://data.llgc.org.uk/lla/id/ship/15772-477332-8"/>
  </rdf:Description>
  <rdf:Description rdf:about="http://data.llgc.org.uk/lla/id/ship/15772-477332-8">
    <rdf:type rdf:resource="http://data.llgc.org.uk/lla/def#Ship"/>
    <lla:mentionedIn rdf:resource="http://data.llgc.org.uk/lla/id/archivefile/477-33_vtls004957170"/>
    <lla:mentionedIn rdf:resource="http://data.llgc.org.uk/lla/id/logbook/15772-477332"/>
    <lla:mentionedIn rdf:resource="http://data.llgc.org.uk/lla/id/logbookentry/15772-477332-8"/>
    <rdfs:label xml:lang="en">Ottawa</rdfs:label>
  </rdf:Description>
  <rdf:Description rdf:about="http://data.llgc.org.uk/lla/id/event/joining/15772-477332-8">
    <rdf:type rdf:resource="http://data.llgc.org.uk/lla/def#ShipJoiningEvent"/>
    <dc:date rdf:datatype="http://www.w3.org/2001/XMLSchema#dateTime">1026</dc:date>
    <bio:place xml:lang="en">Rochester</bio:place>
    <lla:hasCapacity xml:lang="en">Able Seaman</lla:hasCapacity>
    <lla:involvesMariner rdf:resource="http://data.llgc.org.uk/lla/id/mariner/15772-477332-8"/>
    <lla:recordedIn rdf:resource="http://data.llgc.org.uk/lla/id/logbookentry/15772-477332-8"/>
    <lla:involvesShip rdf:resource="http://data.llgc.org.uk/lla/id/ship/15772"/>
    <lla:hasPreviousIndividualEvent rdf:resource="http://data.llgc.org.uk/lla/id/event/leaving/15772-477332-8-2"/>
  </rdf:Description>
  <rdf:Description rdf:about="http://data.llgc.org.uk/lla/id/event/leaving/15772-477332-8">
    <rdf:type rdf:resource="http://data.llgc.org.uk/lla/def#ShipLeavingEvent"/>
    <dc:date rdf:datatype="http://www.w3.org/2001/XMLSchema#dateTime">1096</dc:date>
    <bio:place xml:lang="en">London</bio:place>
    <lla:involvesMariner rdf:resource="http://data.llgc.org.uk/lla/id/mariner/15772-477332-8"/>
    <lla:recordedIn rdf:resource="http://data.llgc.org.uk/lla/id/logbookentry/15772-477332-8"/>
    <lla:involvesShip rdf:resource="http://data.llgc.org.uk/lla/id/ship/15772"/>
  </rdf:Description>
  <rdf:Description rdf:about="http://data.llgc.org.uk/lla/id/logbookentry/15772-477332-9">
    <rdf:type rdf:resource="http://data.llgc.org.uk/lla/def#LogbookEntry"/>
    <dcterms:isPartOf rdf:resource="http://data.llgc.org.uk/lla/id/logbook/15772-477332"/>
    <lla:calculatedAge rdf:datatype="http://www.w3.org/2001/XMLSchema#int">36</lla:calculatedAge>
    <lla:describesEvent rdf:resource="http://data.llgc.org.uk/lla/id/event/leaving/15772-477332-9-2"/>
    <lla:describesEvent rdf:resource="http://data.llgc.org.uk/lla/id/event/joining/15772-477332-9"/>
    <lla:describesEvent rdf:resource="http://data.llgc.org.uk/lla/id/event/leaving/15772-477332-9"/>
    <lla:reason xml:lang="en">Remaining</lla:reason>
    <lla:mark rdf:datatype="http://www.w3.org/2001/XMLSchema#boolean">false</lla:mark>
  </rdf:Description>
  <rdf:Description rdf:about="http://data.llgc.org.uk/lla/id/mariner/15772-477332-9">
    <rdf:type rdf:resource="http://data.llgc.org.uk/lla/def#Mariner"/>
    <foaf:name>William Geall</foaf:name>
    <bio:Birth rdf:resource="http://data.llgc.org.uk/lla/id/event/birth/15772-477332-9"/>
  </rdf:Description>
  <rdf:Description rdf:about="http://data.llgc.org.uk/lla/id/event/birth/15772-477332-9">
    <rdf:type rdf:resource="http://purl.org/vocab/bio/0.1/Birth"/>
    <dc:date rdf:datatype="http://www.w3.org/2001/XMLSchema#dateTime">1866-01-01</dc:date>
    <bio:place xml:lang="en">Poole</bio:place>
    <bio:agent rdf:resource="http://data.llgc.org.uk/lla/id/mariner/15772-477332-9"/>
  </rdf:Description>
  <rdf:Description rdf:about="http://data.llgc.org.uk/lla/id/event/leaving/15772-477332-9-2">
    <rdf:type rdf:resource="http://data.llgc.org.uk/lla/def#ShipLeavingEvent"/>
    <dc:date rdf:datatype="http://www.w3.org/2001/XMLSchema#dateTime">1902</dc:date>
    <lla:involvesMariner rdf:resource="http://data.llgc.org.uk/lla/id/mariner/15772-477332-9"/>
    <lla:recordedIn rdf:resource="http://data.llgc.org.uk/lla/id/logbookentry/15772-477332-9"/>
    <lla:involvesShip rdf:resource="http://data.llgc.org.uk/lla/id/ship/15772-477332-9"/>
  </rdf:Description>
  <rdf:Description rdf:about="http://data.llgc.org.uk/lla/id/ship/15772-477332-9">
    <rdf:type rdf:resource="http://data.llgc.org.uk/lla/def#Ship"/>
    <lla:hasHomePort xml:lang="en">$</lla:hasHomePort>
    <lla:mentionedIn rdf:resource="http://data.llgc.org.uk/lla/id/archivefile/477-33_vtls004957170"/>
    <lla:mentionedIn rdf:resource="http://data.llgc.org.uk/lla/id/logbook/15772-477332"/>
    <lla:mentionedIn rdf:resource="http://data.llgc.org.uk/lla/id/logbookentry/15772-477332-9"/>
    <rdfs:label xml:lang="en">[Cryotae]</rdfs:label>
  </rdf:Description>
  <rdf:Description rdf:about="http://data.llgc.org.uk/lla/id/event/joining/15772-477332-9">
    <rdf:type rdf:resource="http://data.llgc.org.uk/lla/def#ShipJoiningEvent"/>
    <dc:date rdf:datatype="http://www.w3.org/2001/XMLSchema#dateTime">1041</dc:date>
    <bio:place xml:lang="en">Plymouth</bio:place>
    <lla:hasCapacity xml:lang="en">Able Seaman</lla:hasCapacity>
    <lla:involvesMariner rdf:resource="http://data.llgc.org.uk/lla/id/mariner/15772-477332-9"/>
    <lla:recordedIn rdf:resource="http://data.llgc.org.uk/lla/id/logbookentry/15772-477332-9"/>
    <lla:involvesShip rdf:resource="http://data.llgc.org.uk/lla/id/ship/15772"/>
    <lla:hasPreviousIndividualEvent rdf:resource="http://data.llgc.org.uk/lla/id/event/leaving/15772-477332-9-2"/>
  </rdf:Description>
  <rdf:Description rdf:about="http://data.llgc.org.uk/lla/id/event/leaving/15772-477332-9">
    <rdf:type rdf:resource="http://data.llgc.org.uk/lla/def#ShipLeavingEvent"/>
    <dc:date rdf:datatype="http://www.w3.org/2001/XMLSchema#dateTime">1096</dc:date>
    <bio:place xml:lang="en">London</bio:place>
    <lla:involvesMariner rdf:resource="http://data.llgc.org.uk/lla/id/mariner/15772-477332-9"/>
    <lla:recordedIn rdf:resource="http://data.llgc.org.uk/lla/id/logbookentry/15772-477332-9"/>
    <lla:involvesShip rdf:resource="http://data.llgc.org.uk/lla/id/ship/15772"/>
  </rdf:Description>
  <rdf:Description rdf:about="http://data.llgc.org.uk/lla/id/logbookentry/15772-477332-10">
    <rdf:type rdf:resource="http://data.llgc.org.uk/lla/def#LogbookEntry"/>
    <dcterms:isPartOf rdf:resource="http://data.llgc.org.uk/lla/id/logbook/15772-477332"/>
    <lla:calculatedAge rdf:datatype="http://www.w3.org/2001/XMLSchema#int">24</lla:calculatedAge>
    <lla:describesEvent rdf:resource="http://data.llgc.org.uk/lla/id/event/leaving/15772-477332-10-2"/>
    <lla:describesEvent rdf:resource="http://data.llgc.org.uk/lla/id/event/joining/15772-477332-10"/>
    <lla:describesEvent rdf:resource="http://data.llgc.org.uk/lla/id/event/leaving/15772-477332-10"/>
    <lla:reason xml:lang="en">Remaining</lla:reason>
    <lla:mark rdf:datatype="http://www.w3.org/2001/XMLSchema#boolean">false</lla:mark>
  </rdf:Description>
  <rdf:Description rdf:about="http://data.llgc.org.uk/lla/id/mariner/15772-477332-10">
    <rdf:type rdf:resource="http://data.llgc.org.uk/lla/def#Mariner"/>
    <foaf:name>William Brown</foaf:name>
    <bio:Birth rdf:resource="http://data.llgc.org.uk/lla/id/event/birth/15772-477332-10"/>
  </rdf:Description>
  <rdf:Description rdf:about="http://data.llgc.org.uk/lla/id/event/birth/15772-477332-10">
    <rdf:type rdf:resource="http://purl.org/vocab/bio/0.1/Birth"/>
    <dc:date rdf:datatype="http://www.w3.org/2001/XMLSchema#dateTime">1878-01-01</dc:date>
    <bio:place xml:lang="en">London</bio:place>
    <bio:agent rdf:resource="http://data.llgc.org.uk/lla/id/mariner/15772-477332-10"/>
  </rdf:Description>
  <rdf:Description rdf:about="http://data.llgc.org.uk/lla/id/event/leaving/15772-477332-10-2">
    <rdf:type rdf:resource="http://data.llgc.org.uk/lla/def#ShipLeavingEvent"/>
    <dc:date rdf:datatype="http://www.w3.org/2001/XMLSchema#dateTime">1902</dc:date>
    <lla:involvesMariner rdf:resource="http://data.llgc.org.uk/lla/id/mariner/15772-477332-10"/>
    <lla:recordedIn rdf:resource="http://data.llgc.org.uk/lla/id/logbookentry/15772-477332-10"/>
    <lla:involvesShip rdf:resource="http://data.llgc.org.uk/lla/id/ship/15772-477332-10"/>
  </rdf:Description>
  <rdf:Description rdf:about="http://data.llgc.org.uk/lla/id/ship/15772-477332-10">
    <rdf:type rdf:resource="http://data.llgc.org.uk/lla/def#Ship"/>
    <lla:mentionedIn rdf:resource="http://data.llgc.org.uk/lla/id/archivefile/477-33_vtls004957170"/>
    <lla:mentionedIn rdf:resource="http://data.llgc.org.uk/lla/id/logbook/15772-477332"/>
    <lla:mentionedIn rdf:resource="http://data.llgc.org.uk/lla/id/logbookentry/15772-477332-10"/>
    <rdfs:label xml:lang="en">Elsie</rdfs:label>
  </rdf:Description>
  <rdf:Description rdf:about="http://data.llgc.org.uk/lla/id/event/joining/15772-477332-10">
    <rdf:type rdf:resource="http://data.llgc.org.uk/lla/def#ShipJoiningEvent"/>
    <dc:date rdf:datatype="http://www.w3.org/2001/XMLSchema#dateTime">1041</dc:date>
    <bio:place xml:lang="en">Plymouth</bio:place>
    <lla:hasCapacity xml:lang="en">Cook</lla:hasCapacity>
    <lla:involvesMariner rdf:resource="http://data.llgc.org.uk/lla/id/mariner/15772-477332-10"/>
    <lla:recordedIn rdf:resource="http://data.llgc.org.uk/lla/id/logbookentry/15772-477332-10"/>
    <lla:involvesShip rdf:resource="http://data.llgc.org.uk/lla/id/ship/15772"/>
    <lla:hasPreviousIndividualEvent rdf:resource="http://data.llgc.org.uk/lla/id/event/leaving/15772-477332-10-2"/>
  </rdf:Description>
  <rdf:Description rdf:about="http://data.llgc.org.uk/lla/id/event/leaving/15772-477332-10">
    <rdf:type rdf:resource="http://data.llgc.org.uk/lla/def#ShipLeavingEvent"/>
    <dc:date rdf:datatype="http://www.w3.org/2001/XMLSchema#dateTime">1096</dc:date>
    <bio:place xml:lang="en">London</bio:place>
    <lla:involvesMariner rdf:resource="http://data.llgc.org.uk/lla/id/mariner/15772-477332-10"/>
    <lla:recordedIn rdf:resource="http://data.llgc.org.uk/lla/id/logbookentry/15772-477332-10"/>
    <lla:involvesShip rdf:resource="http://data.llgc.org.uk/lla/id/ship/15772"/>
  </rdf:Description>
  <rdf:Description rdf:about="http://data.llgc.org.uk/lla/id/logbookentry/15772-477332-11">
    <rdf:type rdf:resource="http://data.llgc.org.uk/lla/def#LogbookEntry"/>
    <dcterms:isPartOf rdf:resource="http://data.llgc.org.uk/lla/id/logbook/15772-477332"/>
    <lla:calculatedAge rdf:datatype="http://www.w3.org/2001/XMLSchema#int">30</lla:calculatedAge>
    <lla:describesEvent rdf:resource="http://data.llgc.org.uk/lla/id/event/leaving/15772-477332-11-2"/>
    <lla:describesEvent rdf:resource="http://data.llgc.org.uk/lla/id/event/joining/15772-477332-11"/>
    <lla:describesEvent rdf:resource="http://data.llgc.org.uk/lla/id/event/leaving/15772-477332-11"/>
    <lla:reason xml:lang="en">Remaining</lla:reason>
    <lla:mark rdf:datatype="http://www.w3.org/2001/XMLSchema#boolean">false</lla:mark>
  </rdf:Description>
  <rdf:Description rdf:about="http://data.llgc.org.uk/lla/id/mariner/15772-477332-11">
    <rdf:type rdf:resource="http://data.llgc.org.uk/lla/def#Mariner"/>
    <foaf:name>J G Holland</foaf:name>
    <bio:Birth rdf:resource="http://data.llgc.org.uk/lla/id/event/birth/15772-477332-11"/>
  </rdf:Description>
  <rdf:Description rdf:about="http://data.llgc.org.uk/lla/id/event/birth/15772-477332-11">
    <rdf:type rdf:resource="http://purl.org/vocab/bio/0.1/Birth"/>
    <dc:date rdf:datatype="http://www.w3.org/2001/XMLSchema#dateTime">1872-01-01</dc:date>
    <bio:place xml:lang="en">Bridgewater</bio:place>
    <bio:agent rdf:resource="http://data.llgc.org.uk/lla/id/mariner/15772-477332-11"/>
  </rdf:Description>
  <rdf:Description rdf:about="http://data.llgc.org.uk/lla/id/event/leaving/15772-477332-11-2">
    <rdf:type rdf:resource="http://data.llgc.org.uk/lla/def#ShipLeavingEvent"/>
    <dc:date rdf:datatype="http://www.w3.org/2001/XMLSchema#dateTime">1902</dc:date>
    <lla:involvesMariner rdf:resource="http://data.llgc.org.uk/lla/id/mariner/15772-477332-11"/>
    <lla:recordedIn rdf:resource="http://data.llgc.org.uk/lla/id/logbookentry/15772-477332-11"/>
    <lla:involvesShip rdf:resource="http://data.llgc.org.uk/lla/id/ship/15772-477332-11"/>
  </rdf:Description>
  <rdf:Description rdf:about="http://data.llgc.org.uk/lla/id/ship/15772-477332-11">
    <rdf:type rdf:resource="http://data.llgc.org.uk/lla/def#Ship"/>
    <lla:mentionedIn rdf:resource="http://data.llgc.org.uk/lla/id/archivefile/477-33_vtls004957170"/>
    <lla:mentionedIn rdf:resource="http://data.llgc.org.uk/lla/id/logbook/15772-477332"/>
    <lla:mentionedIn rdf:resource="http://data.llgc.org.uk/lla/id/logbookentry/15772-477332-11"/>
    <rdfs:label xml:lang="en">Emma</rdfs:label>
  </rdf:Description>
  <rdf:Description rdf:about="http://data.llgc.org.uk/lla/id/event/joining/15772-477332-11">
    <rdf:type rdf:resource="http://data.llgc.org.uk/lla/def#ShipJoiningEvent"/>
    <dc:date rdf:datatype="http://www.w3.org/2001/XMLSchema#dateTime">1078</dc:date>
    <bio:place xml:lang="en">Folkstone</bio:place>
    <lla:hasCapacity xml:lang="en">Master</lla:hasCapacity>
    <lla:involvesMariner rdf:resource="http://data.llgc.org.uk/lla/id/mariner/15772-477332-11"/>
    <lla:recordedIn rdf:resource="http://data.llgc.org.uk/lla/id/logbookentry/15772-477332-11"/>
    <lla:involvesShip rdf:resource="http://data.llgc.org.uk/lla/id/ship/15772"/>
    <lla:hasPreviousIndividualEvent rdf:resource="http://data.llgc.org.uk/lla/id/event/leaving/15772-477332-11-2"/>
  </rdf:Description>
  <rdf:Description rdf:about="http://data.llgc.org.uk/lla/id/event/leaving/15772-477332-11">
    <rdf:type rdf:resource="http://data.llgc.org.uk/lla/def#ShipLeavingEvent"/>
    <dc:date rdf:datatype="http://www.w3.org/2001/XMLSchema#dateTime">1096</dc:date>
    <bio:place xml:lang="en">London</bio:place>
    <lla:involvesMariner rdf:resource="http://data.llgc.org.uk/lla/id/mariner/15772-477332-11"/>
    <lla:recordedIn rdf:resource="http://data.llgc.org.uk/lla/id/logbookentry/15772-477332-11"/>
    <lla:involvesShip rdf:resource="http://data.llgc.org.uk/lla/id/ship/15772"/>
  </rdf:Description>
  <rdf:Description rdf:about="http://data.llgc.org.uk/lla/id/logbookentry/15772-477332-12">
    <rdf:type rdf:resource="http://data.llgc.org.uk/lla/def#LogbookEntry"/>
    <dcterms:isPartOf rdf:resource="http://data.llgc.org.uk/lla/id/logbook/15772-477332"/>
    <lla:calculatedAge rdf:datatype="http://www.w3.org/2001/XMLSchema#int">44</lla:calculatedAge>
    <lla:describesEvent rdf:resource="http://data.llgc.org.uk/lla/id/event/joining/15772-477332-12"/>
    <lla:describesEvent rdf:resource="http://data.llgc.org.uk/lla/id/event/leaving/15772-477332-12"/>
    <lla:reason xml:lang="en">Discharged</lla:reason>
    <lla:mark rdf:datatype="http://www.w3.org/2001/XMLSchema#boolean">false</lla:mark>
  </rdf:Description>
  <rdf:Description rdf:about="http://data.llgc.org.uk/lla/id/mariner/15772-477332-12">
    <rdf:type rdf:resource="http://data.llgc.org.uk/lla/def#Mariner"/>
    <foaf:name>N Roberts</foaf:name>
    <bio:Birth rdf:resource="http://data.llgc.org.uk/lla/id/event/birth/15772-477332-12"/>
  </rdf:Description>
  <rdf:Description rdf:about="http://data.llgc.org.uk/lla/id/event/birth/15772-477332-12">
    <rdf:type rdf:resource="http://purl.org/vocab/bio/0.1/Birth"/>
    <dc:date rdf:datatype="http://www.w3.org/2001/XMLSchema#dateTime">1858-01-01</dc:date>
    <bio:place xml:lang="en">Newquay</bio:place>
    <bio:agent rdf:resource="http://data.llgc.org.uk/lla/id/mariner/15772-477332-12"/>
  </rdf:Description>
  <rdf:Description rdf:about="http://data.llgc.org.uk/lla/id/event/joining/15772-477332-12">
    <rdf:type rdf:resource="http://data.llgc.org.uk/lla/def#ShipJoiningEvent"/>
    <dc:date rdf:datatype="http://www.w3.org/2001/XMLSchema#dateTime">933</dc:date>
    <bio:place xml:lang="en">Lancaster</bio:place>
    <lla:hasCapacity xml:lang="en">Able Seaman</lla:hasCapacity>
    <lla:involvesMariner rdf:resource="http://data.llgc.org.uk/lla/id/mariner/15772-477332-12"/>
    <lla:recordedIn rdf:resource="http://data.llgc.org.uk/lla/id/logbookentry/15772-477332-12"/>
    <lla:involvesShip rdf:resource="http://data.llgc.org.uk/lla/id/ship/15772"/>
  </rdf:Description>
  <rdf:Description rdf:about="http://data.llgc.org.uk/lla/id/event/leaving/15772-477332-12">
    <rdf:type rdf:resource="http://data.llgc.org.uk/lla/def#ShipLeavingEvent"/>
    <dc:date rdf:datatype="http://www.w3.org/2001/XMLSchema#dateTime">943</dc:date>
    <bio:place xml:lang="en">Lancaster</bio:place>
    <lla:involvesMariner rdf:resource="http://data.llgc.org.uk/lla/id/mariner/15772-477332-12"/>
    <lla:recordedIn rdf:resource="http://data.llgc.org.uk/lla/id/logbookentry/15772-477332-12"/>
    <lla:involvesShip rdf:resource="http://data.llgc.org.uk/lla/id/ship/15772"/>
  </rdf:Description>
</rdf:RDF>
