<?xml version="1.0" encoding="UTF-8"?>
<rdf:RDF xmlns:rdf="http://www.w3.org/1999/02/22-rdf-syntax-ns#" xmlns:lla="http://data.llgc.org.uk/lla/def#" xmlns:rdfs="http://www.w3.org/2000/01/rdf-schema#" xmlns:dcterms="http://purl.org/dc/terms/" xmlns:archiveshub="http://data.archiveshub.ac.uk/def" xmlns:foaf="http://xmlns.com/foaf/0.1/" xmlns:bio="http://purl.org/vocab/bio/0.1/" xmlns:dc="http://purl.org/dc/elements/1.1/" xmlns:void="http://rdfs.org/ns/void#" xmlns:owl="http://www.w3.org/2002/07/owl#">
  <rdf:Description rdf:about="http://data.llgc.org.uk/lla/id/ship/22980">
    <rdf:type rdf:resource="http://data.llgc.org.uk/lla/def#LogbookShip"/>
    <lla:hasHomePort xml:lang="en">Aberystwyth</lla:hasHomePort>
    <lla:officialnumber rdf:datatype="http://www.w3.org/2001/XMLSchema#string">22980</lla:officialnumber>
    <lla:mentionedIn rdf:resource="http://data.llgc.org.uk/lla/id/archivefile/64-8_vtls004625393"/>
    <rdfs:label xml:lang="en">Battus</rdfs:label>
    <owl:sameAs rdf:resource="http://www.wikidata.org/entity/Q24027141"/>
    <lla:mentionedIn rdf:resource="http://data.llgc.org.uk/lla/id/logbook/22980-6481"/>
    <lla:mentionedIn rdf:resource="http://data.llgc.org.uk/lla/id/logbookentry/22980-6481-1"/>
    <lla:mentionedIn rdf:resource="http://data.llgc.org.uk/lla/id/logbookentry/22980-6481-2"/>
    <lla:mentionedIn rdf:resource="http://data.llgc.org.uk/lla/id/logbookentry/22980-6481-3"/>
    <lla:mentionedIn rdf:resource="http://data.llgc.org.uk/lla/id/logbookentry/22980-6481-4"/>
    <lla:mentionedIn rdf:resource="http://data.llgc.org.uk/lla/id/logbookentry/22980-6481-5"/>
    <lla:mentionedIn rdf:resource="http://data.llgc.org.uk/lla/id/logbookentry/22980-6481-6"/>
    <lla:mentionedIn rdf:resource="http://data.llgc.org.uk/lla/id/logbookentry/22980-6481-7"/>
    <lla:mentionedIn rdf:resource="http://data.llgc.org.uk/lla/id/logbook/22980-6482"/>
    <lla:mentionedIn rdf:resource="http://data.llgc.org.uk/lla/id/logbookentry/22980-6482-1"/>
    <lla:mentionedIn rdf:resource="http://data.llgc.org.uk/lla/id/logbookentry/22980-6482-2"/>
    <lla:mentionedIn rdf:resource="http://data.llgc.org.uk/lla/id/logbookentry/22980-6482-3"/>
    <lla:mentionedIn rdf:resource="http://data.llgc.org.uk/lla/id/logbookentry/22980-6482-4"/>
    <lla:mentionedIn rdf:resource="http://data.llgc.org.uk/lla/id/logbookentry/22980-6482-5"/>
    <lla:mentionedIn rdf:resource="http://data.llgc.org.uk/lla/id/logbookentry/22980-6482-6"/>
    <lla:mentionedIn rdf:resource="http://data.llgc.org.uk/lla/id/logbookentry/22980-6482-7"/>
    <lla:mentionedIn rdf:resource="http://data.llgc.org.uk/lla/id/logbook/22980-6483"/>
    <lla:mentionedIn rdf:resource="http://data.llgc.org.uk/lla/id/logbookentry/22980-6483-1"/>
    <lla:mentionedIn rdf:resource="http://data.llgc.org.uk/lla/id/logbookentry/22980-6483-2"/>
    <lla:mentionedIn rdf:resource="http://data.llgc.org.uk/lla/id/logbookentry/22980-6483-3"/>
    <lla:mentionedIn rdf:resource="http://data.llgc.org.uk/lla/id/logbookentry/22980-6483-4"/>
    <lla:mentionedIn rdf:resource="http://data.llgc.org.uk/lla/id/logbookentry/22980-6483-5"/>
    <lla:mentionedIn rdf:resource="http://data.llgc.org.uk/lla/id/logbookentry/22980-6483-6"/>
    <lla:mentionedIn rdf:resource="http://data.llgc.org.uk/lla/id/logbookentry/22980-6483-7"/>
    <lla:mentionedIn rdf:resource="http://data.llgc.org.uk/lla/id/logbookentry/22980-6483-8"/>
    <lla:mentionedIn rdf:resource="http://data.llgc.org.uk/lla/id/logbookentry/22980-6483-9"/>
  </rdf:Description>
  <rdf:Description rdf:about="http://data.llgc.org.uk/lla/id/archivefile/64-8_vtls004625393">
    <rdf:type rdf:resource="http://data.llgc.org.uk/lla/def#File"/>
    <lla:vtlsNum rdf:datatype="http://www.w3.org/2001/XMLSchema#string">004625393</lla:vtlsNum>
    <dcterms:identifier rdf:datatype="http://www.w3.org/2001/XMLSchema#string">64-8</dcterms:identifier>
    <lla:sourceFile rdf:datatype="http://www.w3.org/2001/XMLSchema#string">File_64-8_vtls004625393.xls</lla:sourceFile>
    <lla:mentions rdf:resource="http://data.llgc.org.uk/lla/id/ship/22980"/>
    <dcterms:hasPart rdf:resource="http://data.llgc.org.uk/lla/id/logbook/22980-6481"/>
    <dcterms:hasPart rdf:resource="http://data.llgc.org.uk/lla/id/logbook/22980-6482"/>
    <dcterms:hasPart rdf:resource="http://data.llgc.org.uk/lla/id/logbook/22980-6483"/>
  </rdf:Description>
  <rdf:Description rdf:about="http://data.llgc.org.uk/lla/id/logbook/22980-6481">
    <rdf:type rdf:resource="http://data.llgc.org.uk/lla/def#Logbook"/>
    <dcterms:identifier rdf:datatype="http://www.w3.org/2001/XMLSchema#string">64-8-1</dcterms:identifier>
    <dcterms:isPartOf rdf:resource="http://data.llgc.org.uk/lla/id/archivefile/64-8_vtls004625393"/>
    <dcterms:hasPart rdf:resource="http://data.llgc.org.uk/lla/id/logbookentry/22980-6481-1"/>
    <dcterms:hasPart rdf:resource="http://data.llgc.org.uk/lla/id/logbookentry/22980-6481-2"/>
    <dcterms:hasPart rdf:resource="http://data.llgc.org.uk/lla/id/logbookentry/22980-6481-3"/>
    <dcterms:hasPart rdf:resource="http://data.llgc.org.uk/lla/id/logbookentry/22980-6481-4"/>
    <dcterms:hasPart rdf:resource="http://data.llgc.org.uk/lla/id/logbookentry/22980-6481-5"/>
    <dcterms:hasPart rdf:resource="http://data.llgc.org.uk/lla/id/logbookentry/22980-6481-6"/>
    <dcterms:hasPart rdf:resource="http://data.llgc.org.uk/lla/id/logbookentry/22980-6481-7"/>
  </rdf:Description>
  <rdf:Description rdf:about="http://data.llgc.org.uk/lla/id/logbookentry/22980-6481-1">
    <rdf:type rdf:resource="http://data.llgc.org.uk/lla/def#LogbookEntry"/>
    <dcterms:isPartOf rdf:resource="http://data.llgc.org.uk/lla/id/logbook/22980-6481"/>
    <lla:logbookAge rdf:datatype="http://www.w3.org/2001/XMLSchema#int">35</lla:logbookAge>
    <lla:describesEvent rdf:resource="http://data.llgc.org.uk/lla/id/event/joining/22980-6481-1"/>
    <lla:reason xml:lang="en">Remains on board</lla:reason>
    <lla:mark rdf:datatype="http://www.w3.org/2001/XMLSchema#boolean">false</lla:mark>
  </rdf:Description>
  <rdf:Description rdf:about="http://data.llgc.org.uk/lla/id/mariner/22980-6481-1">
    <rdf:type rdf:resource="http://data.llgc.org.uk/lla/def#Mariner"/>
    <foaf:name>Evan Jones</foaf:name>
    <bio:Birth rdf:resource="http://data.llgc.org.uk/lla/id/event/birth/22980-6481-1"/>
  </rdf:Description>
  <rdf:Description rdf:about="http://data.llgc.org.uk/lla/id/event/birth/22980-6481-1">
    <rdf:type rdf:resource="http://purl.org/vocab/bio/0.1/Birth"/>
    <bio:place xml:lang="en">Aberystwyth</bio:place>
    <bio:agent rdf:resource="http://data.llgc.org.uk/lla/id/mariner/22980-6481-1"/>
  </rdf:Description>
  <rdf:Description rdf:about="http://data.llgc.org.uk/lla/id/event/joining/22980-6481-1">
    <rdf:type rdf:resource="http://data.llgc.org.uk/lla/def#ShipJoiningEvent"/>
    <dc:date rdf:datatype="http://www.w3.org/2001/XMLSchema#dateTime">1873-01-14</dc:date>
    <bio:place xml:lang="en">Runcorn</bio:place>
    <lla:hasCapacity xml:lang="en">Master</lla:hasCapacity>
    <lla:involvesMariner rdf:resource="http://data.llgc.org.uk/lla/id/mariner/22980-6481-1"/>
    <lla:recordedIn rdf:resource="http://data.llgc.org.uk/lla/id/logbookentry/22980-6481-1"/>
    <lla:involvesShip rdf:resource="http://data.llgc.org.uk/lla/id/ship/22980"/>
  </rdf:Description>
  <rdf:Description rdf:about="http://data.llgc.org.uk/lla/id/logbookentry/22980-6481-2">
    <rdf:type rdf:resource="http://data.llgc.org.uk/lla/def#LogbookEntry"/>
    <dcterms:isPartOf rdf:resource="http://data.llgc.org.uk/lla/id/logbook/22980-6481"/>
    <lla:logbookAge rdf:datatype="http://www.w3.org/2001/XMLSchema#int">32</lla:logbookAge>
    <lla:describesEvent rdf:resource="http://data.llgc.org.uk/lla/id/event/joining/22980-6481-2"/>
    <lla:describesEvent rdf:resource="http://data.llgc.org.uk/lla/id/event/leaving/22980-6481-2"/>
    <lla:reason xml:lang="en">Discharged</lla:reason>
    <lla:mark rdf:datatype="http://www.w3.org/2001/XMLSchema#boolean">false</lla:mark>
  </rdf:Description>
  <rdf:Description rdf:about="http://data.llgc.org.uk/lla/id/mariner/22980-6481-2">
    <rdf:type rdf:resource="http://data.llgc.org.uk/lla/def#Mariner"/>
    <foaf:name>Edward Jones</foaf:name>
    <bio:Birth rdf:resource="http://data.llgc.org.uk/lla/id/event/birth/22980-6481-2"/>
  </rdf:Description>
  <rdf:Description rdf:about="http://data.llgc.org.uk/lla/id/event/birth/22980-6481-2">
    <rdf:type rdf:resource="http://purl.org/vocab/bio/0.1/Birth"/>
    <bio:place xml:lang="en">Aberystwyth</bio:place>
    <bio:agent rdf:resource="http://data.llgc.org.uk/lla/id/mariner/22980-6481-2"/>
  </rdf:Description>
  <rdf:Description rdf:about="http://data.llgc.org.uk/lla/id/event/joining/22980-6481-2">
    <rdf:type rdf:resource="http://data.llgc.org.uk/lla/def#ShipJoiningEvent"/>
    <dc:date rdf:datatype="http://www.w3.org/2001/XMLSchema#dateTime">1873-01-14</dc:date>
    <bio:place xml:lang="en">Runcorn</bio:place>
    <lla:hasCapacity xml:lang="en">Mate</lla:hasCapacity>
    <lla:involvesMariner rdf:resource="http://data.llgc.org.uk/lla/id/mariner/22980-6481-2"/>
    <lla:recordedIn rdf:resource="http://data.llgc.org.uk/lla/id/logbookentry/22980-6481-2"/>
    <lla:involvesShip rdf:resource="http://data.llgc.org.uk/lla/id/ship/22980"/>
  </rdf:Description>
  <rdf:Description rdf:about="http://data.llgc.org.uk/lla/id/event/leaving/22980-6481-2">
    <rdf:type rdf:resource="http://data.llgc.org.uk/lla/def#ShipLeavingEvent"/>
    <dc:date rdf:datatype="http://www.w3.org/2001/XMLSchema#dateTime">1873-04-29</dc:date>
    <bio:place xml:lang="en">Llanelly</bio:place>
    <lla:involvesMariner rdf:resource="http://data.llgc.org.uk/lla/id/mariner/22980-6481-2"/>
    <lla:recordedIn rdf:resource="http://data.llgc.org.uk/lla/id/logbookentry/22980-6481-2"/>
    <lla:involvesShip rdf:resource="http://data.llgc.org.uk/lla/id/ship/22980"/>
  </rdf:Description>
  <rdf:Description rdf:about="http://data.llgc.org.uk/lla/id/logbookentry/22980-6481-3">
    <rdf:type rdf:resource="http://data.llgc.org.uk/lla/def#LogbookEntry"/>
    <dcterms:isPartOf rdf:resource="http://data.llgc.org.uk/lla/id/logbook/22980-6481"/>
    <lla:logbookAge rdf:datatype="http://www.w3.org/2001/XMLSchema#int">42</lla:logbookAge>
    <lla:describesEvent rdf:resource="http://data.llgc.org.uk/lla/id/event/joining/22980-6481-3"/>
    <lla:describesEvent rdf:resource="http://data.llgc.org.uk/lla/id/event/leaving/22980-6481-3"/>
    <lla:reason xml:lang="en">Discharged</lla:reason>
    <lla:mark rdf:datatype="http://www.w3.org/2001/XMLSchema#boolean">false</lla:mark>
  </rdf:Description>
  <rdf:Description rdf:about="http://data.llgc.org.uk/lla/id/mariner/22980-6481-3">
    <rdf:type rdf:resource="http://data.llgc.org.uk/lla/def#Mariner"/>
    <foaf:name>David Davies</foaf:name>
    <bio:Birth rdf:resource="http://data.llgc.org.uk/lla/id/event/birth/22980-6481-3"/>
  </rdf:Description>
  <rdf:Description rdf:about="http://data.llgc.org.uk/lla/id/event/birth/22980-6481-3">
    <rdf:type rdf:resource="http://purl.org/vocab/bio/0.1/Birth"/>
    <bio:place xml:lang="en">Borth</bio:place>
    <bio:agent rdf:resource="http://data.llgc.org.uk/lla/id/mariner/22980-6481-3"/>
  </rdf:Description>
  <rdf:Description rdf:about="http://data.llgc.org.uk/lla/id/event/joining/22980-6481-3">
    <rdf:type rdf:resource="http://data.llgc.org.uk/lla/def#ShipJoiningEvent"/>
    <dc:date rdf:datatype="http://www.w3.org/2001/XMLSchema#dateTime">1873-01-14</dc:date>
    <bio:place xml:lang="en">Runcorn</bio:place>
    <lla:hasCapacity xml:lang="en">Boatswain</lla:hasCapacity>
    <lla:involvesMariner rdf:resource="http://data.llgc.org.uk/lla/id/mariner/22980-6481-3"/>
    <lla:recordedIn rdf:resource="http://data.llgc.org.uk/lla/id/logbookentry/22980-6481-3"/>
    <lla:involvesShip rdf:resource="http://data.llgc.org.uk/lla/id/ship/22980"/>
  </rdf:Description>
  <rdf:Description rdf:about="http://data.llgc.org.uk/lla/id/event/leaving/22980-6481-3">
    <rdf:type rdf:resource="http://data.llgc.org.uk/lla/def#ShipLeavingEvent"/>
    <dc:date rdf:datatype="http://www.w3.org/2001/XMLSchema#dateTime">1873-04-29</dc:date>
    <bio:place xml:lang="en">Llanelly</bio:place>
    <lla:involvesMariner rdf:resource="http://data.llgc.org.uk/lla/id/mariner/22980-6481-3"/>
    <lla:recordedIn rdf:resource="http://data.llgc.org.uk/lla/id/logbookentry/22980-6481-3"/>
    <lla:involvesShip rdf:resource="http://data.llgc.org.uk/lla/id/ship/22980"/>
  </rdf:Description>
  <rdf:Description rdf:about="http://data.llgc.org.uk/lla/id/logbookentry/22980-6481-4">
    <rdf:type rdf:resource="http://data.llgc.org.uk/lla/def#LogbookEntry"/>
    <dcterms:isPartOf rdf:resource="http://data.llgc.org.uk/lla/id/logbook/22980-6481"/>
    <lla:logbookAge rdf:datatype="http://www.w3.org/2001/XMLSchema#int">55</lla:logbookAge>
    <lla:describesEvent rdf:resource="http://data.llgc.org.uk/lla/id/event/joining/22980-6481-4"/>
    <lla:describesEvent rdf:resource="http://data.llgc.org.uk/lla/id/event/leaving/22980-6481-4"/>
    <lla:reason xml:lang="en">Discharged</lla:reason>
    <lla:mark rdf:datatype="http://www.w3.org/2001/XMLSchema#boolean">false</lla:mark>
  </rdf:Description>
  <rdf:Description rdf:about="http://data.llgc.org.uk/lla/id/mariner/22980-6481-4">
    <rdf:type rdf:resource="http://data.llgc.org.uk/lla/def#Mariner"/>
    <foaf:name>John Davies</foaf:name>
    <bio:Birth rdf:resource="http://data.llgc.org.uk/lla/id/event/birth/22980-6481-4"/>
  </rdf:Description>
  <rdf:Description rdf:about="http://data.llgc.org.uk/lla/id/event/birth/22980-6481-4">
    <rdf:type rdf:resource="http://purl.org/vocab/bio/0.1/Birth"/>
    <bio:place xml:lang="en">Aberystwyth</bio:place>
    <bio:agent rdf:resource="http://data.llgc.org.uk/lla/id/mariner/22980-6481-4"/>
  </rdf:Description>
  <rdf:Description rdf:about="http://data.llgc.org.uk/lla/id/event/joining/22980-6481-4">
    <rdf:type rdf:resource="http://data.llgc.org.uk/lla/def#ShipJoiningEvent"/>
    <dc:date rdf:datatype="http://www.w3.org/2001/XMLSchema#dateTime">1873-01-14</dc:date>
    <bio:place xml:lang="en">Runcorn</bio:place>
    <lla:hasCapacity xml:lang="en">Cook &amp; Steward</lla:hasCapacity>
    <lla:involvesMariner rdf:resource="http://data.llgc.org.uk/lla/id/mariner/22980-6481-4"/>
    <lla:recordedIn rdf:resource="http://data.llgc.org.uk/lla/id/logbookentry/22980-6481-4"/>
    <lla:involvesShip rdf:resource="http://data.llgc.org.uk/lla/id/ship/22980"/>
  </rdf:Description>
  <rdf:Description rdf:about="http://data.llgc.org.uk/lla/id/event/leaving/22980-6481-4">
    <rdf:type rdf:resource="http://data.llgc.org.uk/lla/def#ShipLeavingEvent"/>
    <dc:date rdf:datatype="http://www.w3.org/2001/XMLSchema#dateTime">1873-04-29</dc:date>
    <bio:place xml:lang="en">Llanelly</bio:place>
    <lla:involvesMariner rdf:resource="http://data.llgc.org.uk/lla/id/mariner/22980-6481-4"/>
    <lla:recordedIn rdf:resource="http://data.llgc.org.uk/lla/id/logbookentry/22980-6481-4"/>
    <lla:involvesShip rdf:resource="http://data.llgc.org.uk/lla/id/ship/22980"/>
  </rdf:Description>
  <rdf:Description rdf:about="http://data.llgc.org.uk/lla/id/logbookentry/22980-6481-5">
    <rdf:type rdf:resource="http://data.llgc.org.uk/lla/def#LogbookEntry"/>
    <dcterms:isPartOf rdf:resource="http://data.llgc.org.uk/lla/id/logbook/22980-6481"/>
    <lla:logbookAge rdf:datatype="http://www.w3.org/2001/XMLSchema#int">24</lla:logbookAge>
    <lla:describesEvent rdf:resource="http://data.llgc.org.uk/lla/id/event/joining/22980-6481-5"/>
    <lla:describesEvent rdf:resource="http://data.llgc.org.uk/lla/id/event/leaving/22980-6481-5"/>
    <lla:reason xml:lang="en">Discharged</lla:reason>
    <lla:mark rdf:datatype="http://www.w3.org/2001/XMLSchema#boolean">false</lla:mark>
  </rdf:Description>
  <rdf:Description rdf:about="http://data.llgc.org.uk/lla/id/mariner/22980-6481-5">
    <rdf:type rdf:resource="http://data.llgc.org.uk/lla/def#Mariner"/>
    <foaf:name>John Shilton</foaf:name>
    <bio:Birth rdf:resource="http://data.llgc.org.uk/lla/id/event/birth/22980-6481-5"/>
  </rdf:Description>
  <rdf:Description rdf:about="http://data.llgc.org.uk/lla/id/event/birth/22980-6481-5">
    <rdf:type rdf:resource="http://purl.org/vocab/bio/0.1/Birth"/>
    <bio:place xml:lang="en">Plymouth</bio:place>
    <bio:agent rdf:resource="http://data.llgc.org.uk/lla/id/mariner/22980-6481-5"/>
  </rdf:Description>
  <rdf:Description rdf:about="http://data.llgc.org.uk/lla/id/event/joining/22980-6481-5">
    <rdf:type rdf:resource="http://data.llgc.org.uk/lla/def#ShipJoiningEvent"/>
    <dc:date rdf:datatype="http://www.w3.org/2001/XMLSchema#dateTime">1873-01-14</dc:date>
    <bio:place xml:lang="en">Runcorn</bio:place>
    <lla:hasCapacity xml:lang="en">Able Seaman</lla:hasCapacity>
    <lla:involvesMariner rdf:resource="http://data.llgc.org.uk/lla/id/mariner/22980-6481-5"/>
    <lla:recordedIn rdf:resource="http://data.llgc.org.uk/lla/id/logbookentry/22980-6481-5"/>
    <lla:involvesShip rdf:resource="http://data.llgc.org.uk/lla/id/ship/22980"/>
  </rdf:Description>
  <rdf:Description rdf:about="http://data.llgc.org.uk/lla/id/event/leaving/22980-6481-5">
    <rdf:type rdf:resource="http://data.llgc.org.uk/lla/def#ShipLeavingEvent"/>
    <dc:date rdf:datatype="http://www.w3.org/2001/XMLSchema#dateTime">1873-04-29</dc:date>
    <bio:place xml:lang="en">Llanelly</bio:place>
    <lla:involvesMariner rdf:resource="http://data.llgc.org.uk/lla/id/mariner/22980-6481-5"/>
    <lla:recordedIn rdf:resource="http://data.llgc.org.uk/lla/id/logbookentry/22980-6481-5"/>
    <lla:involvesShip rdf:resource="http://data.llgc.org.uk/lla/id/ship/22980"/>
  </rdf:Description>
  <rdf:Description rdf:about="http://data.llgc.org.uk/lla/id/logbookentry/22980-6481-6">
    <rdf:type rdf:resource="http://data.llgc.org.uk/lla/def#LogbookEntry"/>
    <dcterms:isPartOf rdf:resource="http://data.llgc.org.uk/lla/id/logbook/22980-6481"/>
    <lla:logbookAge rdf:datatype="http://www.w3.org/2001/XMLSchema#int">23</lla:logbookAge>
    <lla:describesEvent rdf:resource="http://data.llgc.org.uk/lla/id/event/joining/22980-6481-6"/>
    <lla:describesEvent rdf:resource="http://data.llgc.org.uk/lla/id/event/leaving/22980-6481-6"/>
    <lla:reason xml:lang="en">Discharged</lla:reason>
    <lla:mark rdf:datatype="http://www.w3.org/2001/XMLSchema#boolean">false</lla:mark>
  </rdf:Description>
  <rdf:Description rdf:about="http://data.llgc.org.uk/lla/id/mariner/22980-6481-6">
    <rdf:type rdf:resource="http://data.llgc.org.uk/lla/def#Mariner"/>
    <foaf:name>William Pierce</foaf:name>
    <bio:Birth rdf:resource="http://data.llgc.org.uk/lla/id/event/birth/22980-6481-6"/>
  </rdf:Description>
  <rdf:Description rdf:about="http://data.llgc.org.uk/lla/id/event/birth/22980-6481-6">
    <rdf:type rdf:resource="http://purl.org/vocab/bio/0.1/Birth"/>
    <bio:place xml:lang="en">Borth</bio:place>
    <bio:agent rdf:resource="http://data.llgc.org.uk/lla/id/mariner/22980-6481-6"/>
  </rdf:Description>
  <rdf:Description rdf:about="http://data.llgc.org.uk/lla/id/event/joining/22980-6481-6">
    <rdf:type rdf:resource="http://data.llgc.org.uk/lla/def#ShipJoiningEvent"/>
    <dc:date rdf:datatype="http://www.w3.org/2001/XMLSchema#dateTime">1873-01-14</dc:date>
    <bio:place xml:lang="en">Runcorn</bio:place>
    <lla:hasCapacity xml:lang="en">Able Seaman</lla:hasCapacity>
    <lla:involvesMariner rdf:resource="http://data.llgc.org.uk/lla/id/mariner/22980-6481-6"/>
    <lla:recordedIn rdf:resource="http://data.llgc.org.uk/lla/id/logbookentry/22980-6481-6"/>
    <lla:involvesShip rdf:resource="http://data.llgc.org.uk/lla/id/ship/22980"/>
  </rdf:Description>
  <rdf:Description rdf:about="http://data.llgc.org.uk/lla/id/event/leaving/22980-6481-6">
    <rdf:type rdf:resource="http://data.llgc.org.uk/lla/def#ShipLeavingEvent"/>
    <dc:date rdf:datatype="http://www.w3.org/2001/XMLSchema#dateTime">1873-04-29</dc:date>
    <bio:place xml:lang="en">Llanelly</bio:place>
    <lla:involvesMariner rdf:resource="http://data.llgc.org.uk/lla/id/mariner/22980-6481-6"/>
    <lla:recordedIn rdf:resource="http://data.llgc.org.uk/lla/id/logbookentry/22980-6481-6"/>
    <lla:involvesShip rdf:resource="http://data.llgc.org.uk/lla/id/ship/22980"/>
  </rdf:Description>
  <rdf:Description rdf:about="http://data.llgc.org.uk/lla/id/logbookentry/22980-6481-7">
    <rdf:type rdf:resource="http://data.llgc.org.uk/lla/def#LogbookEntry"/>
    <dcterms:isPartOf rdf:resource="http://data.llgc.org.uk/lla/id/logbook/22980-6481"/>
    <lla:logbookAge rdf:datatype="http://www.w3.org/2001/XMLSchema#int">26</lla:logbookAge>
    <lla:describesEvent rdf:resource="http://data.llgc.org.uk/lla/id/event/joining/22980-6481-7"/>
    <lla:describesEvent rdf:resource="http://data.llgc.org.uk/lla/id/event/leaving/22980-6481-7"/>
    <lla:reason xml:lang="en">Discharged</lla:reason>
    <lla:mark rdf:datatype="http://www.w3.org/2001/XMLSchema#boolean">false</lla:mark>
  </rdf:Description>
  <rdf:Description rdf:about="http://data.llgc.org.uk/lla/id/mariner/22980-6481-7">
    <rdf:type rdf:resource="http://data.llgc.org.uk/lla/def#Mariner"/>
    <foaf:name>John Davies</foaf:name>
    <bio:Birth rdf:resource="http://data.llgc.org.uk/lla/id/event/birth/22980-6481-7"/>
  </rdf:Description>
  <rdf:Description rdf:about="http://data.llgc.org.uk/lla/id/event/birth/22980-6481-7">
    <rdf:type rdf:resource="http://purl.org/vocab/bio/0.1/Birth"/>
    <bio:place xml:lang="en">Aberystwyth</bio:place>
    <bio:agent rdf:resource="http://data.llgc.org.uk/lla/id/mariner/22980-6481-7"/>
  </rdf:Description>
  <rdf:Description rdf:about="http://data.llgc.org.uk/lla/id/event/joining/22980-6481-7">
    <rdf:type rdf:resource="http://data.llgc.org.uk/lla/def#ShipJoiningEvent"/>
    <dc:date rdf:datatype="http://www.w3.org/2001/XMLSchema#dateTime">1873-01-14</dc:date>
    <bio:place xml:lang="en">Runcorn</bio:place>
    <lla:hasCapacity xml:lang="en">Able Seaman</lla:hasCapacity>
    <lla:involvesMariner rdf:resource="http://data.llgc.org.uk/lla/id/mariner/22980-6481-7"/>
    <lla:recordedIn rdf:resource="http://data.llgc.org.uk/lla/id/logbookentry/22980-6481-7"/>
    <lla:involvesShip rdf:resource="http://data.llgc.org.uk/lla/id/ship/22980"/>
  </rdf:Description>
  <rdf:Description rdf:about="http://data.llgc.org.uk/lla/id/event/leaving/22980-6481-7">
    <rdf:type rdf:resource="http://data.llgc.org.uk/lla/def#ShipLeavingEvent"/>
    <dc:date rdf:datatype="http://www.w3.org/2001/XMLSchema#dateTime">1873-04-29</dc:date>
    <bio:place xml:lang="en">Llanelly</bio:place>
    <lla:involvesMariner rdf:resource="http://data.llgc.org.uk/lla/id/mariner/22980-6481-7"/>
    <lla:recordedIn rdf:resource="http://data.llgc.org.uk/lla/id/logbookentry/22980-6481-7"/>
    <lla:involvesShip rdf:resource="http://data.llgc.org.uk/lla/id/ship/22980"/>
  </rdf:Description>
  <rdf:Description rdf:about="http://data.llgc.org.uk/lla/id/logbook/22980-6482">
    <rdf:type rdf:resource="http://data.llgc.org.uk/lla/def#Logbook"/>
    <dcterms:identifier rdf:datatype="http://www.w3.org/2001/XMLSchema#string">64-8-2</dcterms:identifier>
    <dcterms:isPartOf rdf:resource="http://data.llgc.org.uk/lla/id/archivefile/64-8_vtls004625393"/>
    <dcterms:hasPart rdf:resource="http://data.llgc.org.uk/lla/id/logbookentry/22980-6482-1"/>
    <dcterms:hasPart rdf:resource="http://data.llgc.org.uk/lla/id/logbookentry/22980-6482-2"/>
    <dcterms:hasPart rdf:resource="http://data.llgc.org.uk/lla/id/logbookentry/22980-6482-3"/>
    <dcterms:hasPart rdf:resource="http://data.llgc.org.uk/lla/id/logbookentry/22980-6482-4"/>
    <dcterms:hasPart rdf:resource="http://data.llgc.org.uk/lla/id/logbookentry/22980-6482-5"/>
    <dcterms:hasPart rdf:resource="http://data.llgc.org.uk/lla/id/logbookentry/22980-6482-6"/>
    <dcterms:hasPart rdf:resource="http://data.llgc.org.uk/lla/id/logbookentry/22980-6482-7"/>
  </rdf:Description>
  <rdf:Description rdf:about="http://data.llgc.org.uk/lla/id/logbookentry/22980-6482-1">
    <rdf:type rdf:resource="http://data.llgc.org.uk/lla/def#LogbookEntry"/>
    <dcterms:isPartOf rdf:resource="http://data.llgc.org.uk/lla/id/logbook/22980-6482"/>
    <lla:logbookAge rdf:datatype="http://www.w3.org/2001/XMLSchema#int">35</lla:logbookAge>
    <lla:describesEvent rdf:resource="http://data.llgc.org.uk/lla/id/event/joining/22980-6482-1"/>
    <lla:reason xml:lang="en">Continued</lla:reason>
    <lla:mark rdf:datatype="http://www.w3.org/2001/XMLSchema#boolean">false</lla:mark>
  </rdf:Description>
  <rdf:Description rdf:about="http://data.llgc.org.uk/lla/id/mariner/22980-6482-1">
    <rdf:type rdf:resource="http://data.llgc.org.uk/lla/def#Mariner"/>
    <foaf:name>Evan Jones</foaf:name>
    <bio:Birth rdf:resource="http://data.llgc.org.uk/lla/id/event/birth/22980-6482-1"/>
  </rdf:Description>
  <rdf:Description rdf:about="http://data.llgc.org.uk/lla/id/event/birth/22980-6482-1">
    <rdf:type rdf:resource="http://purl.org/vocab/bio/0.1/Birth"/>
    <bio:place xml:lang="en">Aberystwyth</bio:place>
    <bio:agent rdf:resource="http://data.llgc.org.uk/lla/id/mariner/22980-6482-1"/>
  </rdf:Description>
  <rdf:Description rdf:about="http://data.llgc.org.uk/lla/id/event/joining/22980-6482-1">
    <rdf:type rdf:resource="http://data.llgc.org.uk/lla/def#ShipJoiningEvent"/>
    <dc:date rdf:datatype="http://www.w3.org/2001/XMLSchema#dateTime">Continued</dc:date>
    <lla:hasCapacity xml:lang="en">Master</lla:hasCapacity>
    <lla:involvesMariner rdf:resource="http://data.llgc.org.uk/lla/id/mariner/22980-6482-1"/>
    <lla:recordedIn rdf:resource="http://data.llgc.org.uk/lla/id/logbookentry/22980-6482-1"/>
    <lla:involvesShip rdf:resource="http://data.llgc.org.uk/lla/id/ship/22980"/>
  </rdf:Description>
  <rdf:Description rdf:about="http://data.llgc.org.uk/lla/id/logbookentry/22980-6482-2">
    <rdf:type rdf:resource="http://data.llgc.org.uk/lla/def#LogbookEntry"/>
    <dcterms:isPartOf rdf:resource="http://data.llgc.org.uk/lla/id/logbook/22980-6482"/>
    <lla:logbookAge rdf:datatype="http://www.w3.org/2001/XMLSchema#int">32</lla:logbookAge>
    <lla:describesEvent rdf:resource="http://data.llgc.org.uk/lla/id/event/joining/22980-6482-2"/>
    <lla:describesEvent rdf:resource="http://data.llgc.org.uk/lla/id/event/leaving/22980-6482-2"/>
    <lla:reason xml:lang="en">Discharged</lla:reason>
    <lla:mark rdf:datatype="http://www.w3.org/2001/XMLSchema#boolean">false</lla:mark>
  </rdf:Description>
  <rdf:Description rdf:about="http://data.llgc.org.uk/lla/id/mariner/22980-6482-2">
    <rdf:type rdf:resource="http://data.llgc.org.uk/lla/def#Mariner"/>
    <foaf:name>Edward Jones</foaf:name>
    <bio:Birth rdf:resource="http://data.llgc.org.uk/lla/id/event/birth/22980-6482-2"/>
  </rdf:Description>
  <rdf:Description rdf:about="http://data.llgc.org.uk/lla/id/event/birth/22980-6482-2">
    <rdf:type rdf:resource="http://purl.org/vocab/bio/0.1/Birth"/>
    <bio:place xml:lang="en">Aberystwyth</bio:place>
    <bio:agent rdf:resource="http://data.llgc.org.uk/lla/id/mariner/22980-6482-2"/>
  </rdf:Description>
  <rdf:Description rdf:about="http://data.llgc.org.uk/lla/id/event/joining/22980-6482-2">
    <rdf:type rdf:resource="http://data.llgc.org.uk/lla/def#ShipJoiningEvent"/>
    <dc:date rdf:datatype="http://www.w3.org/2001/XMLSchema#dateTime">1873-05-27</dc:date>
    <bio:place xml:lang="en">Llanelly</bio:place>
    <lla:hasCapacity xml:lang="en">Mate</lla:hasCapacity>
    <lla:involvesMariner rdf:resource="http://data.llgc.org.uk/lla/id/mariner/22980-6482-2"/>
    <lla:recordedIn rdf:resource="http://data.llgc.org.uk/lla/id/logbookentry/22980-6482-2"/>
    <lla:involvesShip rdf:resource="http://data.llgc.org.uk/lla/id/ship/22980"/>
  </rdf:Description>
  <rdf:Description rdf:about="http://data.llgc.org.uk/lla/id/event/leaving/22980-6482-2">
    <rdf:type rdf:resource="http://data.llgc.org.uk/lla/def#ShipLeavingEvent"/>
    <dc:date rdf:datatype="http://www.w3.org/2001/XMLSchema#dateTime">1873-07-03</dc:date>
    <bio:place xml:lang="en">Llanelly</bio:place>
    <lla:involvesMariner rdf:resource="http://data.llgc.org.uk/lla/id/mariner/22980-6482-2"/>
    <lla:recordedIn rdf:resource="http://data.llgc.org.uk/lla/id/logbookentry/22980-6482-2"/>
    <lla:involvesShip rdf:resource="http://data.llgc.org.uk/lla/id/ship/22980"/>
  </rdf:Description>
  <rdf:Description rdf:about="http://data.llgc.org.uk/lla/id/logbookentry/22980-6482-3">
    <rdf:type rdf:resource="http://data.llgc.org.uk/lla/def#LogbookEntry"/>
    <dcterms:isPartOf rdf:resource="http://data.llgc.org.uk/lla/id/logbook/22980-6482"/>
    <lla:logbookAge rdf:datatype="http://www.w3.org/2001/XMLSchema#int">60</lla:logbookAge>
    <lla:describesEvent rdf:resource="http://data.llgc.org.uk/lla/id/event/joining/22980-6482-3"/>
    <lla:describesEvent rdf:resource="http://data.llgc.org.uk/lla/id/event/leaving/22980-6482-3"/>
    <lla:reason xml:lang="en">Discharged</lla:reason>
    <lla:mark rdf:datatype="http://www.w3.org/2001/XMLSchema#boolean">true</lla:mark>
  </rdf:Description>
  <rdf:Description rdf:about="http://data.llgc.org.uk/lla/id/mariner/22980-6482-3">
    <rdf:type rdf:resource="http://data.llgc.org.uk/lla/def#Mariner"/>
    <foaf:name>John Davies</foaf:name>
    <bio:Birth rdf:resource="http://data.llgc.org.uk/lla/id/event/birth/22980-6482-3"/>
  </rdf:Description>
  <rdf:Description rdf:about="http://data.llgc.org.uk/lla/id/event/birth/22980-6482-3">
    <rdf:type rdf:resource="http://purl.org/vocab/bio/0.1/Birth"/>
    <bio:place xml:lang="en">Aberystwyth</bio:place>
    <bio:agent rdf:resource="http://data.llgc.org.uk/lla/id/mariner/22980-6482-3"/>
  </rdf:Description>
  <rdf:Description rdf:about="http://data.llgc.org.uk/lla/id/event/joining/22980-6482-3">
    <rdf:type rdf:resource="http://data.llgc.org.uk/lla/def#ShipJoiningEvent"/>
    <dc:date rdf:datatype="http://www.w3.org/2001/XMLSchema#dateTime">1873-05-27</dc:date>
    <bio:place xml:lang="en">Llanelly</bio:place>
    <lla:hasCapacity xml:lang="en">Cook &amp; Steward</lla:hasCapacity>
    <lla:involvesMariner rdf:resource="http://data.llgc.org.uk/lla/id/mariner/22980-6482-3"/>
    <lla:recordedIn rdf:resource="http://data.llgc.org.uk/lla/id/logbookentry/22980-6482-3"/>
    <lla:involvesShip rdf:resource="http://data.llgc.org.uk/lla/id/ship/22980"/>
  </rdf:Description>
  <rdf:Description rdf:about="http://data.llgc.org.uk/lla/id/event/leaving/22980-6482-3">
    <rdf:type rdf:resource="http://data.llgc.org.uk/lla/def#ShipLeavingEvent"/>
    <dc:date rdf:datatype="http://www.w3.org/2001/XMLSchema#dateTime">1873-07-03</dc:date>
    <bio:place xml:lang="en">Llanelly</bio:place>
    <lla:involvesMariner rdf:resource="http://data.llgc.org.uk/lla/id/mariner/22980-6482-3"/>
    <lla:recordedIn rdf:resource="http://data.llgc.org.uk/lla/id/logbookentry/22980-6482-3"/>
    <lla:involvesShip rdf:resource="http://data.llgc.org.uk/lla/id/ship/22980"/>
  </rdf:Description>
  <rdf:Description rdf:about="http://data.llgc.org.uk/lla/id/logbookentry/22980-6482-4">
    <rdf:type rdf:resource="http://data.llgc.org.uk/lla/def#LogbookEntry"/>
    <dcterms:isPartOf rdf:resource="http://data.llgc.org.uk/lla/id/logbook/22980-6482"/>
    <lla:logbookAge rdf:datatype="http://www.w3.org/2001/XMLSchema#int">27</lla:logbookAge>
    <lla:describesEvent rdf:resource="http://data.llgc.org.uk/lla/id/event/joining/22980-6482-4"/>
    <lla:describesEvent rdf:resource="http://data.llgc.org.uk/lla/id/event/leaving/22980-6482-4"/>
    <lla:reason xml:lang="en">Discharged</lla:reason>
    <lla:mark rdf:datatype="http://www.w3.org/2001/XMLSchema#boolean">false</lla:mark>
  </rdf:Description>
  <rdf:Description rdf:about="http://data.llgc.org.uk/lla/id/mariner/22980-6482-4">
    <rdf:type rdf:resource="http://data.llgc.org.uk/lla/def#Mariner"/>
    <foaf:name>John Davies</foaf:name>
    <bio:Birth rdf:resource="http://data.llgc.org.uk/lla/id/event/birth/22980-6482-4"/>
  </rdf:Description>
  <rdf:Description rdf:about="http://data.llgc.org.uk/lla/id/event/birth/22980-6482-4">
    <rdf:type rdf:resource="http://purl.org/vocab/bio/0.1/Birth"/>
    <bio:place xml:lang="en">Aberystwyth</bio:place>
    <bio:agent rdf:resource="http://data.llgc.org.uk/lla/id/mariner/22980-6482-4"/>
  </rdf:Description>
  <rdf:Description rdf:about="http://data.llgc.org.uk/lla/id/event/joining/22980-6482-4">
    <rdf:type rdf:resource="http://data.llgc.org.uk/lla/def#ShipJoiningEvent"/>
    <dc:date rdf:datatype="http://www.w3.org/2001/XMLSchema#dateTime">1873-05-27</dc:date>
    <bio:place xml:lang="en">Llanelly</bio:place>
    <lla:hasCapacity xml:lang="en">Able Seaman</lla:hasCapacity>
    <lla:involvesMariner rdf:resource="http://data.llgc.org.uk/lla/id/mariner/22980-6482-4"/>
    <lla:recordedIn rdf:resource="http://data.llgc.org.uk/lla/id/logbookentry/22980-6482-4"/>
    <lla:involvesShip rdf:resource="http://data.llgc.org.uk/lla/id/ship/22980"/>
  </rdf:Description>
  <rdf:Description rdf:about="http://data.llgc.org.uk/lla/id/event/leaving/22980-6482-4">
    <rdf:type rdf:resource="http://data.llgc.org.uk/lla/def#ShipLeavingEvent"/>
    <dc:date rdf:datatype="http://www.w3.org/2001/XMLSchema#dateTime">1873-07-03</dc:date>
    <bio:place xml:lang="en">Llanelly</bio:place>
    <lla:involvesMariner rdf:resource="http://data.llgc.org.uk/lla/id/mariner/22980-6482-4"/>
    <lla:recordedIn rdf:resource="http://data.llgc.org.uk/lla/id/logbookentry/22980-6482-4"/>
    <lla:involvesShip rdf:resource="http://data.llgc.org.uk/lla/id/ship/22980"/>
  </rdf:Description>
  <rdf:Description rdf:about="http://data.llgc.org.uk/lla/id/logbookentry/22980-6482-5">
    <rdf:type rdf:resource="http://data.llgc.org.uk/lla/def#LogbookEntry"/>
    <dcterms:isPartOf rdf:resource="http://data.llgc.org.uk/lla/id/logbook/22980-6482"/>
    <lla:logbookAge rdf:datatype="http://www.w3.org/2001/XMLSchema#int">20</lla:logbookAge>
    <lla:describesEvent rdf:resource="http://data.llgc.org.uk/lla/id/event/leaving/22980-6482-5-2"/>
    <lla:describesEvent rdf:resource="http://data.llgc.org.uk/lla/id/event/joining/22980-6482-5"/>
    <lla:describesEvent rdf:resource="http://data.llgc.org.uk/lla/id/event/leaving/22980-6482-5"/>
    <lla:reason xml:lang="en">Discharged</lla:reason>
    <lla:mark rdf:datatype="http://www.w3.org/2001/XMLSchema#boolean">false</lla:mark>
  </rdf:Description>
  <rdf:Description rdf:about="http://data.llgc.org.uk/lla/id/mariner/22980-6482-5">
    <rdf:type rdf:resource="http://data.llgc.org.uk/lla/def#Mariner"/>
    <foaf:name>W Williams</foaf:name>
    <bio:Birth rdf:resource="http://data.llgc.org.uk/lla/id/event/birth/22980-6482-5"/>
  </rdf:Description>
  <rdf:Description rdf:about="http://data.llgc.org.uk/lla/id/event/birth/22980-6482-5">
    <rdf:type rdf:resource="http://purl.org/vocab/bio/0.1/Birth"/>
    <bio:place xml:lang="en">Borth</bio:place>
    <bio:agent rdf:resource="http://data.llgc.org.uk/lla/id/mariner/22980-6482-5"/>
  </rdf:Description>
  <rdf:Description rdf:about="http://data.llgc.org.uk/lla/id/event/leaving/22980-6482-5-2">
    <rdf:type rdf:resource="http://data.llgc.org.uk/lla/def#ShipLeavingEvent"/>
    <dc:date rdf:datatype="http://www.w3.org/2001/XMLSchema#dateTime">1873</dc:date>
    <lla:involvesMariner rdf:resource="http://data.llgc.org.uk/lla/id/mariner/22980-6482-5"/>
    <lla:recordedIn rdf:resource="http://data.llgc.org.uk/lla/id/logbookentry/22980-6482-5"/>
    <lla:involvesShip rdf:resource="http://data.llgc.org.uk/lla/id/ship/22980-6482-5"/>
  </rdf:Description>
  <rdf:Description rdf:about="http://data.llgc.org.uk/lla/id/ship/22980-6482-5">
    <rdf:type rdf:resource="http://data.llgc.org.uk/lla/def#Ship"/>
    <lla:hasHomePort xml:lang="en">Glasgow</lla:hasHomePort>
    <lla:mentionedIn rdf:resource="http://data.llgc.org.uk/lla/id/archivefile/64-8_vtls004625393"/>
    <lla:mentionedIn rdf:resource="http://data.llgc.org.uk/lla/id/logbook/22980-6482"/>
    <lla:mentionedIn rdf:resource="http://data.llgc.org.uk/lla/id/logbookentry/22980-6482-5"/>
    <rdfs:label xml:lang="en">Nola</rdfs:label>
  </rdf:Description>
  <rdf:Description rdf:about="http://data.llgc.org.uk/lla/id/event/joining/22980-6482-5">
    <rdf:type rdf:resource="http://data.llgc.org.uk/lla/def#ShipJoiningEvent"/>
    <dc:date rdf:datatype="http://www.w3.org/2001/XMLSchema#dateTime">1873-05-27</dc:date>
    <bio:place xml:lang="en">Llanelly</bio:place>
    <lla:hasCapacity xml:lang="en">Able Seaman</lla:hasCapacity>
    <lla:involvesMariner rdf:resource="http://data.llgc.org.uk/lla/id/mariner/22980-6482-5"/>
    <lla:recordedIn rdf:resource="http://data.llgc.org.uk/lla/id/logbookentry/22980-6482-5"/>
    <lla:involvesShip rdf:resource="http://data.llgc.org.uk/lla/id/ship/22980"/>
    <lla:hasPreviousIndividualEvent rdf:resource="http://data.llgc.org.uk/lla/id/event/leaving/22980-6482-5-2"/>
  </rdf:Description>
  <rdf:Description rdf:about="http://data.llgc.org.uk/lla/id/event/leaving/22980-6482-5">
    <rdf:type rdf:resource="http://data.llgc.org.uk/lla/def#ShipLeavingEvent"/>
    <dc:date rdf:datatype="http://www.w3.org/2001/XMLSchema#dateTime">1873-07-03</dc:date>
    <bio:place xml:lang="en">Llanelly</bio:place>
    <lla:involvesMariner rdf:resource="http://data.llgc.org.uk/lla/id/mariner/22980-6482-5"/>
    <lla:recordedIn rdf:resource="http://data.llgc.org.uk/lla/id/logbookentry/22980-6482-5"/>
    <lla:involvesShip rdf:resource="http://data.llgc.org.uk/lla/id/ship/22980"/>
  </rdf:Description>
  <rdf:Description rdf:about="http://data.llgc.org.uk/lla/id/logbookentry/22980-6482-6">
    <rdf:type rdf:resource="http://data.llgc.org.uk/lla/def#LogbookEntry"/>
    <dcterms:isPartOf rdf:resource="http://data.llgc.org.uk/lla/id/logbook/22980-6482"/>
    <lla:logbookAge rdf:datatype="http://www.w3.org/2001/XMLSchema#int">22</lla:logbookAge>
    <lla:describesEvent rdf:resource="http://data.llgc.org.uk/lla/id/event/leaving/22980-6482-6-2"/>
    <lla:describesEvent rdf:resource="http://data.llgc.org.uk/lla/id/event/joining/22980-6482-6"/>
    <lla:describesEvent rdf:resource="http://data.llgc.org.uk/lla/id/event/leaving/22980-6482-6"/>
    <lla:reason xml:lang="en">Discharged</lla:reason>
    <lla:mark rdf:datatype="http://www.w3.org/2001/XMLSchema#boolean">false</lla:mark>
  </rdf:Description>
  <rdf:Description rdf:about="http://data.llgc.org.uk/lla/id/mariner/22980-6482-6">
    <rdf:type rdf:resource="http://data.llgc.org.uk/lla/def#Mariner"/>
    <foaf:name>John Roberts</foaf:name>
    <bio:Birth rdf:resource="http://data.llgc.org.uk/lla/id/event/birth/22980-6482-6"/>
  </rdf:Description>
  <rdf:Description rdf:about="http://data.llgc.org.uk/lla/id/event/birth/22980-6482-6">
    <rdf:type rdf:resource="http://purl.org/vocab/bio/0.1/Birth"/>
    <bio:place xml:lang="en">Aberystwyth</bio:place>
    <bio:agent rdf:resource="http://data.llgc.org.uk/lla/id/mariner/22980-6482-6"/>
  </rdf:Description>
  <rdf:Description rdf:about="http://data.llgc.org.uk/lla/id/event/leaving/22980-6482-6-2">
    <rdf:type rdf:resource="http://data.llgc.org.uk/lla/def#ShipLeavingEvent"/>
    <dc:date rdf:datatype="http://www.w3.org/2001/XMLSchema#dateTime">1873</dc:date>
    <lla:involvesMariner rdf:resource="http://data.llgc.org.uk/lla/id/mariner/22980-6482-6"/>
    <lla:recordedIn rdf:resource="http://data.llgc.org.uk/lla/id/logbookentry/22980-6482-6"/>
    <lla:involvesShip rdf:resource="http://data.llgc.org.uk/lla/id/ship/22980-6482-6"/>
  </rdf:Description>
  <rdf:Description rdf:about="http://data.llgc.org.uk/lla/id/ship/22980-6482-6">
    <rdf:type rdf:resource="http://data.llgc.org.uk/lla/def#Ship"/>
    <lla:hasHomePort xml:lang="en">Aberystwyth</lla:hasHomePort>
    <lla:mentionedIn rdf:resource="http://data.llgc.org.uk/lla/id/archivefile/64-8_vtls004625393"/>
    <lla:mentionedIn rdf:resource="http://data.llgc.org.uk/lla/id/logbook/22980-6482"/>
    <lla:mentionedIn rdf:resource="http://data.llgc.org.uk/lla/id/logbookentry/22980-6482-6"/>
    <rdfs:label xml:lang="en">Glenalvon</rdfs:label>
  </rdf:Description>
  <rdf:Description rdf:about="http://data.llgc.org.uk/lla/id/event/joining/22980-6482-6">
    <rdf:type rdf:resource="http://data.llgc.org.uk/lla/def#ShipJoiningEvent"/>
    <dc:date rdf:datatype="http://www.w3.org/2001/XMLSchema#dateTime">1873-05-27</dc:date>
    <bio:place xml:lang="en">Llanelly</bio:place>
    <lla:hasCapacity xml:lang="en">Able Seaman</lla:hasCapacity>
    <lla:involvesMariner rdf:resource="http://data.llgc.org.uk/lla/id/mariner/22980-6482-6"/>
    <lla:recordedIn rdf:resource="http://data.llgc.org.uk/lla/id/logbookentry/22980-6482-6"/>
    <lla:involvesShip rdf:resource="http://data.llgc.org.uk/lla/id/ship/22980"/>
    <lla:hasPreviousIndividualEvent rdf:resource="http://data.llgc.org.uk/lla/id/event/leaving/22980-6482-6-2"/>
  </rdf:Description>
  <rdf:Description rdf:about="http://data.llgc.org.uk/lla/id/event/leaving/22980-6482-6">
    <rdf:type rdf:resource="http://data.llgc.org.uk/lla/def#ShipLeavingEvent"/>
    <dc:date rdf:datatype="http://www.w3.org/2001/XMLSchema#dateTime">1873-07-03</dc:date>
    <bio:place xml:lang="en">Llanelly</bio:place>
    <lla:involvesMariner rdf:resource="http://data.llgc.org.uk/lla/id/mariner/22980-6482-6"/>
    <lla:recordedIn rdf:resource="http://data.llgc.org.uk/lla/id/logbookentry/22980-6482-6"/>
    <lla:involvesShip rdf:resource="http://data.llgc.org.uk/lla/id/ship/22980"/>
  </rdf:Description>
  <rdf:Description rdf:about="http://data.llgc.org.uk/lla/id/logbookentry/22980-6482-7">
    <rdf:type rdf:resource="http://data.llgc.org.uk/lla/def#LogbookEntry"/>
    <dcterms:isPartOf rdf:resource="http://data.llgc.org.uk/lla/id/logbook/22980-6482"/>
    <lla:logbookAge rdf:datatype="http://www.w3.org/2001/XMLSchema#int">18</lla:logbookAge>
    <lla:describesEvent rdf:resource="http://data.llgc.org.uk/lla/id/event/leaving/22980-6482-7-2"/>
    <lla:describesEvent rdf:resource="http://data.llgc.org.uk/lla/id/event/joining/22980-6482-7"/>
    <lla:describesEvent rdf:resource="http://data.llgc.org.uk/lla/id/event/leaving/22980-6482-7"/>
    <lla:reason xml:lang="en">Discharged</lla:reason>
    <lla:mark rdf:datatype="http://www.w3.org/2001/XMLSchema#boolean">false</lla:mark>
  </rdf:Description>
  <rdf:Description rdf:about="http://data.llgc.org.uk/lla/id/mariner/22980-6482-7">
    <rdf:type rdf:resource="http://data.llgc.org.uk/lla/def#Mariner"/>
    <foaf:name>William Jenkins</foaf:name>
    <bio:Birth rdf:resource="http://data.llgc.org.uk/lla/id/event/birth/22980-6482-7"/>
  </rdf:Description>
  <rdf:Description rdf:about="http://data.llgc.org.uk/lla/id/event/birth/22980-6482-7">
    <rdf:type rdf:resource="http://purl.org/vocab/bio/0.1/Birth"/>
    <bio:place xml:lang="en">Borth</bio:place>
    <bio:agent rdf:resource="http://data.llgc.org.uk/lla/id/mariner/22980-6482-7"/>
  </rdf:Description>
  <rdf:Description rdf:about="http://data.llgc.org.uk/lla/id/event/leaving/22980-6482-7-2">
    <rdf:type rdf:resource="http://data.llgc.org.uk/lla/def#ShipLeavingEvent"/>
    <dc:date rdf:datatype="http://www.w3.org/2001/XMLSchema#dateTime">1873</dc:date>
    <lla:involvesMariner rdf:resource="http://data.llgc.org.uk/lla/id/mariner/22980-6482-7"/>
    <lla:recordedIn rdf:resource="http://data.llgc.org.uk/lla/id/logbookentry/22980-6482-7"/>
    <lla:involvesShip rdf:resource="http://data.llgc.org.uk/lla/id/ship/22980-6482-7"/>
  </rdf:Description>
  <rdf:Description rdf:about="http://data.llgc.org.uk/lla/id/ship/22980-6482-7">
    <rdf:type rdf:resource="http://data.llgc.org.uk/lla/def#Ship"/>
    <lla:hasHomePort xml:lang="en">Aberystwyth</lla:hasHomePort>
    <lla:mentionedIn rdf:resource="http://data.llgc.org.uk/lla/id/archivefile/64-8_vtls004625393"/>
    <lla:mentionedIn rdf:resource="http://data.llgc.org.uk/lla/id/logbook/22980-6482"/>
    <lla:mentionedIn rdf:resource="http://data.llgc.org.uk/lla/id/logbookentry/22980-6482-7"/>
    <rdfs:label xml:lang="en">Sarah Davies</rdfs:label>
  </rdf:Description>
  <rdf:Description rdf:about="http://data.llgc.org.uk/lla/id/event/joining/22980-6482-7">
    <rdf:type rdf:resource="http://data.llgc.org.uk/lla/def#ShipJoiningEvent"/>
    <dc:date rdf:datatype="http://www.w3.org/2001/XMLSchema#dateTime">1873-05-28</dc:date>
    <bio:place xml:lang="en">Llanelly</bio:place>
    <lla:hasCapacity xml:lang="en">Ordinary Seaman</lla:hasCapacity>
    <lla:involvesMariner rdf:resource="http://data.llgc.org.uk/lla/id/mariner/22980-6482-7"/>
    <lla:recordedIn rdf:resource="http://data.llgc.org.uk/lla/id/logbookentry/22980-6482-7"/>
    <lla:involvesShip rdf:resource="http://data.llgc.org.uk/lla/id/ship/22980"/>
    <lla:hasPreviousIndividualEvent rdf:resource="http://data.llgc.org.uk/lla/id/event/leaving/22980-6482-7-2"/>
  </rdf:Description>
  <rdf:Description rdf:about="http://data.llgc.org.uk/lla/id/event/leaving/22980-6482-7">
    <rdf:type rdf:resource="http://data.llgc.org.uk/lla/def#ShipLeavingEvent"/>
    <dc:date rdf:datatype="http://www.w3.org/2001/XMLSchema#dateTime">1873-07-03</dc:date>
    <bio:place xml:lang="en">Llanelly</bio:place>
    <lla:involvesMariner rdf:resource="http://data.llgc.org.uk/lla/id/mariner/22980-6482-7"/>
    <lla:recordedIn rdf:resource="http://data.llgc.org.uk/lla/id/logbookentry/22980-6482-7"/>
    <lla:involvesShip rdf:resource="http://data.llgc.org.uk/lla/id/ship/22980"/>
  </rdf:Description>
  <rdf:Description rdf:about="http://data.llgc.org.uk/lla/id/logbook/22980-6483">
    <rdf:type rdf:resource="http://data.llgc.org.uk/lla/def#Logbook"/>
    <dcterms:identifier rdf:datatype="http://www.w3.org/2001/XMLSchema#string">64-8-3</dcterms:identifier>
    <dcterms:isPartOf rdf:resource="http://data.llgc.org.uk/lla/id/archivefile/64-8_vtls004625393"/>
    <dcterms:hasPart rdf:resource="http://data.llgc.org.uk/lla/id/logbookentry/22980-6483-1"/>
    <dcterms:hasPart rdf:resource="http://data.llgc.org.uk/lla/id/logbookentry/22980-6483-2"/>
    <dcterms:hasPart rdf:resource="http://data.llgc.org.uk/lla/id/logbookentry/22980-6483-3"/>
    <dcterms:hasPart rdf:resource="http://data.llgc.org.uk/lla/id/logbookentry/22980-6483-4"/>
    <dcterms:hasPart rdf:resource="http://data.llgc.org.uk/lla/id/logbookentry/22980-6483-5"/>
    <dcterms:hasPart rdf:resource="http://data.llgc.org.uk/lla/id/logbookentry/22980-6483-6"/>
    <dcterms:hasPart rdf:resource="http://data.llgc.org.uk/lla/id/logbookentry/22980-6483-7"/>
    <dcterms:hasPart rdf:resource="http://data.llgc.org.uk/lla/id/logbookentry/22980-6483-8"/>
    <dcterms:hasPart rdf:resource="http://data.llgc.org.uk/lla/id/logbookentry/22980-6483-9"/>
  </rdf:Description>
  <rdf:Description rdf:about="http://data.llgc.org.uk/lla/id/logbookentry/22980-6483-1">
    <rdf:type rdf:resource="http://data.llgc.org.uk/lla/def#LogbookEntry"/>
    <dcterms:isPartOf rdf:resource="http://data.llgc.org.uk/lla/id/logbook/22980-6483"/>
    <lla:logbookAge rdf:datatype="http://www.w3.org/2001/XMLSchema#int">34</lla:logbookAge>
    <lla:describesEvent rdf:resource="http://data.llgc.org.uk/lla/id/event/leaving/22980-6483-1-2"/>
    <lla:describesEvent rdf:resource="http://data.llgc.org.uk/lla/id/event/joining/22980-6483-1"/>
    <lla:reason xml:lang="en">Remains on board</lla:reason>
    <lla:mark rdf:datatype="http://www.w3.org/2001/XMLSchema#boolean">false</lla:mark>
  </rdf:Description>
  <rdf:Description rdf:about="http://data.llgc.org.uk/lla/id/mariner/22980-6483-1">
    <rdf:type rdf:resource="http://data.llgc.org.uk/lla/def#Mariner"/>
    <foaf:name>Evan Lewis</foaf:name>
    <bio:Birth rdf:resource="http://data.llgc.org.uk/lla/id/event/birth/22980-6483-1"/>
  </rdf:Description>
  <rdf:Description rdf:about="http://data.llgc.org.uk/lla/id/event/birth/22980-6483-1">
    <rdf:type rdf:resource="http://purl.org/vocab/bio/0.1/Birth"/>
    <bio:place xml:lang="en">Cardigan</bio:place>
    <bio:agent rdf:resource="http://data.llgc.org.uk/lla/id/mariner/22980-6483-1"/>
  </rdf:Description>
  <rdf:Description rdf:about="http://data.llgc.org.uk/lla/id/event/leaving/22980-6483-1-2">
    <rdf:type rdf:resource="http://data.llgc.org.uk/lla/def#ShipLeavingEvent"/>
    <dc:date rdf:datatype="http://www.w3.org/2001/XMLSchema#dateTime">1873</dc:date>
    <lla:involvesMariner rdf:resource="http://data.llgc.org.uk/lla/id/mariner/22980-6483-1"/>
    <lla:recordedIn rdf:resource="http://data.llgc.org.uk/lla/id/logbookentry/22980-6483-1"/>
    <lla:involvesShip rdf:resource="http://data.llgc.org.uk/lla/id/ship/22980-6483-1"/>
  </rdf:Description>
  <rdf:Description rdf:about="http://data.llgc.org.uk/lla/id/ship/22980-6483-1">
    <rdf:type rdf:resource="http://data.llgc.org.uk/lla/def#Ship"/>
    <lla:hasHomePort xml:lang="en">Fowey</lla:hasHomePort>
    <lla:mentionedIn rdf:resource="http://data.llgc.org.uk/lla/id/archivefile/64-8_vtls004625393"/>
    <lla:mentionedIn rdf:resource="http://data.llgc.org.uk/lla/id/logbook/22980-6483"/>
    <lla:mentionedIn rdf:resource="http://data.llgc.org.uk/lla/id/logbookentry/22980-6483-1"/>
    <rdfs:label xml:lang="en">Elizabeth Moss</rdfs:label>
  </rdf:Description>
  <rdf:Description rdf:about="http://data.llgc.org.uk/lla/id/event/joining/22980-6483-1">
    <rdf:type rdf:resource="http://data.llgc.org.uk/lla/def#ShipJoiningEvent"/>
    <dc:date rdf:datatype="http://www.w3.org/2001/XMLSchema#dateTime">1873-07-15</dc:date>
    <bio:place xml:lang="en">Llanelly</bio:place>
    <lla:hasCapacity xml:lang="en">Master</lla:hasCapacity>
    <lla:involvesMariner rdf:resource="http://data.llgc.org.uk/lla/id/mariner/22980-6483-1"/>
    <lla:recordedIn rdf:resource="http://data.llgc.org.uk/lla/id/logbookentry/22980-6483-1"/>
    <lla:involvesShip rdf:resource="http://data.llgc.org.uk/lla/id/ship/22980"/>
    <lla:hasPreviousIndividualEvent rdf:resource="http://data.llgc.org.uk/lla/id/event/leaving/22980-6483-1-2"/>
  </rdf:Description>
  <rdf:Description rdf:about="http://data.llgc.org.uk/lla/id/logbookentry/22980-6483-2">
    <rdf:type rdf:resource="http://data.llgc.org.uk/lla/def#LogbookEntry"/>
    <dcterms:isPartOf rdf:resource="http://data.llgc.org.uk/lla/id/logbook/22980-6483"/>
    <lla:logbookAge rdf:datatype="http://www.w3.org/2001/XMLSchema#int">32</lla:logbookAge>
    <lla:describesEvent rdf:resource="http://data.llgc.org.uk/lla/id/event/joining/22980-6483-2"/>
    <lla:describesEvent rdf:resource="http://data.llgc.org.uk/lla/id/event/leaving/22980-6483-2"/>
    <lla:reason xml:lang="en">Paid off</lla:reason>
    <lla:mark rdf:datatype="http://www.w3.org/2001/XMLSchema#boolean">false</lla:mark>
  </rdf:Description>
  <rdf:Description rdf:about="http://data.llgc.org.uk/lla/id/mariner/22980-6483-2">
    <rdf:type rdf:resource="http://data.llgc.org.uk/lla/def#Mariner"/>
    <foaf:name>Edward Jones</foaf:name>
    <bio:Birth rdf:resource="http://data.llgc.org.uk/lla/id/event/birth/22980-6483-2"/>
  </rdf:Description>
  <rdf:Description rdf:about="http://data.llgc.org.uk/lla/id/event/birth/22980-6483-2">
    <rdf:type rdf:resource="http://purl.org/vocab/bio/0.1/Birth"/>
    <bio:place xml:lang="en">Aberystwyth</bio:place>
    <bio:agent rdf:resource="http://data.llgc.org.uk/lla/id/mariner/22980-6483-2"/>
  </rdf:Description>
  <rdf:Description rdf:about="http://data.llgc.org.uk/lla/id/event/joining/22980-6483-2">
    <rdf:type rdf:resource="http://data.llgc.org.uk/lla/def#ShipJoiningEvent"/>
    <dc:date rdf:datatype="http://www.w3.org/2001/XMLSchema#dateTime">1873-07-15</dc:date>
    <bio:place xml:lang="en">Llanelly</bio:place>
    <lla:hasCapacity xml:lang="en">Mate</lla:hasCapacity>
    <lla:involvesMariner rdf:resource="http://data.llgc.org.uk/lla/id/mariner/22980-6483-2"/>
    <lla:recordedIn rdf:resource="http://data.llgc.org.uk/lla/id/logbookentry/22980-6483-2"/>
    <lla:involvesShip rdf:resource="http://data.llgc.org.uk/lla/id/ship/22980"/>
  </rdf:Description>
  <rdf:Description rdf:about="http://data.llgc.org.uk/lla/id/event/leaving/22980-6483-2">
    <rdf:type rdf:resource="http://data.llgc.org.uk/lla/def#ShipLeavingEvent"/>
    <dc:date rdf:datatype="http://www.w3.org/2001/XMLSchema#dateTime">1873-11-20</dc:date>
    <bio:place xml:lang="en">Appledoe</bio:place>
    <lla:involvesMariner rdf:resource="http://data.llgc.org.uk/lla/id/mariner/22980-6483-2"/>
    <lla:recordedIn rdf:resource="http://data.llgc.org.uk/lla/id/logbookentry/22980-6483-2"/>
    <lla:involvesShip rdf:resource="http://data.llgc.org.uk/lla/id/ship/22980"/>
  </rdf:Description>
  <rdf:Description rdf:about="http://data.llgc.org.uk/lla/id/logbookentry/22980-6483-3">
    <rdf:type rdf:resource="http://data.llgc.org.uk/lla/def#LogbookEntry"/>
    <dcterms:isPartOf rdf:resource="http://data.llgc.org.uk/lla/id/logbook/22980-6483"/>
    <lla:logbookAge rdf:datatype="http://www.w3.org/2001/XMLSchema#int">22</lla:logbookAge>
    <lla:describesEvent rdf:resource="http://data.llgc.org.uk/lla/id/event/leaving/22980-6483-3-2"/>
    <lla:describesEvent rdf:resource="http://data.llgc.org.uk/lla/id/event/joining/22980-6483-3"/>
    <lla:describesEvent rdf:resource="http://data.llgc.org.uk/lla/id/event/leaving/22980-6483-3"/>
    <lla:reason xml:lang="en">Paid off</lla:reason>
    <lla:mark rdf:datatype="http://www.w3.org/2001/XMLSchema#boolean">true</lla:mark>
  </rdf:Description>
  <rdf:Description rdf:about="http://data.llgc.org.uk/lla/id/mariner/22980-6483-3">
    <rdf:type rdf:resource="http://data.llgc.org.uk/lla/def#Mariner"/>
    <foaf:name>John Jones</foaf:name>
    <bio:Birth rdf:resource="http://data.llgc.org.uk/lla/id/event/birth/22980-6483-3"/>
  </rdf:Description>
  <rdf:Description rdf:about="http://data.llgc.org.uk/lla/id/event/birth/22980-6483-3">
    <rdf:type rdf:resource="http://purl.org/vocab/bio/0.1/Birth"/>
    <bio:place xml:lang="en">Carmarthen</bio:place>
    <bio:agent rdf:resource="http://data.llgc.org.uk/lla/id/mariner/22980-6483-3"/>
  </rdf:Description>
  <rdf:Description rdf:about="http://data.llgc.org.uk/lla/id/event/leaving/22980-6483-3-2">
    <rdf:type rdf:resource="http://data.llgc.org.uk/lla/def#ShipLeavingEvent"/>
    <dc:date rdf:datatype="http://www.w3.org/2001/XMLSchema#dateTime">1873</dc:date>
    <lla:involvesMariner rdf:resource="http://data.llgc.org.uk/lla/id/mariner/22980-6483-3"/>
    <lla:recordedIn rdf:resource="http://data.llgc.org.uk/lla/id/logbookentry/22980-6483-3"/>
    <lla:involvesShip rdf:resource="http://data.llgc.org.uk/lla/id/ship/22980-6483-3"/>
  </rdf:Description>
  <rdf:Description rdf:about="http://data.llgc.org.uk/lla/id/ship/22980-6483-3">
    <rdf:type rdf:resource="http://data.llgc.org.uk/lla/def#Ship"/>
    <lla:hasHomePort xml:lang="en">Llanelly</lla:hasHomePort>
    <lla:mentionedIn rdf:resource="http://data.llgc.org.uk/lla/id/archivefile/64-8_vtls004625393"/>
    <lla:mentionedIn rdf:resource="http://data.llgc.org.uk/lla/id/logbook/22980-6483"/>
    <lla:mentionedIn rdf:resource="http://data.llgc.org.uk/lla/id/logbookentry/22980-6483-3"/>
    <rdfs:label xml:lang="en">Brothers</rdfs:label>
  </rdf:Description>
  <rdf:Description rdf:about="http://data.llgc.org.uk/lla/id/event/joining/22980-6483-3">
    <rdf:type rdf:resource="http://data.llgc.org.uk/lla/def#ShipJoiningEvent"/>
    <dc:date rdf:datatype="http://www.w3.org/2001/XMLSchema#dateTime">1873-07-15</dc:date>
    <bio:place xml:lang="en">Llanelly</bio:place>
    <lla:hasCapacity xml:lang="en">Boatswain</lla:hasCapacity>
    <lla:involvesMariner rdf:resource="http://data.llgc.org.uk/lla/id/mariner/22980-6483-3"/>
    <lla:recordedIn rdf:resource="http://data.llgc.org.uk/lla/id/logbookentry/22980-6483-3"/>
    <lla:involvesShip rdf:resource="http://data.llgc.org.uk/lla/id/ship/22980"/>
    <lla:hasPreviousIndividualEvent rdf:resource="http://data.llgc.org.uk/lla/id/event/leaving/22980-6483-3-2"/>
  </rdf:Description>
  <rdf:Description rdf:about="http://data.llgc.org.uk/lla/id/event/leaving/22980-6483-3">
    <rdf:type rdf:resource="http://data.llgc.org.uk/lla/def#ShipLeavingEvent"/>
    <dc:date rdf:datatype="http://www.w3.org/2001/XMLSchema#dateTime">1873-11-20</dc:date>
    <bio:place xml:lang="en">Appledoe</bio:place>
    <lla:involvesMariner rdf:resource="http://data.llgc.org.uk/lla/id/mariner/22980-6483-3"/>
    <lla:recordedIn rdf:resource="http://data.llgc.org.uk/lla/id/logbookentry/22980-6483-3"/>
    <lla:involvesShip rdf:resource="http://data.llgc.org.uk/lla/id/ship/22980"/>
  </rdf:Description>
  <rdf:Description rdf:about="http://data.llgc.org.uk/lla/id/logbookentry/22980-6483-4">
    <rdf:type rdf:resource="http://data.llgc.org.uk/lla/def#LogbookEntry"/>
    <dcterms:isPartOf rdf:resource="http://data.llgc.org.uk/lla/id/logbook/22980-6483"/>
    <lla:logbookAge rdf:datatype="http://www.w3.org/2001/XMLSchema#int">38</lla:logbookAge>
    <lla:describesEvent rdf:resource="http://data.llgc.org.uk/lla/id/event/leaving/22980-6483-4-2"/>
    <lla:describesEvent rdf:resource="http://data.llgc.org.uk/lla/id/event/joining/22980-6483-4"/>
    <lla:describesEvent rdf:resource="http://data.llgc.org.uk/lla/id/event/leaving/22980-6483-4"/>
    <lla:reason xml:lang="en">Paid off</lla:reason>
    <lla:mark rdf:datatype="http://www.w3.org/2001/XMLSchema#boolean">false</lla:mark>
  </rdf:Description>
  <rdf:Description rdf:about="http://data.llgc.org.uk/lla/id/mariner/22980-6483-4">
    <rdf:type rdf:resource="http://data.llgc.org.uk/lla/def#Mariner"/>
    <foaf:name>James Gilmore</foaf:name>
    <bio:Birth rdf:resource="http://data.llgc.org.uk/lla/id/event/birth/22980-6483-4"/>
  </rdf:Description>
  <rdf:Description rdf:about="http://data.llgc.org.uk/lla/id/event/birth/22980-6483-4">
    <rdf:type rdf:resource="http://purl.org/vocab/bio/0.1/Birth"/>
    <bio:place xml:lang="en">Llanelly</bio:place>
    <bio:agent rdf:resource="http://data.llgc.org.uk/lla/id/mariner/22980-6483-4"/>
  </rdf:Description>
  <rdf:Description rdf:about="http://data.llgc.org.uk/lla/id/event/leaving/22980-6483-4-2">
    <rdf:type rdf:resource="http://data.llgc.org.uk/lla/def#ShipLeavingEvent"/>
    <dc:date rdf:datatype="http://www.w3.org/2001/XMLSchema#dateTime">1873</dc:date>
    <lla:involvesMariner rdf:resource="http://data.llgc.org.uk/lla/id/mariner/22980-6483-4"/>
    <lla:recordedIn rdf:resource="http://data.llgc.org.uk/lla/id/logbookentry/22980-6483-4"/>
    <lla:involvesShip rdf:resource="http://data.llgc.org.uk/lla/id/ship/22980-6483-4"/>
  </rdf:Description>
  <rdf:Description rdf:about="http://data.llgc.org.uk/lla/id/ship/22980-6483-4">
    <rdf:type rdf:resource="http://data.llgc.org.uk/lla/def#Ship"/>
    <lla:hasHomePort xml:lang="en">Llanelly</lla:hasHomePort>
    <lla:mentionedIn rdf:resource="http://data.llgc.org.uk/lla/id/archivefile/64-8_vtls004625393"/>
    <lla:mentionedIn rdf:resource="http://data.llgc.org.uk/lla/id/logbook/22980-6483"/>
    <lla:mentionedIn rdf:resource="http://data.llgc.org.uk/lla/id/logbookentry/22980-6483-4"/>
    <rdfs:label xml:lang="en">Brothers</rdfs:label>
  </rdf:Description>
  <rdf:Description rdf:about="http://data.llgc.org.uk/lla/id/event/joining/22980-6483-4">
    <rdf:type rdf:resource="http://data.llgc.org.uk/lla/def#ShipJoiningEvent"/>
    <dc:date rdf:datatype="http://www.w3.org/2001/XMLSchema#dateTime">1873-07-15</dc:date>
    <bio:place xml:lang="en">Llanelly</bio:place>
    <lla:hasCapacity xml:lang="en">Cook &amp; Steward</lla:hasCapacity>
    <lla:involvesMariner rdf:resource="http://data.llgc.org.uk/lla/id/mariner/22980-6483-4"/>
    <lla:recordedIn rdf:resource="http://data.llgc.org.uk/lla/id/logbookentry/22980-6483-4"/>
    <lla:involvesShip rdf:resource="http://data.llgc.org.uk/lla/id/ship/22980"/>
    <lla:hasPreviousIndividualEvent rdf:resource="http://data.llgc.org.uk/lla/id/event/leaving/22980-6483-4-2"/>
  </rdf:Description>
  <rdf:Description rdf:about="http://data.llgc.org.uk/lla/id/event/leaving/22980-6483-4">
    <rdf:type rdf:resource="http://data.llgc.org.uk/lla/def#ShipLeavingEvent"/>
    <dc:date rdf:datatype="http://www.w3.org/2001/XMLSchema#dateTime">1873-11-20</dc:date>
    <bio:place xml:lang="en">Appledoe</bio:place>
    <lla:involvesMariner rdf:resource="http://data.llgc.org.uk/lla/id/mariner/22980-6483-4"/>
    <lla:recordedIn rdf:resource="http://data.llgc.org.uk/lla/id/logbookentry/22980-6483-4"/>
    <lla:involvesShip rdf:resource="http://data.llgc.org.uk/lla/id/ship/22980"/>
  </rdf:Description>
  <rdf:Description rdf:about="http://data.llgc.org.uk/lla/id/logbookentry/22980-6483-5">
    <rdf:type rdf:resource="http://data.llgc.org.uk/lla/def#LogbookEntry"/>
    <dcterms:isPartOf rdf:resource="http://data.llgc.org.uk/lla/id/logbook/22980-6483"/>
    <lla:logbookAge rdf:datatype="http://www.w3.org/2001/XMLSchema#int">34</lla:logbookAge>
    <lla:describesEvent rdf:resource="http://data.llgc.org.uk/lla/id/event/leaving/22980-6483-5-2"/>
    <lla:describesEvent rdf:resource="http://data.llgc.org.uk/lla/id/event/joining/22980-6483-5"/>
    <lla:describesEvent rdf:resource="http://data.llgc.org.uk/lla/id/event/leaving/22980-6483-5"/>
    <lla:reason xml:lang="en">Paid off</lla:reason>
    <lla:mark rdf:datatype="http://www.w3.org/2001/XMLSchema#boolean">true</lla:mark>
  </rdf:Description>
  <rdf:Description rdf:about="http://data.llgc.org.uk/lla/id/mariner/22980-6483-5">
    <rdf:type rdf:resource="http://data.llgc.org.uk/lla/def#Mariner"/>
    <foaf:name>Robert Davies</foaf:name>
    <bio:Birth rdf:resource="http://data.llgc.org.uk/lla/id/event/birth/22980-6483-5"/>
  </rdf:Description>
  <rdf:Description rdf:about="http://data.llgc.org.uk/lla/id/event/birth/22980-6483-5">
    <rdf:type rdf:resource="http://purl.org/vocab/bio/0.1/Birth"/>
    <bio:place xml:lang="en">St Clears</bio:place>
    <bio:agent rdf:resource="http://data.llgc.org.uk/lla/id/mariner/22980-6483-5"/>
  </rdf:Description>
  <rdf:Description rdf:about="http://data.llgc.org.uk/lla/id/event/leaving/22980-6483-5-2">
    <rdf:type rdf:resource="http://data.llgc.org.uk/lla/def#ShipLeavingEvent"/>
    <dc:date rdf:datatype="http://www.w3.org/2001/XMLSchema#dateTime">1873</dc:date>
    <lla:involvesMariner rdf:resource="http://data.llgc.org.uk/lla/id/mariner/22980-6483-5"/>
    <lla:recordedIn rdf:resource="http://data.llgc.org.uk/lla/id/logbookentry/22980-6483-5"/>
    <lla:involvesShip rdf:resource="http://data.llgc.org.uk/lla/id/ship/22980-6483-5"/>
  </rdf:Description>
  <rdf:Description rdf:about="http://data.llgc.org.uk/lla/id/ship/22980-6483-5">
    <rdf:type rdf:resource="http://data.llgc.org.uk/lla/def#Ship"/>
    <lla:hasHomePort xml:lang="en">Llanelly</lla:hasHomePort>
    <lla:mentionedIn rdf:resource="http://data.llgc.org.uk/lla/id/archivefile/64-8_vtls004625393"/>
    <lla:mentionedIn rdf:resource="http://data.llgc.org.uk/lla/id/logbook/22980-6483"/>
    <lla:mentionedIn rdf:resource="http://data.llgc.org.uk/lla/id/logbookentry/22980-6483-5"/>
    <rdfs:label xml:lang="en">Lord Rolle</rdfs:label>
  </rdf:Description>
  <rdf:Description rdf:about="http://data.llgc.org.uk/lla/id/event/joining/22980-6483-5">
    <rdf:type rdf:resource="http://data.llgc.org.uk/lla/def#ShipJoiningEvent"/>
    <dc:date rdf:datatype="http://www.w3.org/2001/XMLSchema#dateTime">1873-07-19</dc:date>
    <bio:place xml:lang="en">Llanelly</bio:place>
    <lla:hasCapacity xml:lang="en">Able Seaman</lla:hasCapacity>
    <lla:involvesMariner rdf:resource="http://data.llgc.org.uk/lla/id/mariner/22980-6483-5"/>
    <lla:recordedIn rdf:resource="http://data.llgc.org.uk/lla/id/logbookentry/22980-6483-5"/>
    <lla:involvesShip rdf:resource="http://data.llgc.org.uk/lla/id/ship/22980"/>
    <lla:hasPreviousIndividualEvent rdf:resource="http://data.llgc.org.uk/lla/id/event/leaving/22980-6483-5-2"/>
  </rdf:Description>
  <rdf:Description rdf:about="http://data.llgc.org.uk/lla/id/event/leaving/22980-6483-5">
    <rdf:type rdf:resource="http://data.llgc.org.uk/lla/def#ShipLeavingEvent"/>
    <dc:date rdf:datatype="http://www.w3.org/2001/XMLSchema#dateTime">1873-11-20</dc:date>
    <bio:place xml:lang="en">Appledoe</bio:place>
    <lla:involvesMariner rdf:resource="http://data.llgc.org.uk/lla/id/mariner/22980-6483-5"/>
    <lla:recordedIn rdf:resource="http://data.llgc.org.uk/lla/id/logbookentry/22980-6483-5"/>
    <lla:involvesShip rdf:resource="http://data.llgc.org.uk/lla/id/ship/22980"/>
  </rdf:Description>
  <rdf:Description rdf:about="http://data.llgc.org.uk/lla/id/logbookentry/22980-6483-6">
    <rdf:type rdf:resource="http://data.llgc.org.uk/lla/def#LogbookEntry"/>
    <dcterms:isPartOf rdf:resource="http://data.llgc.org.uk/lla/id/logbook/22980-6483"/>
    <lla:logbookAge rdf:datatype="http://www.w3.org/2001/XMLSchema#int">24</lla:logbookAge>
    <lla:describesEvent rdf:resource="http://data.llgc.org.uk/lla/id/event/leaving/22980-6483-6-2"/>
    <lla:describesEvent rdf:resource="http://data.llgc.org.uk/lla/id/event/joining/22980-6483-6"/>
    <lla:describesEvent rdf:resource="http://data.llgc.org.uk/lla/id/event/leaving/22980-6483-6"/>
    <lla:reason xml:lang="en">Deserted</lla:reason>
    <lla:mark rdf:datatype="http://www.w3.org/2001/XMLSchema#boolean">false</lla:mark>
  </rdf:Description>
  <rdf:Description rdf:about="http://data.llgc.org.uk/lla/id/mariner/22980-6483-6">
    <rdf:type rdf:resource="http://data.llgc.org.uk/lla/def#Mariner"/>
    <foaf:name>John Shilton</foaf:name>
    <bio:Birth rdf:resource="http://data.llgc.org.uk/lla/id/event/birth/22980-6483-6"/>
  </rdf:Description>
  <rdf:Description rdf:about="http://data.llgc.org.uk/lla/id/event/birth/22980-6483-6">
    <rdf:type rdf:resource="http://purl.org/vocab/bio/0.1/Birth"/>
    <bio:place xml:lang="en">Plymouth</bio:place>
    <bio:agent rdf:resource="http://data.llgc.org.uk/lla/id/mariner/22980-6483-6"/>
  </rdf:Description>
  <rdf:Description rdf:about="http://data.llgc.org.uk/lla/id/event/leaving/22980-6483-6-2">
    <rdf:type rdf:resource="http://data.llgc.org.uk/lla/def#ShipLeavingEvent"/>
    <dc:date rdf:datatype="http://www.w3.org/2001/XMLSchema#dateTime">1873</dc:date>
    <lla:involvesMariner rdf:resource="http://data.llgc.org.uk/lla/id/mariner/22980-6483-6"/>
    <lla:recordedIn rdf:resource="http://data.llgc.org.uk/lla/id/logbookentry/22980-6483-6"/>
    <lla:involvesShip rdf:resource="http://data.llgc.org.uk/lla/id/ship/22980-6483-6"/>
  </rdf:Description>
  <rdf:Description rdf:about="http://data.llgc.org.uk/lla/id/ship/22980-6483-6">
    <rdf:type rdf:resource="http://data.llgc.org.uk/lla/def#Ship"/>
    <lla:hasHomePort xml:lang="en">Llanelly</lla:hasHomePort>
    <lla:mentionedIn rdf:resource="http://data.llgc.org.uk/lla/id/archivefile/64-8_vtls004625393"/>
    <lla:mentionedIn rdf:resource="http://data.llgc.org.uk/lla/id/logbook/22980-6483"/>
    <lla:mentionedIn rdf:resource="http://data.llgc.org.uk/lla/id/logbookentry/22980-6483-6"/>
    <rdfs:label xml:lang="en">Catherine</rdfs:label>
  </rdf:Description>
  <rdf:Description rdf:about="http://data.llgc.org.uk/lla/id/event/joining/22980-6483-6">
    <rdf:type rdf:resource="http://data.llgc.org.uk/lla/def#ShipJoiningEvent"/>
    <dc:date rdf:datatype="http://www.w3.org/2001/XMLSchema#dateTime">1873-07-21</dc:date>
    <bio:place xml:lang="en">Llanelly</bio:place>
    <lla:hasCapacity xml:lang="en">Able Seaman</lla:hasCapacity>
    <lla:involvesMariner rdf:resource="http://data.llgc.org.uk/lla/id/mariner/22980-6483-6"/>
    <lla:recordedIn rdf:resource="http://data.llgc.org.uk/lla/id/logbookentry/22980-6483-6"/>
    <lla:involvesShip rdf:resource="http://data.llgc.org.uk/lla/id/ship/22980"/>
    <lla:hasPreviousIndividualEvent rdf:resource="http://data.llgc.org.uk/lla/id/event/leaving/22980-6483-6-2"/>
  </rdf:Description>
  <rdf:Description rdf:about="http://data.llgc.org.uk/lla/id/event/leaving/22980-6483-6">
    <rdf:type rdf:resource="http://data.llgc.org.uk/lla/def#ShipLeavingEvent"/>
    <dc:date rdf:datatype="http://www.w3.org/2001/XMLSchema#dateTime">1873-08-13</dc:date>
    <bio:place xml:lang="en">Yarmouth</bio:place>
    <lla:involvesMariner rdf:resource="http://data.llgc.org.uk/lla/id/mariner/22980-6483-6"/>
    <lla:recordedIn rdf:resource="http://data.llgc.org.uk/lla/id/logbookentry/22980-6483-6"/>
    <lla:involvesShip rdf:resource="http://data.llgc.org.uk/lla/id/ship/22980"/>
  </rdf:Description>
  <rdf:Description rdf:about="http://data.llgc.org.uk/lla/id/logbookentry/22980-6483-7">
    <rdf:type rdf:resource="http://data.llgc.org.uk/lla/def#LogbookEntry"/>
    <dcterms:isPartOf rdf:resource="http://data.llgc.org.uk/lla/id/logbook/22980-6483"/>
    <lla:logbookAge rdf:datatype="http://www.w3.org/2001/XMLSchema#int">32</lla:logbookAge>
    <lla:describesEvent rdf:resource="http://data.llgc.org.uk/lla/id/event/leaving/22980-6483-7-2"/>
    <lla:describesEvent rdf:resource="http://data.llgc.org.uk/lla/id/event/joining/22980-6483-7"/>
    <lla:describesEvent rdf:resource="http://data.llgc.org.uk/lla/id/event/leaving/22980-6483-7"/>
    <lla:reason xml:lang="en">Paid off</lla:reason>
    <lla:mark rdf:datatype="http://www.w3.org/2001/XMLSchema#boolean">false</lla:mark>
  </rdf:Description>
  <rdf:Description rdf:about="http://data.llgc.org.uk/lla/id/mariner/22980-6483-7">
    <rdf:type rdf:resource="http://data.llgc.org.uk/lla/def#Mariner"/>
    <foaf:name>Daniel Rees</foaf:name>
    <bio:Birth rdf:resource="http://data.llgc.org.uk/lla/id/event/birth/22980-6483-7"/>
  </rdf:Description>
  <rdf:Description rdf:about="http://data.llgc.org.uk/lla/id/event/birth/22980-6483-7">
    <rdf:type rdf:resource="http://purl.org/vocab/bio/0.1/Birth"/>
    <bio:place xml:lang="en">Llanelly</bio:place>
    <bio:agent rdf:resource="http://data.llgc.org.uk/lla/id/mariner/22980-6483-7"/>
  </rdf:Description>
  <rdf:Description rdf:about="http://data.llgc.org.uk/lla/id/event/leaving/22980-6483-7-2">
    <rdf:type rdf:resource="http://data.llgc.org.uk/lla/def#ShipLeavingEvent"/>
    <dc:date rdf:datatype="http://www.w3.org/2001/XMLSchema#dateTime">1873</dc:date>
    <lla:involvesMariner rdf:resource="http://data.llgc.org.uk/lla/id/mariner/22980-6483-7"/>
    <lla:recordedIn rdf:resource="http://data.llgc.org.uk/lla/id/logbookentry/22980-6483-7"/>
    <lla:involvesShip rdf:resource="http://data.llgc.org.uk/lla/id/ship/22980-6483-7"/>
  </rdf:Description>
  <rdf:Description rdf:about="http://data.llgc.org.uk/lla/id/ship/22980-6483-7">
    <rdf:type rdf:resource="http://data.llgc.org.uk/lla/def#Ship"/>
    <lla:hasHomePort xml:lang="en">Llanelly</lla:hasHomePort>
    <lla:mentionedIn rdf:resource="http://data.llgc.org.uk/lla/id/archivefile/64-8_vtls004625393"/>
    <lla:mentionedIn rdf:resource="http://data.llgc.org.uk/lla/id/logbook/22980-6483"/>
    <lla:mentionedIn rdf:resource="http://data.llgc.org.uk/lla/id/logbookentry/22980-6483-7"/>
    <rdfs:label xml:lang="en">Osprey</rdfs:label>
  </rdf:Description>
  <rdf:Description rdf:about="http://data.llgc.org.uk/lla/id/event/joining/22980-6483-7">
    <rdf:type rdf:resource="http://data.llgc.org.uk/lla/def#ShipJoiningEvent"/>
    <dc:date rdf:datatype="http://www.w3.org/2001/XMLSchema#dateTime">1873-07-21</dc:date>
    <bio:place xml:lang="en">Llanelly</bio:place>
    <lla:hasCapacity xml:lang="en">Able Seaman</lla:hasCapacity>
    <lla:involvesMariner rdf:resource="http://data.llgc.org.uk/lla/id/mariner/22980-6483-7"/>
    <lla:recordedIn rdf:resource="http://data.llgc.org.uk/lla/id/logbookentry/22980-6483-7"/>
    <lla:involvesShip rdf:resource="http://data.llgc.org.uk/lla/id/ship/22980"/>
    <lla:hasPreviousIndividualEvent rdf:resource="http://data.llgc.org.uk/lla/id/event/leaving/22980-6483-7-2"/>
  </rdf:Description>
  <rdf:Description rdf:about="http://data.llgc.org.uk/lla/id/event/leaving/22980-6483-7">
    <rdf:type rdf:resource="http://data.llgc.org.uk/lla/def#ShipLeavingEvent"/>
    <dc:date rdf:datatype="http://www.w3.org/2001/XMLSchema#dateTime">1873-11-20</dc:date>
    <bio:place xml:lang="en">Appledoe</bio:place>
    <lla:involvesMariner rdf:resource="http://data.llgc.org.uk/lla/id/mariner/22980-6483-7"/>
    <lla:recordedIn rdf:resource="http://data.llgc.org.uk/lla/id/logbookentry/22980-6483-7"/>
    <lla:involvesShip rdf:resource="http://data.llgc.org.uk/lla/id/ship/22980"/>
  </rdf:Description>
  <rdf:Description rdf:about="http://data.llgc.org.uk/lla/id/logbookentry/22980-6483-8">
    <rdf:type rdf:resource="http://data.llgc.org.uk/lla/def#LogbookEntry"/>
    <dcterms:isPartOf rdf:resource="http://data.llgc.org.uk/lla/id/logbook/22980-6483"/>
    <lla:logbookAge rdf:datatype="http://www.w3.org/2001/XMLSchema#int">18</lla:logbookAge>
    <lla:describesEvent rdf:resource="http://data.llgc.org.uk/lla/id/event/leaving/22980-6483-8-2"/>
    <lla:describesEvent rdf:resource="http://data.llgc.org.uk/lla/id/event/joining/22980-6483-8"/>
    <lla:describesEvent rdf:resource="http://data.llgc.org.uk/lla/id/event/leaving/22980-6483-8"/>
    <lla:reason xml:lang="en">Paid off</lla:reason>
    <lla:mark rdf:datatype="http://www.w3.org/2001/XMLSchema#boolean">false</lla:mark>
  </rdf:Description>
  <rdf:Description rdf:about="http://data.llgc.org.uk/lla/id/mariner/22980-6483-8">
    <rdf:type rdf:resource="http://data.llgc.org.uk/lla/def#Mariner"/>
    <foaf:name>William George</foaf:name>
    <bio:Birth rdf:resource="http://data.llgc.org.uk/lla/id/event/birth/22980-6483-8"/>
  </rdf:Description>
  <rdf:Description rdf:about="http://data.llgc.org.uk/lla/id/event/birth/22980-6483-8">
    <rdf:type rdf:resource="http://purl.org/vocab/bio/0.1/Birth"/>
    <bio:place xml:lang="en">Fishguard</bio:place>
    <bio:agent rdf:resource="http://data.llgc.org.uk/lla/id/mariner/22980-6483-8"/>
  </rdf:Description>
  <rdf:Description rdf:about="http://data.llgc.org.uk/lla/id/event/leaving/22980-6483-8-2">
    <rdf:type rdf:resource="http://data.llgc.org.uk/lla/def#ShipLeavingEvent"/>
    <dc:date rdf:datatype="http://www.w3.org/2001/XMLSchema#dateTime">1873</dc:date>
    <lla:involvesMariner rdf:resource="http://data.llgc.org.uk/lla/id/mariner/22980-6483-8"/>
    <lla:recordedIn rdf:resource="http://data.llgc.org.uk/lla/id/logbookentry/22980-6483-8"/>
    <lla:involvesShip rdf:resource="http://data.llgc.org.uk/lla/id/ship/22980-6483-8"/>
  </rdf:Description>
  <rdf:Description rdf:about="http://data.llgc.org.uk/lla/id/ship/22980-6483-8">
    <rdf:type rdf:resource="http://data.llgc.org.uk/lla/def#Ship"/>
    <lla:hasHomePort xml:lang="en">Llanelly</lla:hasHomePort>
    <lla:mentionedIn rdf:resource="http://data.llgc.org.uk/lla/id/archivefile/64-8_vtls004625393"/>
    <lla:mentionedIn rdf:resource="http://data.llgc.org.uk/lla/id/logbook/22980-6483"/>
    <lla:mentionedIn rdf:resource="http://data.llgc.org.uk/lla/id/logbookentry/22980-6483-8"/>
    <rdfs:label xml:lang="en">Grafton</rdfs:label>
  </rdf:Description>
  <rdf:Description rdf:about="http://data.llgc.org.uk/lla/id/event/joining/22980-6483-8">
    <rdf:type rdf:resource="http://data.llgc.org.uk/lla/def#ShipJoiningEvent"/>
    <dc:date rdf:datatype="http://www.w3.org/2001/XMLSchema#dateTime">1873-07-12</dc:date>
    <bio:place xml:lang="en">Llanelly</bio:place>
    <lla:hasCapacity xml:lang="en">Ordinary Seaman</lla:hasCapacity>
    <lla:involvesMariner rdf:resource="http://data.llgc.org.uk/lla/id/mariner/22980-6483-8"/>
    <lla:recordedIn rdf:resource="http://data.llgc.org.uk/lla/id/logbookentry/22980-6483-8"/>
    <lla:involvesShip rdf:resource="http://data.llgc.org.uk/lla/id/ship/22980"/>
    <lla:hasPreviousIndividualEvent rdf:resource="http://data.llgc.org.uk/lla/id/event/leaving/22980-6483-8-2"/>
  </rdf:Description>
  <rdf:Description rdf:about="http://data.llgc.org.uk/lla/id/event/leaving/22980-6483-8">
    <rdf:type rdf:resource="http://data.llgc.org.uk/lla/def#ShipLeavingEvent"/>
    <dc:date rdf:datatype="http://www.w3.org/2001/XMLSchema#dateTime">1873-11-20</dc:date>
    <bio:place xml:lang="en">Appledoe</bio:place>
    <lla:involvesMariner rdf:resource="http://data.llgc.org.uk/lla/id/mariner/22980-6483-8"/>
    <lla:recordedIn rdf:resource="http://data.llgc.org.uk/lla/id/logbookentry/22980-6483-8"/>
    <lla:involvesShip rdf:resource="http://data.llgc.org.uk/lla/id/ship/22980"/>
  </rdf:Description>
  <rdf:Description rdf:about="http://data.llgc.org.uk/lla/id/logbookentry/22980-6483-9">
    <rdf:type rdf:resource="http://data.llgc.org.uk/lla/def#LogbookEntry"/>
    <dcterms:isPartOf rdf:resource="http://data.llgc.org.uk/lla/id/logbook/22980-6483"/>
    <lla:logbookAge rdf:datatype="http://www.w3.org/2001/XMLSchema#int">21</lla:logbookAge>
    <lla:describesEvent rdf:resource="http://data.llgc.org.uk/lla/id/event/leaving/22980-6483-9-2"/>
    <lla:describesEvent rdf:resource="http://data.llgc.org.uk/lla/id/event/joining/22980-6483-9"/>
    <lla:describesEvent rdf:resource="http://data.llgc.org.uk/lla/id/event/leaving/22980-6483-9"/>
    <lla:reason xml:lang="en">Paid off</lla:reason>
    <lla:mark rdf:datatype="http://www.w3.org/2001/XMLSchema#boolean">false</lla:mark>
  </rdf:Description>
  <rdf:Description rdf:about="http://data.llgc.org.uk/lla/id/mariner/22980-6483-9">
    <rdf:type rdf:resource="http://data.llgc.org.uk/lla/def#Mariner"/>
    <foaf:name>Walter Murphy</foaf:name>
    <bio:Birth rdf:resource="http://data.llgc.org.uk/lla/id/event/birth/22980-6483-9"/>
  </rdf:Description>
  <rdf:Description rdf:about="http://data.llgc.org.uk/lla/id/event/birth/22980-6483-9">
    <rdf:type rdf:resource="http://purl.org/vocab/bio/0.1/Birth"/>
    <bio:place xml:lang="en">London</bio:place>
    <bio:agent rdf:resource="http://data.llgc.org.uk/lla/id/mariner/22980-6483-9"/>
  </rdf:Description>
  <rdf:Description rdf:about="http://data.llgc.org.uk/lla/id/event/leaving/22980-6483-9-2">
    <rdf:type rdf:resource="http://data.llgc.org.uk/lla/def#ShipLeavingEvent"/>
    <dc:date rdf:datatype="http://www.w3.org/2001/XMLSchema#dateTime">1873</dc:date>
    <lla:involvesMariner rdf:resource="http://data.llgc.org.uk/lla/id/mariner/22980-6483-9"/>
    <lla:recordedIn rdf:resource="http://data.llgc.org.uk/lla/id/logbookentry/22980-6483-9"/>
    <lla:involvesShip rdf:resource="http://data.llgc.org.uk/lla/id/ship/22980-6483-9"/>
  </rdf:Description>
  <rdf:Description rdf:about="http://data.llgc.org.uk/lla/id/ship/22980-6483-9">
    <rdf:type rdf:resource="http://data.llgc.org.uk/lla/def#Ship"/>
    <lla:hasHomePort xml:lang="en">Sweden</lla:hasHomePort>
    <lla:mentionedIn rdf:resource="http://data.llgc.org.uk/lla/id/archivefile/64-8_vtls004625393"/>
    <lla:mentionedIn rdf:resource="http://data.llgc.org.uk/lla/id/logbook/22980-6483"/>
    <lla:mentionedIn rdf:resource="http://data.llgc.org.uk/lla/id/logbookentry/22980-6483-9"/>
    <rdfs:label xml:lang="en">[Tris]</rdfs:label>
  </rdf:Description>
  <rdf:Description rdf:about="http://data.llgc.org.uk/lla/id/event/joining/22980-6483-9">
    <rdf:type rdf:resource="http://data.llgc.org.uk/lla/def#ShipJoiningEvent"/>
    <dc:date rdf:datatype="http://www.w3.org/2001/XMLSchema#dateTime">1873-09-27</dc:date>
    <bio:place xml:lang="en">London</bio:place>
    <lla:hasCapacity xml:lang="en">Able Seaman</lla:hasCapacity>
    <lla:involvesMariner rdf:resource="http://data.llgc.org.uk/lla/id/mariner/22980-6483-9"/>
    <lla:recordedIn rdf:resource="http://data.llgc.org.uk/lla/id/logbookentry/22980-6483-9"/>
    <lla:involvesShip rdf:resource="http://data.llgc.org.uk/lla/id/ship/22980"/>
    <lla:hasPreviousIndividualEvent rdf:resource="http://data.llgc.org.uk/lla/id/event/leaving/22980-6483-9-2"/>
  </rdf:Description>
  <rdf:Description rdf:about="http://data.llgc.org.uk/lla/id/event/leaving/22980-6483-9">
    <rdf:type rdf:resource="http://data.llgc.org.uk/lla/def#ShipLeavingEvent"/>
    <dc:date rdf:datatype="http://www.w3.org/2001/XMLSchema#dateTime">1873-11-20</dc:date>
    <bio:place xml:lang="en">Appledoe</bio:place>
    <lla:involvesMariner rdf:resource="http://data.llgc.org.uk/lla/id/mariner/22980-6483-9"/>
    <lla:recordedIn rdf:resource="http://data.llgc.org.uk/lla/id/logbookentry/22980-6483-9"/>
    <lla:involvesShip rdf:resource="http://data.llgc.org.uk/lla/id/ship/22980"/>
  </rdf:Description>
</rdf:RDF>
